Workbook
Name b: Insumos!$XAO$1

Sheet Vituca Cakes
B3: N° | C3: Fecha | D3: Año | E3: Mes | F3: Cliente | G3: N° Artículo | H3: Categoría | I3: Detalle | J3: Unidades | K3: Costo Total | L3: Venta Total | M3: Ganancia | N3: Metodo de PAGO
B4: 1 | C4: 44100 | D4: =IF(C4="","",YEAR(C4)) -> 2020 | E4: =IF(C4="","",MONTH(C4)) -> 9 | F4: Agus Paramidani | G4: 2 | H4: macarrons | I4: sabores surtidos | J4: 5 | K4: 147 | L4: 350 | M4: =L4-K4 -> 203
B5: =B4+1 -> 2 | C5: 44101 | D5: =IF(C5="","",YEAR(C5)) -> 2020 | E5: =IF(C5="","",MONTH(C5)) -> 9 | F5: Lucas Capello | G5: 2 | H5: macarrons | I5: sabores surtidos | J5: 5 | K5: 147 | L5: 350 | M5: =L5-K5 -> 203
B6: =B5+1 -> 3 | C6: 44102 | D6: =IF(C6="","",YEAR(C6)) -> 2020 | E6: =IF(C6="","",MONTH(C6)) -> 9 | F6: Ornella D´estefano | H6: torta brownie | I6: frutos rojos tamaño 24cm | J6: 1 | K6: 409 | L6: 1000 | M6: =L6-K6 -> 591
B7: =B6+1 -> 4 | C7: 44102 | D7: =IF(C7="","",YEAR(C7)) -> 2020 | E7: =IF(C7="","",MONTH(C7)) -> 9 | F7: Leidymar | H7: desayuno | I7: 1 jugo baggio 1 mini budin limon1 mini budin marmolado, 4 cookies de chips de chocolate, 4 cookies en forma de flor, 1 porcion de brownie, 1 chocolatada, mantelito | J7: 1 | L7: 1200 | M7: =L7-K7 -> 1200
B8: =B7+1 -> 5 | C8: 44103 | D8: =IF(C8="","",YEAR(C8)) -> 2020 | E8: =IF(C8="","",MONTH(C8)) -> 9 | F8: Ornella D´estefano | H8: torta brownie | I8: frutos rojos tamaño 24cm | J8: 2 | K8: 818 | L8: 2200 | M8: =L8-K8 -> 1382
B9: =B8+1 -> 6 | C9: 44104 | D9: =IF(C9="","",YEAR(C9)) -> 2020 | E9: =IF(C9="","",MONTH(C9)) -> 9 | F9: Maxi Cardoso | H9: macarrons | I9: 4 chocolate blanco 2 limon 2 frutilla y 2 chocolate | J9: 10 | K9: 294 | L9: 600 | M9: =L9-K9 -> 306
B10: =B9+1 -> 7 | C10: 44107 | D10: =IF(C10="","",YEAR(C10)) -> 2020 | E10: =IF(C10="","",MONTH(C10)) -> 10 | F10: Carolina Marsaudon | H10: torta brownie 24 cm | I10: ddl, crema, frutillas y chocolates | J10: 1 | K10: 450 | L10: 1100 | M10: =L10-K10 -> 650
B11: =B10+1 -> 8 | C11: 44107 | D11: =IF(C11="","",YEAR(C11)) -> 2020 | E11: =IF(C11="","",MONTH(C11)) -> 10 | F11: Gaby Morales | H11: Lemon Pie | I11: 20 cm | J11: 1 | K11: 300 | L11: 850 | M11: =L11-K11 -> 550
B12: =B11+1 -> 9 | C12: 44107 | D12: =IF(C12="","",YEAR(C12)) -> 2020 | E12: =IF(C12="","",MONTH(C12)) -> 10 | F12: Gaby Morales | H12: torta brownie | I12: Frutos rojos tamaño 20cm | J12: 1 | K12: 288 | L12: 950 | M12: =L12-K12 -> 662
B13: =B12+1 -> 10 | C13: 44107 | D13: =IF(C13="","",YEAR(C13)) -> 2020 | E13: =IF(C13="","",MONTH(C13)) -> 10 | F13: Agus Perez Romero | H13: Chipa | I13: 1/4 GANADOR! | J13: 1 | K13: 109 | L13: 0 | M13: =L13-K13 -> -109
B14: =B13+1 -> 11 | C14: 44107 | D14: =IF(C14="","",YEAR(C14)) -> 2020 | E14: =IF(C14="","",MONTH(C14)) -> 10 | F14: Priscila Pacifisco | H14: Chipa | I14: 0.5 | J14: 1 | K14: 218 | L14: 360 | M14: =L14-K14 -> 142
B15: =B14+1 -> 12 | C15: 44107 | D15: =IF(C15="","",YEAR(C15)) -> 2020 | E15: =IF(C15="","",MONTH(C15)) -> 10 | F15: Caro Ponti | H15: Pan Trenzado | I15: con semillas | J15: 2 | K15: 72 | L15: 160 | M15: =L15-K15 -> 88
B16: =B15+1 -> 13 | C16: 44107 | D16: =IF(C16="","",YEAR(C16)) -> 2020 | E16: =IF(C16="","",MONTH(C16)) -> 10 | F16: Caro Ponti | H16: Chipa | I16: 0.25 | J16: 1 | K16: 109 | L16: 180 | M16: =L16-K16 -> 71
B17: =B16+1 -> 14 | C17: 44107 | D17: =IF(C17="","",YEAR(C17)) -> 2020 | E17: =IF(C17="","",MONTH(C17)) -> 10 | F17: Estefi Garbarino | H17: Chipa | I17: 0.25 | J17: 1 | K17: 109 | L17: 180 | M17: =L17-K17 -> 71 | N17: PAGO, TRANSFERENCIA
B18: =B17+1 -> 15 | C18: 44108 | D18: =IF(C18="","",YEAR(C18)) -> 2020 | E18: =IF(C18="","",MONTH(C18)) -> 10 | F18: Flor Daboum | H18: macarrons | I18: surtidos blancos y rosas | J18: 5 | K18: 147 | L18: 150 | M18: =L18-K18 -> 3
B19: =B18+1 -> 16 | C19: 44108 | D19: =IF(C19="","",YEAR(C19)) -> 2020 | E19: =IF(C19="","",MONTH(C19)) -> 10 | F19: Flor Vitola | H19: desayuno PLIM PLIM | I19: Baggio, globo, 2 muffins buttercream, 2 cookies glase, 4 cookies chupetin | J19: 1 | K19: 365 | L19: 850 | M19: =L19-K19 -> 485
B20: =B19+1 -> 17 | C20: 44108 | D20: =IF(C20="","",YEAR(C20)) -> 2020 | E20: =IF(C20="","",MONTH(C20)) -> 10 | F20: Flor Vitola | H20: Desayuno FORTNITE | I20: igual que plim plim pero de fortnite | J20: 1 | K20: 365 | L20: 850 | M20: =L20-K20 -> 485
B21: =B20+1 -> 18 | C21: 44108 | D21: =IF(C21="","",YEAR(C21)) -> 2020 | E21: =IF(C21="","",MONTH(C21)) -> 10 | F21: Vicky Minoli | H21: macarrons + tarta manzana | I21: M 3 Limon y 3 Frutilla T: 24 CM | J21: 6 + 1 | K21: 594 | L21: 1200 | M21: =L21-K21 -> 606
B22: =B21+1 -> 19 | C22: 44109 | D22: =IF(C22="","",YEAR(C22)) -> 2020 | E22: =IF(C22="","",MONTH(C22)) -> 10 | F22: Daniela Ares | H22: torta bizcochuelo 50 | I22: dulce de leche-crema y merengue / rosa y dorado | J22: 1 | L22: 3400 | M22: =L22-K22 -> 3400
B23: =B22+1 -> 20 | C23: 44111 | D23: =IF(C23="","",YEAR(C23)) -> 2020 | E23: =IF(C23="","",MONTH(C23)) -> 10 | F23: Lorena Cossovich | H23: torta ferrero rocher + macarrons | I23: 10 macarrons Surtidos, torta 20 cm | J23: 10+ 1 | K23: 1069 | L23: 2350 | M23: =L23-K23 -> 1281
B24: =B23+1 -> 21 | C24: 44113 | D24: =IF(C24="","",YEAR(C24)) -> 2020 | E24: =IF(C24="","",MONTH(C24)) -> 10 | F24: Roxana Solis | H24: Torta Piñata | I24: tematica: DINOSAURIO / ELLOS ME DAN LAS GOLOSINAS | J24: 1 | K24: 322 | L24: 1200 | M24: =L24-K24 -> 878
B25: 22 | C25: 44121 | D25: =IF(C25="","",YEAR(C25)) -> 2020 | E25: =IF(C25="","",MONTH(C25)) -> 10 | F25: Jaqueline | H25: tarta de frutillas y tarta de durazno | I25: 24 cm con pastelera, retira! | J25: 2 | K25: 705 | L25: 1630 | M25: =L25-K25 -> 925 | N25: PAGO SEÑA
B26: 23 | C26: 44122 | D26: =IF(C26="","",YEAR(C26)) -> 2020 | E26: =IF(C26="","",MONTH(C26)) -> 10 | F26: Roxana Solis | H26: Torta Piñata | I26: tematica: TIC TOC / ELLOS ME DAN LAS GOLOSINAS | J26: 1 | K26: 322 | L26: 1200 | M26: =L26-K26 -> 878 | N26: PAGO, TRANSFERENCIA
B27: =B26+1 -> 24 | C27: 44122 | D27: =IF(C27="","",YEAR(C27)) -> 2020 | E27: =IF(C27="","",MONTH(C27)) -> 10 | F27: ezequiel | H27: DIA DE LA MADRE | I27: OPCION 1 | J27: 1 | K27: 787 | L27: 1400 | M27: =L27-K27 -> 613 | N27: PAGO, MERCADO PAGO
B28: =B27+1 -> 25 | C28: 44122 | D28: =IF(C28="","",YEAR(C28)) -> 2020 | E28: =IF(C28="","",MONTH(C28)) -> 10 | F28: Miriam | H28: DIA DE LA MADRE | I28: OPCION 1 + 6 MARPLATENSE + 2 CUCHARAS | J28: 1 | K28: 900 | L28: 1350 | M28: =L28-K28 -> 450 | N28: EFECTIVO
B29: =B28+1 -> 26 | C29: 44122 | D29: =IF(C29="","",YEAR(C29)) -> 2020 | E29: =IF(C29="","",MONTH(C29)) -> 10 | F29: Meco | H29: DIA DE LA MADRE | I29: OPCION 2 | J29: 1 | K29: 787 | L29: 1000 | M29: =L29-K29 -> 213
B30: =B29+1 -> 27 | C30: 44122 | D30: =IF(C30="","",YEAR(C30)) -> 2020 | E30: =IF(C30="","",MONTH(C30)) -> 10 | F30: Cora | H30: DIA DE LA MADRE | I30: OPCION 1 | J30: 2 | K30: 787 | L30: 1600 | M30: =L30-K30 -> 813
B31: =B30+1 -> 28 | C31: 44122 | D31: =IF(C31="","",YEAR(C31)) -> 2020 | E31: =IF(C31="","",MONTH(C31)) -> 10 | F31: Adrian Lopresto | H31: DIA DE LA MADRE | I31: OPCION 2 | J31: 1 | K31: 787 | L31: 1600 | M31: =L31-K31 -> 813 | N31: PAGO, EFECTIVO
B32: =B31+1 -> 29 | C32: 44122 | D32: =IF(C32="","",YEAR(C32)) -> 2020 | E32: =IF(C32="","",MONTH(C32)) -> 10 | F32: Caterina | H32: DIA DE LA MADRE | I32: OPCION 1 | J32: 1 | K32: 787 | L32: 1200 | M32: =L32-K32 -> 413 | N32: PAGO, MERCADO PAGO
B33: =B32+1 -> 30 | C33: 44122 | D33: =IF(C33="","",YEAR(C33)) -> 2020 | E33: =IF(C33="","",MONTH(C33)) -> 10 | F33: Erica | H33: DIA DE LA MADRE | I33: OPCION 1 | J33: 1 | K33: 787 | L33: 1200 | M33: =L33-K33 -> 413 | N33: EFECTIVO
B34: =B33+1 -> 31 | C34: 44122 | D34: =IF(C34="","",YEAR(C34)) -> 2020 | E34: =IF(C34="","",MONTH(C34)) -> 10 | F34: Laura Parroquia | H34: DIA DE LA MADRE | I34: OPCION 2 | J34: 1 | K34: 787 | L34: 1600 | M34: =L34-K34 -> 813 | N34: EFECTIVO
B35: =B34+1 -> 32 | C35: 44122 | D35: =IF(C35="","",YEAR(C35)) -> 2020 | E35: =IF(C35="","",MONTH(C35)) -> 10 | F35: Julian Petruzzelli | H35: DIA DE LA MADRE | I35: OPCION 2 | J35: 1 | K35: 787 | L35: 1600 | M35: =L35-K35 -> 813
B36: =B35+1 -> 33 | C36: 44122 | D36: =IF(C36="","",YEAR(C36)) -> 2020 | E36: =IF(C36="","",MONTH(C36)) -> 10 | F36: Flor Vitola | H36: DIA DE LA MADRE | I36: OPCION 2 | J36: 1 | K36: 787 | L36: 1600 | M36: =L36-K36 -> 813 | N36: PAGO, TRANSFERENCIA
B37: =B36+1 -> 34 | C37: 44122 | D37: =IF(C37="","",YEAR(C37)) -> 2020 | E37: =IF(C37="","",MONTH(C37)) -> 10 | F37: Nicole Avila | H37: DIA DE LA MADRE | I37: OPCION 1 | J37: 1 | K37: 787 | L37: 1200 | M37: =L37-K37 -> 413 | N37: PAGO, MERCADO PAGO
B38: =B37+1 -> 35 | C38: 44122 | D38: =IF(C38="","",YEAR(C38)) -> 2020 | E38: =IF(C38="","",MONTH(C38)) -> 10 | F38: Nicolas Ferros | H38: DIA DE LA MADRE | I38: OPCION 2 | J38: 1 | K38: 787 | L38: 1700 | M38: =L38-K38 -> 913 | N38: PAGO, MERCADO PAGO
B39: =B38+1 -> 36 | C39: 44124 | D39: =IF(C39="","",YEAR(C39)) -> 2020 | E39: =IF(C39="","",MONTH(C39)) -> 10 | F39: MARISEL | H39: DESAYUNO | I39: 2 macarrons choco b y choco, 4 maicena 1 brownie y 4 cookies feliz cumple | J39: 1 | K39: 787 | L39: 1100 | M39: =L39-K39 -> 313 | N39: PAGO, TRANSFERENCIA
B40: =B39+1 -> 37 | C40: 44125 | D40: =IF(C40="","",YEAR(C40)) -> 2020 | E40: =IF(C40="","",MONTH(C40)) -> 10 | F40: MARISEL | H40: DESAYUNO | I40: 2 macarrons choco b y choco, 4 maicena 1 brownie y 4 cookies feliz cumple y globo corazon rosa | J40: 1 | K40: 500 | L40: 1200 | M40: =L40-K40 -> 700 | N40: PAGO, TRANSFERENCIA
B41: =B40+1 -> 38 | C41: 44127 | D41: =IF(C41="","",YEAR(C41)) -> 2020 | E41: =IF(C41="","",MONTH(C41)) -> 10 | F41: NORBERTO | H41: DESAYUNOS | I41: 2 Cookies, 2 budin de chocolate, baggio, taza. Bandeja | J41: 108 | K41: =329*108 -> 35532 | L41: 51840 | M41: =L41-K41 -> 16308 | N41: pago 35.000
B42: 39 | C42: 44135 | D42: =IF(C42="","",YEAR(C42)) -> 2020 | E42: =IF(C42="","",MONTH(C42)) -> 10 | F42: Silvia Lois | H42: HALOWEEN | I42: 12 COOKIES 12 MACARRONS (CHO. CHO B) 6 FANTASMITAS | J42: 1 | K42: 352 | L42: 1870 | M42: =L42-K42 -> 1518 | N42: EFECTIVO
B43: 40 | C43: 44135 | D43: =IF(C43="","",YEAR(C43)) -> 2020 | E43: =IF(C43="","",MONTH(C43)) -> 10 | F43: Lucas Capello | H43: HALLOWEEN | I43: OPCION 1 | J43: 1 | K43: 352 | L43: 1200 | M43: =L43-K43 -> 848
B44: 41 | C44: 44135 | D44: =IF(C44="","",YEAR(C44)) -> 2020 | E44: =IF(C44="","",MONTH(C44)) -> 10 | F44: Gaby Morales | H44: HALLOWEEN | I44: OPCION | K44: 352 | L44: 1200 | M44: =L44-K44 -> 848
B45: 42 | C45: 44135 | D45: =IF(C45="","",YEAR(C45)) -> 2020 | E45: =IF(C45="","",MONTH(C45)) -> 10 | F45: ALDU RIQUELME | H45: HALLOWEEN | I45: OPCION 2 | J45: 1 | K45: 352 | L45: 900 | M45: =L45-K45 -> 548 | N45: EFECTIVO
B46: 43 | C46: 44136 | D46: =IF(C46="","",YEAR(C46)) -> 2020 | E46: =IF(C46="","",MONTH(C46)) -> 11 | F46: CAMILA CLARK | H46: TORTA BALCARCE | I46: 20 cm | J46: 1 | K46: 400 | L46: 1000 | M46: =L46-K46 -> 600
B47: =B46+1 -> 44 | C47: 44149 | D47: =IF(C47="","",YEAR(C47)) -> 2020 | E47: =IF(C47="","",MONTH(C47)) -> 11 | F47: ALDANA DASSO | H47: DESAYUNO | I47: OPCION 2 | J47: 1 | K47: 600 | L47: 1800 | M47: =L47-K47 -> 1200 | N47: TRASFERENCIA
B48: =B47+1 -> 45 | C48: 44149 | D48: =IF(C48="","",YEAR(C48)) -> 2020 | E48: =IF(C48="","",MONTH(C48)) -> 11 | F48: GERALDE | H48: BUDIN LIMON | I48: 1/2 KG | J48: 1 | K48: 220 | L48: 450 | M48: =L48-K48 -> 230 | N48: TRASFERENCIA
B49: 46 | C49: 44149 | D49: =IF(C49="","",YEAR(C49)) -> 2020 | E49: =IF(C49="","",MONTH(C49)) -> 11 | F49: VALERIA CARLONE | H49: 15 MACARRONS | J49: 15 | K49: 455 | L49: 1000 | M49: =L49-K49 -> 545 | N49: EFECTIVO
B50: 47 | C50: 44156 | D50: =IF(C50="","",YEAR(C50)) -> 2020 | E50: =IF(C50="","",MONTH(C50)) -> 11 | F50: Marcela Carbonaro | G50: 24 | H50: chocotorta | J50: 1 | K50: 456 | L50: 1500 | M50: =L50-K50 -> 1044
B51: 48 | C51: 44156 | D51: =IF(C51="","",YEAR(C51)) -> 2020 | E51: =IF(C51="","",MONTH(C51)) -> 11 | F51: marcela Carbonaro | G51: 33 | H51: frambuesas GRandes | J51: 1 | K51: 84 | L51: 250 | M51: =L51-K51 -> 166
B52: 49 | C52: 21/11/2020 | D52: =IF(C52="","",YEAR(C52)) -> 2020 | E52: =IF(C52="","",MONTH(C52)) -> 11 | F52: marcela Carbonaro | G52: 17 | H52: 1 Cheese Cake frutos rojos | I52: 20cm c/u | J52: 1 | K52: 349 | L52: 800 | M52: =L52-K52 -> 451
B53: =B52+1 -> 50 | C53: 44153 | D53: =IF(C53="","",YEAR(C53)) -> 2020 | E53: =IF(C53="","",MONTH(C53)) -> 11 | F53: fabio | G53: 34 | H53: frambuesas chicas | J53: 1 | K53: 129 | L53: 400 | M53: =L53-K53 -> 271
B54: =B53+1 -> 51 | C54: 44153 | D54: =IF(C54="","",YEAR(C54)) -> 2020 | E54: =IF(C54="","",MONTH(C54)) -> 11 | F54: viviana Paslesky | G54: 33 | H54: frambuesas Grandes | J54: 1 | K54: 84 | L54: 250 | M54: =L54-K54 -> 166
B55: =B54+1 -> 52 | C55: 19/11/2020 | D55: =IF(C55="","",YEAR(C55)) -> 2020 | E55: =IF(C55="","",MONTH(C55)) -> 11 | F55: candela Pacifico | G55: 33 | H55: Frambuesas Grandes | J55: 1 | K55: 84 | L55: 250 | M55: =L55-K55 -> 166
B56: =B55+1 -> 53 | C56: 21/11/2020 | D56: =IF(C56="","",YEAR(C56)) -> 2020 | E56: =IF(C56="","",MONTH(C56)) -> 11 | F56: marisel | G56: 33 | H56: frambuesas Grandes | J56: 2 | K56: 170 | L56: 500 | M56: =L56-K56 -> 330
B57: =B56+1 -> 54 | C57: 24/11/2020 | D57: =IF(C57="","",YEAR(C57)) -> 2020 | E57: =IF(C57="","",MONTH(C57)) -> 11 | F57: Delfina | H57: Desayuno Harry Stile | I57: 1 jugo. 3 cookies deco. 3 muffins deco. 2 maicena. 1 mini budin limon | K57: 500 | L57: 1100 | M57: =L57-K57 -> 600
B58: =B57+1 -> 55 | C58: 44156 | D58: =IF(C58="","",YEAR(C58)) -> 2020 | E58: =IF(C58="","",MONTH(C58)) -> 11 | F58: flor lanata | G58: 33 | H58: frambuesas Grandes | J58: 1 | K58: 84 | L58: 250 | M58: =L58-K58 -> 166
B59: =B58+1 -> 56 | C59: 44161 | D59: =IF(C59="","",YEAR(C59)) -> 2020 | E59: =IF(C59="","",MONTH(C59)) -> 11 | F59: ornella D estefano | G59: 33 | H59: frambuesas grandes | J59: 2 | K59: 170 | L59: 500 | M59: =L59-K59 -> 330
B60: =B59+1 -> 57 | C60: 44155 | D60: =IF(C60="","",YEAR(C60)) -> 2020 | E60: =IF(C60="","",MONTH(C60)) -> 11 | F60: Lucas Capello | G60: 33 | H60: frambuesas grandes | J60: 1 | K60: 84 | L60: 250 | M60: =L60-K60 -> 166
B61: =B60+1 -> 58 | C61: 44162 | D61: =IF(C61="","",YEAR(C61)) -> 2020 | E61: =IF(C61="","",MONTH(C61)) -> 11 | F61: Patico guardia | G61: 33 | H61: frambuesas Grandes | J61: 2 | K61: =84+84 -> 168 | L61: 500 | M61: =L61-K61 -> 332
B62: =B61+1 -> 59 | C62: 44155 | D62: =IF(C62="","",YEAR(C62)) -> 2020 | E62: =IF(C62="","",MONTH(C62)) -> 11 | F62: martin caraci | G62: 33 | H62: frambuesas grandes | J62: 1 | K62: 84 | L62: 250 | M62: =L62-K62 -> 166
B63: =B62+1 -> 60 | C63: 44155 | D63: =IF(C63="","",YEAR(C63)) -> 2020 | E63: =IF(C63="","",MONTH(C63)) -> 11 | F63: jimena caraci | G63: 33 | H63: frambuesas grandes | J63: 1 | K63: 84 | L63: 250 | M63: =L63-K63 -> 166
B64: =B63+1 -> 61 | C64: 44177 | D64: =IF(C64="","",YEAR(C64)) -> 2020 | E64: =IF(C64="","",MONTH(C64)) -> 12 | F64: Luli Miramontes | H64: torta abogada | I64: dulce de leche y crema con frutillas | J64: 1 | L64: 1800 | M64: =L64-K64 -> 1800
B65: 62 | C65: 44177 | D65: =IF(C65="","",YEAR(C65)) -> 2020 | E65: =IF(C65="","",MONTH(C65)) -> 12 | F65: Belu Morales | H65: torta cactus | I65: dulce con chips y crema | J65: 1 | L65: 1700 | M65: =L65-K65 -> 1700
B66: 63 | C66: 44177 | D66: =IF(C66="","",YEAR(C66)) -> 2020 | E66: =IF(C66="","",MONTH(C66)) -> 12 | F66: Erica | G66: 36 | H66: pan dulce 1/2 | I66: frutos secos | J66: 1 | K66: 308 | L66: 650 | M66: =L66-K66 -> 342
B67: 64 | C67: 44178 | D67: =IF(C67="","",YEAR(C67)) -> 2020 | E67: =IF(C67="","",MONTH(C67)) -> 12 | F67: Mica Rodriguez | G67: 35 | H67: desayuno | I67: con envio | J67: 1 | K67: 465 | L67: 1700 | M67: =L67-K67 -> 1235
B68: 65 | C68: 44179 | D68: =IF(C68="","",YEAR(C68)) -> 2020 | E68: =IF(C68="","",MONTH(C68)) -> 12 | F68: Leandro | H68: Muffins | I68: 2 mickey y 2 unicornio | J68: 4 | K68: 450 | L68: 450 | M68: =L68-K68 -> 0
B69: 66 | C69: 44181 | D69: =IF(C69="","",YEAR(C69)) -> 2020 | E69: =IF(C69="","",MONTH(C69)) -> 12 | F69: Flor Alonso | H69: torta Letra | I69: dulce, crema y merengue, chocos rosas | J69: 1 | L69: 1500
B70: 67 | C70: 44181 | D70: =IF(C70="","",YEAR(C70)) -> 2020 | E70: =IF(C70="","",MONTH(C70)) -> 12 | F70: Florencia Fernandez | H70: box plim plim | I70: 2 muffins, 3 cookies 3 cookies chupetin, baggio y leche chocolatada | J70: 1 | L70: 1000
B71: 68 | C71: 44182 | D71: =IF(C71="","",YEAR(C71)) -> 2020 | E71: =IF(C71="","",MONTH(C71)) -> 12 | F71: Gladys apura | G71: cookies decoradas | H71: tematica: maestra | I71: seño carla. Sabor vainilla 3, choco 3, limon 3 | J71: 12 | L71: 800
B72: 69 | C72: 44182 | D72: =IF(C72="","",YEAR(C72)) -> 2020 | E72: =IF(C72="","",MONTH(C72)) -> 12 | F72: norberto | G72: pastaflora | H72: 2 de 20x30 | I72: cortadas en 10x10 sabor: membrillo, batata | J72: 2 | L72: 1600
B73: 70 | C73: 44186 | D73: =IF(C73="","",YEAR(C73)) -> 2020 | E73: =IF(C73="","",MONTH(C73)) -> 12 | F73: Fer Mayer | G73: 6 | H73: torta brownie | I73: frutos rojos y merengue | J73: 1 | K73: 408 | L73: 1100 | M73: =L73-K73 -> 692 | N73: seña 800 / mercado pago
B74: =B73+1 -> 71 | C74: 44186 | D74: =IF(C74="","",YEAR(C74)) -> 2020 | E74: =IF(C74="","",MONTH(C74)) -> 12 | F74: Fer Mayer | H74: cookies decoradas | I74: greys anatomy | J74: 6 | L74: 550 | M74: =L74-K74 -> 550
B75: =B74+1 -> 72 | C75: 44189 | D75: =IF(C75="","",YEAR(C75)) -> 2020 | E75: =IF(C75="","",MONTH(C75)) -> 12 | F75: Erica | G75: 36 | H75: pan dulce 1/2 | I75: frutos secos / chips | J75: 2 | K75: 616 | L75: 1300 | M75: =L75-K75 -> 684
B76: =B75+1 -> 73 | C76: 44189 | D76: =IF(C76="","",YEAR(C76)) -> 2020 | E76: =IF(C76="","",MONTH(C76)) -> 12 | F76: Miriam | G76: 38 | H76: pan dulce 1kg | I76: pan dulce frutos secos | J76: 1 | K76: 551 | L76: 1100 | M76: =L76-K76 -> 549
B77: =B76+1 -> 74 | C77: 44189 | D77: =IF(C77="","",YEAR(C77)) -> 2020 | E77: =IF(C77="","",MONTH(C77)) -> 12 | F77: cora | G77: 38 | H77: pan dulce 1 kg | I77: frutas secos y abrillantadas | J77: 1 | K77: 551 | L77: 1100 | M77: =L77-K77 -> 549
B78: =B77+1 -> 75 | C78: 44189 | D78: =IF(C78="","",YEAR(C78)) -> 2020 | E78: =IF(C78="","",MONTH(C78)) -> 12 | F78: Gladys apura | G78: 28 | H78: cookies decoradas | I78: navidad | J78: 12 | K78: 120 | L78: 1000 | M78: =L78-K78 -> 880
B79: =B78+1 -> 76 | C79: 44189 | D79: =IF(C79="","",YEAR(C79)) -> 2020 | E79: =IF(C79="","",MONTH(C79)) -> 12 | F79: Norma | G79: 38 | H79: pan dulce 1kg | I79: frutos secos y abrillantadas | J79: 1 | K79: 551 | L79: 1100 | M79: =L79-K79 -> 549
B80: =B79+1 -> 77 | C80: 44230 | D80: =IF(C80="","",YEAR(C80)) -> 2021 | E80: =IF(C80="","",MONTH(C80)) -> 2 | F80: Katy Hockey | G80: 25 | H80: Oreo doble Cake | I80: 18 cm | J80: 1 | K80: 553 | L80: 1400 | M80: =L80-K80 -> 847
B81: =B80+1 -> 78 | C81: 44236 | D81: =IF(C81="","",YEAR(C81)) -> 2021 | E81: =IF(C81="","",MONTH(C81)) -> 2 | F81: Isabel | G81: 43 | H81: desayuno | I81: opcion 3 | J81: 1 | K81: 576 | L81: 2300 | M81: =L81-K81 -> 1724
B82: =B81+1 -> 79 | C82: 44237 | D82: =IF(C82="","",YEAR(C82)) -> 2021 | E82: =IF(C82="","",MONTH(C82)) -> 2 | F82: Maria Belen Tenuta | G82: 44 | H82: Torta Paw Patrol | I82: 20 cm | J82: 1 | K82: 461 | L82: 2000 | M82: =L82-K82 -> 1539
B83: =B82+1 -> 80 | C83: 44246 | D83: =IF(C83="","",YEAR(C83)) -> 2021 | E83: =IF(C83="","",MONTH(C83)) -> 2 | F83: Ale costales | G83: 45 | H83: brownie 19 | I83: colores granates | J83: 1 | K83: 857 | L83: 2200 | M83: =L83-K83 -> 1343
B84: =B83+1 -> 81 | C84: 44248 | D84: =IF(C84="","",YEAR(C84)) -> 2021 | E84: =IF(C84="","",MONTH(C84)) -> 2 | F84: silvina Scotti | G84: 2 | H84: macarrons | J84: 6 | K84: 306 | L84: 550 | M84: =L84-K84 -> 244
B85: =B84+1 -> 82 | C85: 44248 | D85: =IF(C85="","",YEAR(C85)) -> 2021 | E85: =IF(C85="","",MONTH(C85)) -> 2 | F85: silvina Scotti | G85: 43 | H85: desayuno | I85: opcion 3 | J85: 1 | K85: 576 | L85: 2300 | M85: =L85-K85 -> 1724
B86: =B85+1 -> 83 | C86: 44248 | D86: =IF(C86="","",YEAR(C86)) -> 2021 | E86: =IF(C86="","",MONTH(C86)) -> 2 | F86: dietetica | G86: 24 | H86: chocotorta | I86: 18 cm | J86: 1 | K86: 400 | L86: 850 | M86: =L86-K86 -> 450
B87: =B86+1 -> 84 | C87: 44260 | D87: =IF(C87="","",YEAR(C87)) -> 2021 | E87: =IF(C87="","",MONTH(C87)) -> 3 | F87: Flor Vitola | G87: 35 | H87: desayuno opcion 1 | J87: 1 | K87: 478 | L87: 1700 | M87: =L87-K87 -> 1222
B88: =B87+1 -> 85 | C88: 44261 | D88: =IF(C88="","",YEAR(C88)) -> 2021 | E88: =IF(C88="","",MONTH(C88)) -> 3 | F88: valeria Stella | G88: 2 | H88: macarrons | J88: 5 | K88: 153.5 | L88: 300 | M88: =L88-K88 -> 146.5
B89: =B88+1 -> 86 | C89: 44262 | D89: =IF(C89="","",YEAR(C89)) -> 2021 | E89: =IF(C89="","",MONTH(C89)) -> 3 | F89: luli lobos | G89: 6 | H89: brownie | I89: frutos rojos | J89: 1 | K89: 406 | L89: 2000 | M89: =L89-K89 -> 1594
B90: =B89+1 -> 87 | C90: 44275 | D90: =IF(C90="","",YEAR(C90)) -> 2021 | E90: =IF(C90="","",MONTH(C90)) -> 3 | F90: Daniela Miozzi | H90: cupcakes, cookies, cakepops | I90: militar | J90: 36 | K90: 800 | L90: 2000 | M90: =L90-K90 -> 1200
B91: =B90+1 -> 88 | C91: 44290 | D91: =IF(C91="","",YEAR(C91)) -> 2021 | E91: =IF(C91="","",MONTH(C91)) -> 4 | F91: Nati baltierra | G91: 46 | H91: huevo relleno | I91: 1 verde 2 rosas | J91: 3 | K91: 948 | L91: 2400 | M91: =L91-K91 -> 1452 | N91: pago
B92: =B91+1 -> 89 | C92: 44290 | D92: =IF(C92="","",YEAR(C92)) -> 2021 | E92: =IF(C92="","",MONTH(C92)) -> 4 | F92: Marcela Veron | G92: 46 | H92: huevo relleno | I92: 1 granate 1 rosa | J92: 2 | K92: 632 | L92: 1400 | M92: =L92-K92 -> 768
B93: =B92+1 -> 90 | C93: 44290 | D93: =IF(C93="","",YEAR(C93)) -> 2021 | E93: =IF(C93="","",MONTH(C93)) -> 4 | F93: german piriz | G93: 46 | H93: huevo relleno | I93: chocolate negro | J93: 2 | K93: 632 | L93: 1400 | M93: =L93-K93 -> 768 | N93: pago
B94: =B93+1 -> 91 | C94: 44290 | D94: =IF(C94="","",YEAR(C94)) -> 2021 | E94: =IF(C94="","",MONTH(C94)) -> 4 | F94: Agustin Paramidani | G94: 46 | H94: huevo relleno | I94: chocolate negro y rosa | J94: 1 | K94: 316 | L94: 700 | M94: =L94-K94 -> 384 | N94: pago
B95: =B94+1 -> 92 | C95: 44290 | D95: =IF(C95="","",YEAR(C95)) -> 2021 | E95: =IF(C95="","",MONTH(C95)) -> 4 | F95: Luli Ravale | G95: 46 | H95: huevo relleno | I95: 2 rosas negros y 2 verdes blancos | J95: 4 | K95: 1264 | L95: 2800 | M95: =L95-K95 -> 1536
B96: =B95+1 -> 93 | C96: 44290 | D96: =IF(C96="","",YEAR(C96)) -> 2021 | E96: =IF(C96="","",MONTH(C96)) -> 4 | F96: marcela veron | G96: 23 | H96: tarta de manzana | I96: 16 cm | J96: 1 | K96: 284 | L96: 600 | M96: =L96-K96 -> 316
B97: =B96+1 -> 94 | C97: 44290 | D97: =IF(C97="","",YEAR(C97)) -> 2021 | E97: =IF(C97="","",MONTH(C97)) -> 4 | F97: Viviana Vedani | G97: 46 | H97: huevo relleno | I97: 1 18 cm rosa y 2 verdes | J97: 3 | K97: 948 | L97: 2050 | M97: =L97-K97 -> 1102 | N97: pago
B98: =B97+1 -> 95 | C98: 44300 | D98: =IF(C98="","",YEAR(C98)) -> 2021 | E98: =IF(C98="","",MONTH(C98)) -> 4 | F98: Daniela ares | G98: 35 | H98: desayuno opcion 1 | I98: globos 49 | J98: 1 | K98: 478 | L98: 2750 | M98: =L98-K98 -> 2272 | N98: mercado pago
B99: =B98+1 -> 96 | C99: 44302 | D99: =IF(C99="","",YEAR(C99)) -> 2021 | E99: =IF(C99="","",MONTH(C99)) -> 4 | F99: Aldana Lucila | G99: 28 | H99: cookies decoradas | I99: minions | J99: 12 | K99: 200 | L99: 1220 | M99: =L99-K99 -> 1020
B100: =B99+1 -> 97 | C100: 44302 | D100: =IF(C100="","",YEAR(C100)) -> 2021 | E100: =IF(C100="","",MONTH(C100)) -> 4 | F100: Erica Duarte | G100: 48 | H100: ferrero rocher | I100: 20 cm | J100: 1 | K100: 864 | L100: 2000 | M100: =L100-K100 -> 1136
B101: =B100+1 -> 98 | C101: 44303 | D101: =IF(C101="","",YEAR(C101)) -> 2021 | E101: =IF(C101="","",MONTH(C101)) -> 4 | F101: Ornella Lobos | G101: 49 | H101: Torta Buttercream | I101: 12 cm | J101: 1 | K101: 407 | L101: 1500 | M101: =L101-K101 -> 1093 | N101: TRASFERENCIA
B102: =B101+1 -> 99 | C102: 44303 | D102: =IF(C102="","",YEAR(C102)) -> 2021 | E102: =IF(C102="","",MONTH(C102)) -> 4 | F102: jimena caraci | G102: 44 | H102: torta 12 cm Pasta Ballina | I102: comunion | J102: 1 | K102: 426 | L102: 1500 | M102: =L102-K102 -> 1074
...

Sheet Sheet1
B2: Artículo | C2: Porciones | D2: Precio | F2: Costo | G2: Rentabilidad | H2: Rentabilidad %
B3: Alfajores de Nuez x12 | C3: 12 | D3: 9000 | F3: =VLOOKUP(B3,'Costo x Articulo'!$C$3:$G$153,5,0) -> 3643.1667 | G3: =D3-F3 -> 5356.8333 | H3: =G3/F3 -> 1.4703783
B4: Budín de frutos secos | C4: 10 | D4: 14000 | F4: =VLOOKUP(B4,'Costo x Articulo'!$C$3:$G$153,5,0) -> 6604.7333 | G4: =D4-F4 -> 7395.2667 | H4: =G4/F4 -> 1.1196919
B5: Budín de limón | C5: 10 | D5: 12000 | F5: =VLOOKUP(B5,'Costo x Articulo'!$C$3:$G$153,5,0) -> 5558.0667 | G5: =D5-F5 -> 6441.9333 | H5: =G5/F5 -> 1.1590241
B6: Carrot Cake 22cm | C6: 8 | D6: 14500 | F6: =VLOOKUP(B6,'Costo x Articulo'!$C$3:$G$153,5,0) -> 5555.9524 | G6: =D6-F6 -> 8944.0476 | H6: =G6/F6 -> 1.6098136
B7: Carrot Cake Mini | C7: 1 | D7: 2900 | F7: =F6/6 -> 925.99206 | G7: =D7-F7 -> 1974.0079 | H7: =G7/F7 -> 2.1317763
B8: Cheescake 22cm | C8: 8 | D8: 26000 | F8: =VLOOKUP(B8,'Costo x Articulo'!$C$3:$G$153,5,0) -> 15249.932 | G8: =D8-F8 -> 10750.068 | H8: =G8/F8 -> 0.70492565
B9: Cheescake Mini | C9: 1 | D9: 3500 | F9: =F8/6 -> 2541.6553 | G9: =D9-F9 -> 958.34469 | H9: =G9/F9 -> 0.37705534
B10: Chocotorta clásica redonda 22cm | C10: 8 | D10: 25000 | F10: =VLOOKUP(B10,'Costo x Articulo'!$C$3:$G$153,5,0) -> 16903.571 | G10: =D10-F10 -> 8096.4286 | H10: =G10/F10 -> 0.47897739
B11: Chocotorta clásica cuadrada Mini | C11: 1 | D11: 3500 | F11: =F10/6 -> 2817.2619 | G11: =D11-F11 -> 682.7381 | H11: =G11/F11 -> 0.24234101
B12: Cookies Chips Chocolatesx15 | C12: 15 | D12: 6000 | F12: =VLOOKUP(B12,'Costo x Articulo'!$C$3:$G$153,5,0) -> 2411.1267 | G12: =D12-F12 -> 3588.8733 | H12: =G12/F12 -> 1.4884632
B13: Doble Oreo 22cm | C13: 8 | D13: 24000 | F13: =VLOOKUP(B13,'Costo x Articulo'!$C$3:$G$153,5,0) -> 17915 | G13: =D13-F13 -> 6085 | H13: =G13/F13 -> 0.3396595
B14: Doble Oreo Mini | C14: 1 | D14: 3500 | F14: =F13/6 -> 2985.8333 | G14: =D14-F14 -> 514.16667 | H14: =G14/F14 -> 0.17220207
B15: Lemon pie 24cm | C15: 8 | D15: 21000 | F15: =VLOOKUP(B15,'Costo x Articulo'!$C$3:$G$153,5,0) -> 9123.5333 | G15: =D15-F15 -> 11876.467 | H15: =G15/F15 -> 1.3017398
B16: Lemon pie Mini | C16: 1 | D16: 2700 | F16: =F15/6 -> 1520.5889 | G16: =D16-F16 -> 1179.4111 | H16: =G16/F16 -> 0.77562786
B17: Macarrons x 12 unidades | C17: 12 | D17: 9000 | F17: =VLOOKUP(B17,'Costo x Articulo'!$C$3:$G$153,5,0) -> 3391.1333 | G17: =D17-F17 -> 5608.8667 | H17: =G17/F17 -> 1.65398
B18: Tarta de Manzana 22cm | C18: 8 | D18: 16000 | F18: =VLOOKUP(B18,'Costo x Articulo'!$C$3:$G$153,5,0) -> 6706.1167 | G18: =D18-F18 -> 9293.8833 | H18: =G18/F18 -> 1.3858815
B19: Tarta de Manzana Mini | C19: 1 | D19: 2900 | F19: =F18/6 -> 1117.6861 | G19: =D19-F19 -> 1782.3139 | H19: =G19/F19 -> 1.5946462
B20: Torta brownie 20x20cm | C20: 8 | D20: 22000 | F20: =VLOOKUP(B20,'Costo x Articulo'!$C$3:$G$153,5,0) -> 10233.328 | G20: =D20-F20 -> 11766.672 | H20: =G20/F20 -> 1.1498383
B21: Torta brownie Mini | C21: 1 | D21: 3000 | F21: =F20/6 -> 1705.5546 | G21: =D21-F21 -> 1294.4454 | H21: =G21/F21 -> 0.75895861

Sheet Margen
B2: Mes | C2: Insumos | D2: Ventas | E2: Margen
B3: 45566 | C3: =59000+90700+30000+15000+4400+36150+4300+9900-8000+59310 -> 300760 | D3: =17800+36000+81500+65400+31600+15000+30000+40000+51000+90000+20000+42000+38500+17500 -> 576300 | E3: =IFERROR(D3/C3-1,0) -> 0.91614576
B4: 45597 | C4: =61000+21050+2000+23000+33100 -> 140150 | E4: =IFERROR(D4/C4-1,0) -> -1
B5: 45627 | C5: 85500 | E5: =IFERROR(D5/C5-1,0) -> -1

Sheet Insumos
B3: Insumo | C3: Unidad | D3: Cantidad | E3: Costo | F3: CU | G3: Fecha
B4: 3
B5: Aceite | C5: Cm3 | D5: 3500 | E5: 4500 | F5: =E5/D5 -> 1.2857143 | G5: 45320
B6: albaca | C6: Unidad | D6: 1 | E6: 1800 | F6: =E6/D6 -> 1800
B7: Almedras | C7: Grs | D7: 100 | E7: 1700 | F7: =E7/D7 -> 17 | G7: 45276
B8: aquafaba | C8: Cm3 | D8: 148 | E8: 819 | F8: =E8/D8 -> 5.5337838 | G8: 45320
B9: atun | C9: Unidad | D9: 1 | E9: 2500 | F9: =E9/D9 -> 2500
B10: Azúcar | C10: Grs | D10: 10000 | E10: 14000 | F10: =E10/D10 -> 1.4 | G10: 46145
B11: Azúcar granulada | C11: Grs | D11: 1000 | E11: 15000 | F11: =E11/D11 -> 15 | G11: 45377
B12: Azúcar impalpable | C12: Grs | D12: 10000 | E12: 15000 | F12: =E12/D12 -> 1.5 | G12: 46145
B13: Azucar Negra | C13: Grs | D13: 1000 | E13: 850 | F13: =E13/D13 -> 0.85 | G13: 45082
B14: Baggio | C14: Unidad | D14: 1 | E14: 700 | F14: =E14/D14 -> 700 | G14: 45635
B15: Bandeja cuadrada 10x10 | C15: Unidad | D15: 1 | E15: 400 | F15: =E15/D15 -> 400 | G15: 45565
B16: bandeja mandera logo 25 cm | C16: Unidad | D16: 1 | E16: 1300 | F16: =E16/D16 -> 1300 | G16: 46145
B17: Bandeja N°6 30x25 | C17: Unidad | D17: 100 | E17: 500 | F17: =E17/D17 -> 5
B18: Bandeja redonda 14 cm | C18: Unidad | D18: 1 | E18: 10.2 | F18: =E18/D18 -> 10.2
B19: Bandeja redonda 24cm rigida | C19: Unidad | D19: 1 | E19: 1300 | F19: =E19/D19 -> 1300 | G19: 45492
B20: Bandeja redonda 28cm logo | C20: Unidad | D20: 1 | E20: 1610 | F20: =E20/D20 -> 1610 | G20: 46145
B21: Bandeja Rígida y logo 40x30 | C21: Unidad | D21: 1 | E21: 2250 | F21: =E21/D21 -> 2250 | G21: 45877
B22: Batata | C22: Grs | D22: 500 | E22: 2300 | F22: =E22/D22 -> 4.6 | G22: 45635
B23: Bicarbonato de sodio | C23: Grs | D23: 25 | E23: 416 | F23: =E23/D23 -> 16.64 | G23: 45635
B24: Bloda n°12 | C24: Unidad | D24: 100 | E24: 396 | F24: =E24/D24 -> 3.96 | G24: 45082
B25: Blonda | C25: Unidad | D25: 100 | E25: 625 | F25: =E25/D25 -> 6.25 | G25: 45082
B26: Bolsa 40x30 | C26: Unidad | D26: 100 | E26: 794 | F26: =E26/D26 -> 7.94 | G26: 45082
B27: bolsa condimento bondiola | C27: Unidad | D27: 1 | E27: 1800 | F27: =E27/D27 -> 1800
B28: Bolsa de madera | C28: Unidad | D28: 1 | E28: 34 | F28: =E28/D28 -> 34 | G28: 45082
B29: Bolsa de papel Argentina | C29: Unidad | D29: 10 | E29: 1000 | F29: =E29/D29 -> 100 | G29: 45017
B30: Bolsa de polipropileno x 100 un. | C30: Unidad | D30: 100 | E30: 1100 | F30: =E30/D30 -> 11 | G30: 45276
B31: Bolsitas 12x15 | C31: Unidad | D31: 200 | E31: 202 | F31: =E31/D31 -> 1.01 | G31: 45082
B32: Bombom corazon | C32: Unidad | D32: 1 | E32: 50 | F32: =E32/D32 -> 50
B33: bondiola 1kg | C33: Grs | D33: 1000 | E33: 6200 | F33: =E33/D33 -> 6.2
B34: Botella vidrio 250cc | C34: Unidad | D34: 30 | E34: 2515 | F34: =E34/D34 -> 83.833333
B35: brochette | C35: Unidad | D35: 100 | E35: 1750 | F35: =E35/D35 -> 17.5
B36: Budinera papel x500grms | C36: Unidad | D36: 1 | E36: 40 | F36: =E36/D36 -> 40 | G36: 45082
B37: Cacao | C37: Grs | D37: 180 | E37: 6500 | F37: =E37/D37 -> 36.111111 | G37: 46145
B38: Cacao alcalino | C38: Grs | D38: 1000 | E38: 36000 | F38: =E38/D38 -> 36 | G38: 46145
B39: Café en saquito | C39: Unidad | D39: 20 | E39: 441 | F39: =E39/D39 -> 22.05 | G39: 45082
B40: Café Instantaneo | C40: Grs | D40: 170 | E40: 798 | F40: =E40/D40 -> 4.6941176 | G40: 45082
B41: Caja maletin kraf 25x25x15 | C41: Unidad | D41: 1 | E41: 975 | F41: =E41/D41 -> 975 | G41: 46145
B42: Caja 32x25x10 | C42: Unidad | D42: 1 | E42: 358 | F42: =E42/D42 -> 358 | G42: 45082
B43: Caja desayuno 25x25 | C43: Unidad | D43: 1 | E43: 436 | F43: =E43/D43 -> 436 | G43: 45082
B44: Caja día del padre Messi | C44: Unidad | D44: 1 | E44: 196 | F44: =E44/D44 -> 196 | G44: 45088
B45: Caja Drip Cake 25 x 25 x25 | C45: Unidad | D45: 1 | E45: 1400 | F45: =E45/D45 -> 1400 | G45: 46145
B46: Caja Drip Cake 30 x 30 x25 | C46: Unidad | D46: 1 | E46: 1700 | F46: =E46/D46 -> 1700 | G46: 46145
B47: Caja Flores | C47: Unidad | D47: 10 | E47: 680 | F47: =E47/D47 -> 68
B48: Caja macarrons | C48: Unidad | D48: 1 | E48: 300 | F48: =E48/D48 -> 300 | G48: 45877
B49: Caja macarrons x12 | C49: Unidad | D49: 1 | E49: 410 | F49: =E49/D49 -> 410 | G49: 46145
B50: Caja Medio huevo | C50: Unidad | D50: 1 | E50: 212 | F50: =E50/D50 -> 212 | G50: 45017
B51: Caja mini torta 15X15x15 | C51: Unidad | D51: 1 | E51: 291 | F51: =E51/D51 -> 291 | G51: 45082
B52: Caja Navidad | C52: Unidad | D52: 1 | E52: 55 | F52: =E52/D52 -> 55
B53: Caja pan dulce 1 kg | C53: Unidad | D53: 1 | E53: 52 | F53: =E53/D53 -> 52
B54: Caja Pan dulce 1/2 kg | C54: Unidad | D54: 1 | E54: 43 | F54: =E54/D54 -> 43
B55: Caja Rectangular n° | C55: Unidad | D55: 1 | E55: 2500 | F55: =E55/D55 -> 2500 | G55: 46145
B56: Caja valija chica pascua | C56: Unidad | D56: 1 | E56: 831 | F56: =E56/D56 -> 831 | G56: 45755
B57: Cajas dia del la madre '24 | C57: Unidad | D57: 5 | E57: 6500 | F57: =E57/D57 -> 1300 | G57: 45811
B58: Caju | C58: Grs | D58: 1000 | E58: 4200 | F58: =E58/D58 -> 4.2 | G58: 45082
B59: canape | C59: Unidad | D59: 10 | E59: 2900 | F59: =E59/D59 -> 290
B60: Capuccino Sense | C60: Unidad | D60: 1 | E60: 250 | F60: =E60/D60 -> 250 | G60: 45088
B61: carne picada | C61: Grs | D61: 1000 | E61: 15000 | F61: =E61/D61 -> 15
B62: Cartulina | C62: Unidad | D62: 1 | E62: 20 | F62: =E62/D62 -> 20
B63: Cebolla | C63: Grs | D63: 1000 | E63: 1750 | F63: =E63/D63 -> 1.75
B64: Cebolla deshidratada | C64: Grs | D64: 25 | E64: 225 | F64: =E64/D64 -> 9 | G64: 46178
B65: Cerezas | C65: Grs | D65: 3000 | E65: 24000 | F65: =E65/D65 -> 8 | G65: 45377
B66: Champagne chiquito | C66: Unidad | D66: 1 | E66: 618 | F66: =E66/D66 -> 618 | G66: 45082
B67: Chips de chocolate | C67: Grs | D67: 1000 | E67: 9000 | F67: =E67/D67 -> 9 | G67: 46145
B68: Chocolatada 200ml | C68: Unidad | D68: 1 | E68: 1900 | F68: =E68/D68 -> 1900 | G68: 46145
B69: Chocolate | C69: Grs | D69: 6000 | E69: 60000 | F69: =E69/D69 -> 10 | G69: 46145
B70: Chocolinas | C70: Grs | D70: 250 | E70: 1900 | F70: =E70/D70 -> 7.6 | G70: 46145
B71: Cinta | C71: Unidad | D71: 10 | E71: 610 | F71: =E71/D71 -> 61
B72: Coco rayado | C72: Grs | D72: 1000 | E72: 10500 | F72: =E72/D72 -> 10.5 | G72: 46145
B73: Colorante | C73: Grs | D73: 15 | E73: 1800 | F73: =E73/D73 -> 120 | G73: 46145
B74: Colorante liposoluble | C74: Grs | D74: 15 | E74: 3500 | F74: =E74/D74 -> 233.33333 | G74: 46145
B75: Colorante liposoluble oro | C75: Grs | D75: 15 | E75: 5000 | F75: =E75/D75 -> 333.33333 | G75: 46145
B76: Crema de chocolate | C76: Grs | D76: 1000 | E76: 11000 | F76: =E76/D76 -> 11 | G76: 46145
B77: Crema de leche | C77: Grs | D77: 5000 | E77: 46000 | F77: =E77/D77 -> 9.2 | G77: 46145
B78: Crema vegana | C78: Cm3 | D78: 7000 | E78: 900 | F78: =E78/D78 -> 0.12857143 | G78: 45877
B79: Cuchara pascua | C79: Unidad | D79: 1 | E79: 53 | F79: =E79/D79 -> 53 | G79: 45017
B80: Disco dorado 24 | C80: Unidad | D80: 10 | E80: 4000 | F80: =E80/D80 -> 400 | G80: 45565
B81: Dulce de leche | C81: Grs | D81: 10000 | E81: 34000 | F81: =E81/D81 -> 3.4 | G81: 46145
B82: Dulce de Leche VEGANO | C82: Grs | D82: =(360+250) -> 610 | E82: 5000 | F82: =E82/D82 -> 8.1967213 | G82: 45320
B83: Esencia de vainilla | C83: Cm3 | D83: 5000 | E83: 7600 | F83: =E83/D83 -> 1.52 | G83: 46145
B84: Etiqueta | C84: Unidad | D84: 30 | E84: 50 | F84: =E84/D84 -> 1.6666667
B85: Etiquetas Navidad | C85: Unidad | D85: 50 | E85: 300 | F85: =E85/D85 -> 6
B86: Etiquetas Pascua | C86: Unidad | D86: 30 | E86: 380 | F86: =E86/D86 -> 12.666667 | G86: 45017
B87: Extracto de malta | C87: Grs | D87: 500 | E87: 3500 | F87: =E87/D87 -> 7 | G87: 45635
B88: Fecula de Mandioca | C88: Grs | D88: 1000 | E88: 3500 | F88: =E88/D88 -> 3.5 | G88: 46145
B89: Ferrero rocher | C89: Unidad | D89: 3 | E89: 160 | F89: =E89/D89 -> 53.333333 | G89: 44767
B90: figaza de manteca | C90: Unidad | D90: 36 | E90: 3000 | F90: =E90/D90 -> 83.333333
B91: Foto | C91: Unidad | D91: 1 | E91: 50 | F91: =E91/D91 -> 50
B92: Frambuesas | C92: Grs | D92: 1000 | E92: 1200 | F92: =E92/D92 -> 1.2 | G92: 44767
B93: Frutas abrillantadas | C93: Grs | D93: 1000 | E93: 3000 | F93: =E93/D93 -> 3 | G93: 45276
B94: Frutilla | C94: Unidad | D94: 1000 | E94: 4000 | F94: =E94/D94 -> 4 | G94: 45925
B95: frutos rojos congelados | C95: Grs | D95: 1000 | E95: 11000 | F95: =E95/D95 -> 11 | G95: 46012
B96: Galletitas lincoln | C96: Grs | D96: 153 | E96: 1600 | F96: =E96/D96 -> 10.457516 | G96: 46145
B97: Gelatina Sin Sabor | C97: Grs | D97: 1000 | E97: 18000 | F97: =E97/D97 -> 18 | G97: 45925
B98: Globo corazon | C98: Unidad | D98: 1 | E98: 1500 | F98: =E98/D98 -> 1500 | G98: 45565
B99: Globo HALOWEEN | C99: Unidad | D99: 1 | E99: 37 | F99: =E99/D99 -> 37
B100: Golosinas | C100: Grs | D100: 1000 | E100: 4000 | F100: =E100/D100 -> 4
B101: granas de color | C101: Grs | D101: 500 | E101: 3500 | F101: =E101/D101 -> 7 | G101: 45635
B102: grasa | C102: Grs | D102: 20000 | E102: 8200 | F102: =E102/D102 -> 0.41 | G102: 44767
...

Sheet Recetas
D1: 2 | F1: =D1+1 -> 3 | G1: =F1+1 -> 4
B2: Nro. | C2: Receta | D2: Ingrediente | E2: Unidad | F2: Cantidad | G2: Precio por 1 | H2: Total
B3: 1 | C3: Budín de limón | D3: Manteca | E3: =IFERROR(VLOOKUP($D3,Insumos!$B:$U,D$1,0),"") -> Grs | F3: 200 | G3: =IFERROR(VLOOKUP($D3,Insumos!$B:$U,G$1,0)/VLOOKUP($D3,Insumos!$B:$U,F$1,0),"") -> 11 | H3: =IFERROR(F3*G3,"") -> 2200
B4: =IF($D4="","",B3) -> 1 | C4: =IF($D4="","",C3) -> Budín de limón | D4: Azúcar | E4: =IFERROR(VLOOKUP($D4,Insumos!$B:$U,D$1,0),"") -> Grs | F4: 200 | G4: =IFERROR(VLOOKUP($D4,Insumos!$B:$U,G$1,0)/VLOOKUP($D4,Insumos!$B:$U,F$1,0),"") -> 1.4 | H4: =IFERROR(F4*G4,"") -> 280
B5: =IF($D5="","",B4) -> 1 | C5: =IF($D5="","",C4) -> Budín de limón | D5: Huevo | E5: =IFERROR(VLOOKUP($D5,Insumos!$B:$U,D$1,0),"") -> Unidad | F5: 4 | G5: =IFERROR(VLOOKUP($D5,Insumos!$B:$U,G$1,0)/VLOOKUP($D5,Insumos!$B:$U,F$1,0),"") -> 166.66667 | H5: =IFERROR(F5*G5,"") -> 666.66667
B6: =IF($D6="","",B5) -> 1 | C6: =IF($D6="","",C5) -> Budín de limón | D6: Harina 0000 | E6: =IFERROR(VLOOKUP($D6,Insumos!$B:$U,D$1,0),"") -> Grs | F6: 270 | G6: =IFERROR(VLOOKUP($D6,Insumos!$B:$U,G$1,0)/VLOOKUP($D6,Insumos!$B:$U,F$1,0),"") -> 0.82 | H6: =IFERROR(F6*G6,"") -> 221.4
B7: =IF($D7="","",B6) -> 1 | C7: =IF($D7="","",C6) -> Budín de limón | D7: Polvo de hornear | E7: =IFERROR(VLOOKUP($D7,Insumos!$B:$U,D$1,0),"") -> Grs | F7: 10 | G7: =IFERROR(VLOOKUP($D7,Insumos!$B:$U,G$1,0)/VLOOKUP($D7,Insumos!$B:$U,F$1,0),"") -> 8 | H7: =IFERROR(F7*G7,"") -> 80
B8: =IF($D8="","",B6) -> 1 | C8: =IF($D8="","",C6) -> Budín de limón | D8: Limón | E8: =IFERROR(VLOOKUP($D8,Insumos!$B:$U,D$1,0),"") -> Unidad | F8: 2 | G8: =IFERROR(VLOOKUP($D8,Insumos!$B:$U,G$1,0)/VLOOKUP($D8,Insumos!$B:$U,F$1,0),"") -> 180 | H8: =IFERROR(F8*G8,"") -> 360
B9: =IF($D9="","",B7) -> 1 | C9: =IF($D9="","",C7) -> Budín de limón | D9: Disco dorado 24 | E9: =IFERROR(VLOOKUP($D9,Insumos!$B:$U,D$1,0),"") -> Unidad | F9: 1 | G9: =IFERROR(VLOOKUP($D9,Insumos!$B:$U,G$1,0)/VLOOKUP($D9,Insumos!$B:$U,F$1,0),"") -> 400 | H9: =IFERROR(F9*G9,"") -> 400
B10: =IF($D10="","",B8) -> 1 | C10: =IF($D10="","",C8) -> Budín de limón | D10: Caja maletin kraf 25x25x15 | E10: =IFERROR(VLOOKUP($D10,Insumos!$B:$U,D$1,0),"") -> Unidad | F10: 1 | G10: =IFERROR(VLOOKUP($D10,Insumos!$B:$U,G$1,0)/VLOOKUP($D10,Insumos!$B:$U,F$1,0),"") -> 975 | H10: =IFERROR(F10*G10,"") -> 975
B11: =IF($D11="","",B10) -> 1 | C11: =IF($D11="","",C10) -> Budín de limón | D11: Azúcar impalpable | E11: =IFERROR(VLOOKUP($D11,Insumos!$B:$U,D$1,0),"") -> Grs | F11: 250 | G11: =IFERROR(VLOOKUP($D11,Insumos!$B:$U,G$1,0)/VLOOKUP($D11,Insumos!$B:$U,F$1,0),"") -> 1.5 | H11: =IFERROR(F11*G11,"") -> 375
B12: 2 | C12: Macarrons x 12 unidades | D12: Azúcar | E12: =IFERROR(VLOOKUP($D12,Insumos!$B:$U,D$1,0),"") -> Grs | F12: =130/30*12 -> 52 | G12: =IFERROR(VLOOKUP($D12,Insumos!$B:$U,G$1,0)/VLOOKUP($D12,Insumos!$B:$U,F$1,0),"") -> 1.4 | H12: =IFERROR(F12*G12,"") -> 72.8
B13: =IF($D13="","",B12) -> 2 | C13: =IF($D13="","",C12) -> Macarrons x 12 unidades | D13: Harina de almendras | E13: =IFERROR(VLOOKUP($D13,Insumos!$B:$U,D$1,0),"") -> Grs | F13: =65/30*12 -> 26 | G13: =IFERROR(VLOOKUP($D13,Insumos!$B:$U,G$1,0)/VLOOKUP($D13,Insumos!$B:$U,F$1,0),"") -> 32 | H13: =IFERROR(F13*G13,"") -> 832
B14: =IF($D14="","",B13) -> 2 | C14: =IF($D14="","",C13) -> Macarrons x 12 unidades | D14: Huevo | E14: =IFERROR(VLOOKUP($D14,Insumos!$B:$U,D$1,0),"") -> Unidad | F14: =2/30*12 -> 0.8 | G14: =IFERROR(VLOOKUP($D14,Insumos!$B:$U,G$1,0)/VLOOKUP($D14,Insumos!$B:$U,F$1,0),"") -> 166.66667 | H14: =IFERROR(F14*G14,"") -> 133.33333
B15: =IF($D15="","",B14) -> 2 | C15: =IF($D15="","",C14) -> Macarrons x 12 unidades | D15: Azúcar impalpable | E15: =IFERROR(VLOOKUP($D15,Insumos!$B:$U,D$1,0),"") -> Grs | F15: =65/30*12 -> 26 | G15: =IFERROR(VLOOKUP($D15,Insumos!$B:$U,G$1,0)/VLOOKUP($D15,Insumos!$B:$U,F$1,0),"") -> 1.5 | H15: =IFERROR(F15*G15,"") -> 39
B16: =IF($D16="","",B15) -> 2 | C16: =IF($D16="","",C15) -> Macarrons x 12 unidades | D16: Colorante | E16: =IFERROR(VLOOKUP($D16,Insumos!$B:$U,D$1,0),"") -> Grs | F16: =3/30*12 -> 1.2 | G16: =IFERROR(VLOOKUP($D16,Insumos!$B:$U,G$1,0)/VLOOKUP($D16,Insumos!$B:$U,F$1,0),"") -> 120 | H16: =IFERROR(F16*G16,"") -> 144
B17: =IF($D17="","",B16) -> 2 | C17: =IF($D17="","",C16) -> Macarrons x 12 unidades | D17: Saborizante | E17: =IFERROR(VLOOKUP($D17,Insumos!$B:$U,D$1,0),"") -> Grs | F17: =10/30*12 -> 4 | G17: =IFERROR(VLOOKUP($D17,Insumos!$B:$U,G$1,0)/VLOOKUP($D17,Insumos!$B:$U,F$1,0),"") -> 48 | H17: =IFERROR(F17*G17,"") -> 192
B18: =IF($D18="","",B17) -> 2 | C18: =IF($D18="","",C17) -> Macarrons x 12 unidades | D18: Crema de leche | E18: =IFERROR(VLOOKUP($D18,Insumos!$B:$U,D$1,0),"") -> Grs | F18: =100/30*12 -> 40 | G18: =IFERROR(VLOOKUP($D18,Insumos!$B:$U,G$1,0)/VLOOKUP($D18,Insumos!$B:$U,F$1,0),"") -> 9.2 | H18: =IFERROR(F18*G18,"") -> 368
B19: =IF($D19="","",B18) -> 2 | C19: =IF($D19="","",C18) -> Macarrons x 12 unidades | D19: Chocolate | E19: =IFERROR(VLOOKUP($D19,Insumos!$B:$U,D$1,0),"") -> Grs | F19: 40 | G19: =IFERROR(VLOOKUP($D19,Insumos!$B:$U,G$1,0)/VLOOKUP($D19,Insumos!$B:$U,F$1,0),"") -> 10 | H19: =IFERROR(F19*G19,"") -> 400
B20: =IF($D20="","",B19) -> 2 | C20: =IF($D20="","",C19) -> Macarrons x 12 unidades | D20: Mangas descartables N°4 | E20: =IFERROR(VLOOKUP($D20,Insumos!$B:$U,D$1,0),"") -> Unidad | F20: 2 | G20: =IFERROR(VLOOKUP($D20,Insumos!$B:$U,G$1,0)/VLOOKUP($D20,Insumos!$B:$U,F$1,0),"") -> 400 | H20: =IFERROR(F20*G20,"") -> 800
B21: =IF($D21="","",B20) -> 2 | C21: =IF($D21="","",C20) -> Macarrons x 12 unidades | D21: Caja macarrons x12 | E21: =IFERROR(VLOOKUP($D21,Insumos!$B:$U,D$1,0),"") -> Unidad | F21: 1 | G21: =IFERROR(VLOOKUP($D21,Insumos!$B:$U,G$1,0)/VLOOKUP($D21,Insumos!$B:$U,F$1,0),"") -> 410 | H21: =IFERROR(F21*G21,"") -> 410
B22: 3 | C22: Lemon pie 24cm | D22: Manteca | E22: =IFERROR(VLOOKUP($D22,Insumos!$B:$U,D$1,0),"") -> Grs | F22: =180+150 -> 330 | G22: =IFERROR(VLOOKUP($D22,Insumos!$B:$U,G$1,0)/VLOOKUP($D22,Insumos!$B:$U,F$1,0),"") -> 11 | H22: =IFERROR(F22*G22,"") -> 3630
B23: =IF($D23="","",B22) -> 3 | C23: =IF($D23="","",C22) -> Lemon pie 24cm | D23: Harina 0000 | E23: =IFERROR(VLOOKUP($D23,Insumos!$B:$U,D$1,0),"") -> Grs | F23: 300 | G23: =IFERROR(VLOOKUP($D23,Insumos!$B:$U,G$1,0)/VLOOKUP($D23,Insumos!$B:$U,F$1,0),"") -> 0.82 | H23: =IFERROR(F23*G23,"") -> 246
B24: =IF($D24="","",B23) -> 3 | C24: =IF($D24="","",C23) -> Lemon pie 24cm | D24: Azúcar impalpable | E24: =IFERROR(VLOOKUP($D24,Insumos!$B:$U,D$1,0),"") -> Grs | F24: 120 | G24: =IFERROR(VLOOKUP($D24,Insumos!$B:$U,G$1,0)/VLOOKUP($D24,Insumos!$B:$U,F$1,0),"") -> 1.5 | H24: =IFERROR(F24*G24,"") -> 180
B25: =IF($D25="","",B24) -> 3 | C25: =IF($D25="","",C24) -> Lemon pie 24cm | D25: Huevo | E25: =IFERROR(VLOOKUP($D25,Insumos!$B:$U,D$1,0),"") -> Unidad | F25: =2+4+2 -> 8 | G25: =IFERROR(VLOOKUP($D25,Insumos!$B:$U,G$1,0)/VLOOKUP($D25,Insumos!$B:$U,F$1,0),"") -> 166.66667 | H25: =IFERROR(F25*G25,"") -> 1333.3333
B26: =IF($D26="","",B25) -> 3 | C26: =IF($D26="","",C25) -> Lemon pie 24cm | D26: Esencia de vainilla | E26: =IFERROR(VLOOKUP($D26,Insumos!$B:$U,D$1,0),"") -> Cm3 | F26: 10 | G26: =IFERROR(VLOOKUP($D26,Insumos!$B:$U,G$1,0)/VLOOKUP($D26,Insumos!$B:$U,F$1,0),"") -> 1.52 | H26: =IFERROR(F26*G26,"") -> 15.2
B27: =IF($D27="","",B26) -> 3 | C27: =IF($D27="","",C26) -> Lemon pie 24cm | D27: Bandeja redonda 24cm rigida | E27: =IFERROR(VLOOKUP($D27,Insumos!$B:$U,D$1,0),"") -> Unidad | F27: 1 | G27: =IFERROR(VLOOKUP($D27,Insumos!$B:$U,G$1,0)/VLOOKUP($D27,Insumos!$B:$U,F$1,0),"") -> 1300 | H27: =IFERROR(F27*G27,"") -> 1300
B28: =IF($D28="","",B27) -> 3 | C28: =IF($D28="","",C27) -> Lemon pie 24cm | D28: Caja maletin kraf 25x25x15 | E28: =IFERROR(VLOOKUP($D28,Insumos!$B:$U,D$1,0),"") -> Unidad | F28: 1 | G28: =IFERROR(VLOOKUP($D28,Insumos!$B:$U,G$1,0)/VLOOKUP($D28,Insumos!$B:$U,F$1,0),"") -> 975 | H28: =IFERROR(F28*G28,"") -> 975
B29: =IF($D29="","",B28) -> 3 | C29: =IF($D29="","",C28) -> Lemon pie 24cm | D29: Limón | E29: =IFERROR(VLOOKUP($D29,Insumos!$B:$U,D$1,0),"") -> Unidad | F29: 2 | G29: =IFERROR(VLOOKUP($D29,Insumos!$B:$U,G$1,0)/VLOOKUP($D29,Insumos!$B:$U,F$1,0),"") -> 180 | H29: =IFERROR(F29*G29,"") -> 360
B30: =IF($D30="","",B29) -> 3 | C30: =IF($D30="","",C29) -> Lemon pie 24cm | D30: Azúcar | E30: =IFERROR(VLOOKUP($D30,Insumos!$B:$U,D$1,0),"") -> Grs | F30: =120+240 -> 360 | G30: =IFERROR(VLOOKUP($D30,Insumos!$B:$U,G$1,0)/VLOOKUP($D30,Insumos!$B:$U,F$1,0),"") -> 1.4 | H30: =IFERROR(F30*G30,"") -> 504
B31: =IF($D31="","",B30) -> 3 | C31: =IF($D31="","",C30) -> Lemon pie 24cm | D31: Mangas descartables N°4 | E31: =IFERROR(VLOOKUP($D31,Insumos!$B:$U,D$1,0),"") -> Unidad | F31: 1 | G31: =IFERROR(VLOOKUP($D31,Insumos!$B:$U,G$1,0)/VLOOKUP($D31,Insumos!$B:$U,F$1,0),"") -> 400 | H31: =IFERROR(F31*G31,"") -> 400
B32: =IF($D32="","",B31) -> 3 | C32: =IF($D32="","",C31) -> Lemon pie 24cm | D32: Gelatina Sin Sabor | E32: =IFERROR(VLOOKUP($D32,Insumos!$B:$U,D$1,0),"") -> Grs | F32: 10 | G32: =IFERROR(VLOOKUP($D32,Insumos!$B:$U,G$1,0)/VLOOKUP($D32,Insumos!$B:$U,F$1,0),"") -> 18 | H32: =IFERROR(F32*G32,"") -> 180
B33: 4 | C33: Lemon pie 12cm | D33: Manteca | E33: =IFERROR(VLOOKUP($D33,Insumos!$B:$U,D$1,0),"") -> Grs | F33: =F22/2 -> 165 | G33: =IFERROR(VLOOKUP($D33,Insumos!$B:$U,G$1,0)/VLOOKUP($D33,Insumos!$B:$U,F$1,0),"") -> 11 | H33: =IFERROR(F33*G33,"") -> 1815
B34: =IF($D34="","",B33) -> 4 | C34: =IF($D34="","",C33) -> Lemon pie 12cm | D34: Harina 0000 | E34: =IFERROR(VLOOKUP($D34,Insumos!$B:$U,D$1,0),"") -> Grs | F34: =F23/2 -> 150 | G34: =IFERROR(VLOOKUP($D34,Insumos!$B:$U,G$1,0)/VLOOKUP($D34,Insumos!$B:$U,F$1,0),"") -> 0.82 | H34: =IFERROR(F34*G34,"") -> 123
B35: =IF($D35="","",B34) -> 4 | C35: =IF($D35="","",C34) -> Lemon pie 12cm | D35: Azúcar impalpable | E35: =IFERROR(VLOOKUP($D35,Insumos!$B:$U,D$1,0),"") -> Grs | F35: =F24/2 -> 60 | G35: =IFERROR(VLOOKUP($D35,Insumos!$B:$U,G$1,0)/VLOOKUP($D35,Insumos!$B:$U,F$1,0),"") -> 1.5 | H35: =IFERROR(F35*G35,"") -> 90
B36: =IF($D36="","",B35) -> 4 | C36: =IF($D36="","",C35) -> Lemon pie 12cm | D36: Huevo | E36: =IFERROR(VLOOKUP($D36,Insumos!$B:$U,D$1,0),"") -> Unidad | F36: =F25/2 -> 4 | G36: =IFERROR(VLOOKUP($D36,Insumos!$B:$U,G$1,0)/VLOOKUP($D36,Insumos!$B:$U,F$1,0),"") -> 166.66667 | H36: =IFERROR(F36*G36,"") -> 666.66667
B37: =IF($D37="","",B36) -> 4 | C37: =IF($D37="","",C36) -> Lemon pie 12cm | D37: Esencia de vainilla | E37: =IFERROR(VLOOKUP($D37,Insumos!$B:$U,D$1,0),"") -> Cm3 | F37: =F26/2 -> 5 | G37: =IFERROR(VLOOKUP($D37,Insumos!$B:$U,G$1,0)/VLOOKUP($D37,Insumos!$B:$U,F$1,0),"") -> 1.52 | H37: =IFERROR(F37*G37,"") -> 7.6
B38: =IF($D38="","",B37) -> 4 | C38: =IF($D38="","",C37) -> Lemon pie 12cm | D38: Bandeja redonda 24cm rigida | E38: =IFERROR(VLOOKUP($D38,Insumos!$B:$U,D$1,0),"") -> Unidad | F38: =F27/2 -> 0.5 | G38: =IFERROR(VLOOKUP($D38,Insumos!$B:$U,G$1,0)/VLOOKUP($D38,Insumos!$B:$U,F$1,0),"") -> 1300 | H38: =IFERROR(F38*G38,"") -> 650
B39: =IF($D39="","",B38) -> 4 | C39: =IF($D39="","",C38) -> Lemon pie 12cm | D39: Caja maletin kraf 25x25x15 | E39: =IFERROR(VLOOKUP($D39,Insumos!$B:$U,D$1,0),"") -> Unidad | F39: =F28/2 -> 0.5 | G39: =IFERROR(VLOOKUP($D39,Insumos!$B:$U,G$1,0)/VLOOKUP($D39,Insumos!$B:$U,F$1,0),"") -> 975 | H39: =IFERROR(F39*G39,"") -> 487.5
B40: =IF($D40="","",B39) -> 4 | C40: =IF($D40="","",C39) -> Lemon pie 12cm | D40: Limón | E40: =IFERROR(VLOOKUP($D40,Insumos!$B:$U,D$1,0),"") -> Unidad | F40: =F29/2 -> 1 | G40: =IFERROR(VLOOKUP($D40,Insumos!$B:$U,G$1,0)/VLOOKUP($D40,Insumos!$B:$U,F$1,0),"") -> 180 | H40: =IFERROR(F40*G40,"") -> 180
B41: =IF($D41="","",B40) -> 4 | C41: =IF($D41="","",C40) -> Lemon pie 12cm | D41: Azúcar | E41: =IFERROR(VLOOKUP($D41,Insumos!$B:$U,D$1,0),"") -> Grs | F41: =F30/2 -> 180 | G41: =IFERROR(VLOOKUP($D41,Insumos!$B:$U,G$1,0)/VLOOKUP($D41,Insumos!$B:$U,F$1,0),"") -> 1.4 | H41: =IFERROR(F41*G41,"") -> 252
B42: =IF($D42="","",B41) -> 4 | C42: =IF($D42="","",C41) -> Lemon pie 12cm | D42: Mangas descartables N°4 | E42: =IFERROR(VLOOKUP($D42,Insumos!$B:$U,D$1,0),"") -> Unidad | F42: =F31/2 -> 0.5 | G42: =IFERROR(VLOOKUP($D42,Insumos!$B:$U,G$1,0)/VLOOKUP($D42,Insumos!$B:$U,F$1,0),"") -> 400 | H42: =IFERROR(F42*G42,"") -> 200
B43: =IF($D43="","",B42) -> 4 | C43: =IF($D43="","",C42) -> Lemon pie 12cm | D43: Gelatina Sin Sabor | E43: =IFERROR(VLOOKUP($D43,Insumos!$B:$U,D$1,0),"") -> Grs | F43: =F32/2 -> 5 | G43: =IFERROR(VLOOKUP($D43,Insumos!$B:$U,G$1,0)/VLOOKUP($D43,Insumos!$B:$U,F$1,0),"") -> 18 | H43: =IFERROR(F43*G43,"") -> 90
B44: 5 | C44: Brownie 20x20cm | D44: Manteca | E44: =IFERROR(VLOOKUP($D44,Insumos!$B:$U,D$1,0),"") -> Grs | F44: 110 | G44: =IFERROR(VLOOKUP($D44,Insumos!$B:$U,G$1,0)/VLOOKUP($D44,Insumos!$B:$U,F$1,0),"") -> 11 | H44: =IFERROR(F44*G44,"") -> 1210
B45: =IF($D45="","",B44) -> 5 | C45: =IF($D45="","",C44) -> Brownie 20x20cm | D45: Azúcar | E45: =IFERROR(VLOOKUP($D45,Insumos!$B:$U,D$1,0),"") -> Grs | F45: 225 | G45: =IFERROR(VLOOKUP($D45,Insumos!$B:$U,G$1,0)/VLOOKUP($D45,Insumos!$B:$U,F$1,0),"") -> 1.4 | H45: =IFERROR(F45*G45,"") -> 315
B46: =IF($D46="","",B45) -> 5 | C46: =IF($D46="","",C45) -> Brownie 20x20cm | D46: Huevo | E46: =IFERROR(VLOOKUP($D46,Insumos!$B:$U,D$1,0),"") -> Unidad | F46: 3 | G46: =IFERROR(VLOOKUP($D46,Insumos!$B:$U,G$1,0)/VLOOKUP($D46,Insumos!$B:$U,F$1,0),"") -> 166.66667 | H46: =IFERROR(F46*G46,"") -> 500
B47: =IF($D47="","",B46) -> 5 | C47: =IF($D47="","",C46) -> Brownie 20x20cm | D47: Chocolate | E47: =IFERROR(VLOOKUP($D47,Insumos!$B:$U,D$1,0),"") -> Grs | F47: 110 | G47: =IFERROR(VLOOKUP($D47,Insumos!$B:$U,G$1,0)/VLOOKUP($D47,Insumos!$B:$U,F$1,0),"") -> 10 | H47: =IFERROR(F47*G47,"") -> 1100
B48: =IF($D48="","",B47) -> 5 | C48: =IF($D48="","",C47) -> Brownie 20x20cm | D48: Cacao | E48: =IFERROR(VLOOKUP($D48,Insumos!$B:$U,D$1,0),"") -> Grs | F48: 10 | G48: =IFERROR(VLOOKUP($D48,Insumos!$B:$U,G$1,0)/VLOOKUP($D48,Insumos!$B:$U,F$1,0),"") -> 36.111111 | H48: =IFERROR(F48*G48,"") -> 361.11111
B49: =IF($D49="","",B48) -> 5 | C49: =IF($D49="","",C48) -> Brownie 20x20cm | D49: Harina 0000 | E49: =IFERROR(VLOOKUP($D49,Insumos!$B:$U,D$1,0),"") -> Grs | F49: 65 | G49: =IFERROR(VLOOKUP($D49,Insumos!$B:$U,G$1,0)/VLOOKUP($D49,Insumos!$B:$U,F$1,0),"") -> 0.82 | H49: =IFERROR(F49*G49,"") -> 53.3
B50: =IF($D50="","",B49) -> 5 | C50: =IF($D50="","",C49) -> Brownie 20x20cm | D50: Nuez | E50: =IFERROR(VLOOKUP($D50,Insumos!$B:$U,D$1,0),"") -> Grs | F50: 90 | G50: =IFERROR(VLOOKUP($D50,Insumos!$B:$U,G$1,0)/VLOOKUP($D50,Insumos!$B:$U,F$1,0),"") -> 19 | H50: =IFERROR(F50*G50,"") -> 1710
B51: =IF($D51="","",B50) -> 5 | C51: =IF($D51="","",C50) -> Brownie 20x20cm | D51: Caja maletin kraf 25x25x15 | E51: =IFERROR(VLOOKUP($D51,Insumos!$B:$U,D$1,0),"") -> Unidad | F51: 1 | G51: =IFERROR(VLOOKUP($D51,Insumos!$B:$U,G$1,0)/VLOOKUP($D51,Insumos!$B:$U,F$1,0),"") -> 975 | H51: =IFERROR(F51*G51,"") -> 975
B52: =IF($D52="","",B51) -> 5 | C52: =IF($D52="","",C51) -> Brownie 20x20cm | D52: Bandeja redonda 24cm rigida | E52: =IFERROR(VLOOKUP($D52,Insumos!$B:$U,D$1,0),"") -> Unidad | F52: 1 | G52: =IFERROR(VLOOKUP($D52,Insumos!$B:$U,G$1,0)/VLOOKUP($D52,Insumos!$B:$U,F$1,0),"") -> 1300 | H52: =IFERROR(F52*G52,"") -> 1300
B53: =IF($D53="","",B52) -> 5 | C53: =IF($D53="","",C52) -> Brownie 20x20cm | D53: Blonda | E53: =IFERROR(VLOOKUP($D53,Insumos!$B:$U,D$1,0),"") -> Unidad | F53: 1 | G53: =IFERROR(VLOOKUP($D53,Insumos!$B:$U,G$1,0)/VLOOKUP($D53,Insumos!$B:$U,F$1,0),"") -> 6.25 | H53: =IFERROR(F53*G53,"") -> 6.25
B54: 6 | C54: Torta brownie 20x20cm | D54: Manteca | E54: =IFERROR(VLOOKUP($D54,Insumos!$B:$U,D$1,0),"") -> Grs | F54: 110 | G54: =IFERROR(VLOOKUP($D54,Insumos!$B:$U,G$1,0)/VLOOKUP($D54,Insumos!$B:$U,F$1,0),"") -> 11 | H54: =IFERROR(F54*G54,"") -> 1210
B55: =IF($D55="","",B54) -> 6 | C55: =IF($D55="","",C54) -> Torta brownie 20x20cm | D55: Azúcar | E55: =IFERROR(VLOOKUP($D55,Insumos!$B:$U,D$1,0),"") -> Grs | F55: =225+240 -> 465 | G55: =IFERROR(VLOOKUP($D55,Insumos!$B:$U,G$1,0)/VLOOKUP($D55,Insumos!$B:$U,F$1,0),"") -> 1.4 | H55: =IFERROR(F55*G55,"") -> 651
B56: =IF($D56="","",B55) -> 6 | C56: =IF($D56="","",C55) -> Torta brownie 20x20cm | D56: Huevo | E56: =IFERROR(VLOOKUP($D56,Insumos!$B:$U,D$1,0),"") -> Unidad | F56: =3+4 -> 7 | G56: =IFERROR(VLOOKUP($D56,Insumos!$B:$U,G$1,0)/VLOOKUP($D56,Insumos!$B:$U,F$1,0),"") -> 166.66667 | H56: =IFERROR(F56*G56,"") -> 1166.6667
B57: =IF($D57="","",B56) -> 6 | C57: =IF($D57="","",C56) -> Torta brownie 20x20cm | D57: Chocolate | E57: =IFERROR(VLOOKUP($D57,Insumos!$B:$U,D$1,0),"") -> Grs | F57: 110 | G57: =IFERROR(VLOOKUP($D57,Insumos!$B:$U,G$1,0)/VLOOKUP($D57,Insumos!$B:$U,F$1,0),"") -> 10 | H57: =IFERROR(F57*G57,"") -> 1100
B58: =IF($D58="","",B57) -> 6 | C58: =IF($D58="","",C57) -> Torta brownie 20x20cm | D58: Cacao | E58: =IFERROR(VLOOKUP($D58,Insumos!$B:$U,D$1,0),"") -> Grs | F58: 10 | G58: =IFERROR(VLOOKUP($D58,Insumos!$B:$U,G$1,0)/VLOOKUP($D58,Insumos!$B:$U,F$1,0),"") -> 36.111111 | H58: =IFERROR(F58*G58,"") -> 361.11111
B59: =IF($D59="","",B58) -> 6 | C59: =IF($D59="","",C58) -> Torta brownie 20x20cm | D59: Harina 0000 | E59: =IFERROR(VLOOKUP($D59,Insumos!$B:$U,D$1,0),"") -> Grs | F59: 65 | G59: =IFERROR(VLOOKUP($D59,Insumos!$B:$U,G$1,0)/VLOOKUP($D59,Insumos!$B:$U,F$1,0),"") -> 0.82 | H59: =IFERROR(F59*G59,"") -> 53.3
B60: =IF($D60="","",B59) -> 6 | C60: =IF($D60="","",C59) -> Torta brownie 20x20cm | D60: Nuez | E60: =IFERROR(VLOOKUP($D60,Insumos!$B:$U,D$1,0),"") -> Grs | F60: 90 | G60: =IFERROR(VLOOKUP($D60,Insumos!$B:$U,G$1,0)/VLOOKUP($D60,Insumos!$B:$U,F$1,0),"") -> 19 | H60: =IFERROR(F60*G60,"") -> 1710
B61: =IF($D61="","",B60) -> 6 | C61: =IF($D61="","",C60) -> Torta brownie 20x20cm | D61: Caja maletin kraf 25x25x15 | E61: =IFERROR(VLOOKUP($D61,Insumos!$B:$U,D$1,0),"") -> Unidad | F61: 1 | G61: =IFERROR(VLOOKUP($D61,Insumos!$B:$U,G$1,0)/VLOOKUP($D61,Insumos!$B:$U,F$1,0),"") -> 975 | H61: =IFERROR(F61*G61,"") -> 975
B62: =IF($D62="","",B61) -> 6 | C62: =IF($D62="","",C61) -> Torta brownie 20x20cm | D62: Bandeja redonda 24cm rigida | E62: =IFERROR(VLOOKUP($D62,Insumos!$B:$U,D$1,0),"") -> Unidad | F62: 1 | G62: =IFERROR(VLOOKUP($D62,Insumos!$B:$U,G$1,0)/VLOOKUP($D62,Insumos!$B:$U,F$1,0),"") -> 1300 | H62: =IFERROR(F62*G62,"") -> 1300
B63: =IF($D63="","",B62) -> 6 | C63: =IF($D63="","",C62) -> Torta brownie 20x20cm | D63: Blonda | E63: =IFERROR(VLOOKUP($D63,Insumos!$B:$U,D$1,0),"") -> Unidad | F63: 1 | G63: =IFERROR(VLOOKUP($D63,Insumos!$B:$U,G$1,0)/VLOOKUP($D63,Insumos!$B:$U,F$1,0),"") -> 6.25 | H63: =IFERROR(F63*G63,"") -> 6.25
B64: =IF($D64="","",B63) -> 6 | C64: =IF($D64="","",C63) -> Torta brownie 20x20cm | D64: Dulce de leche | E64: =IFERROR(VLOOKUP($D64,Insumos!$B:$U,D$1,0),"") -> Grs | F64: 500 | G64: =IFERROR(VLOOKUP($D64,Insumos!$B:$U,G$1,0)/VLOOKUP($D64,Insumos!$B:$U,F$1,0),"") -> 3.4 | H64: =IFERROR(F64*G64,"") -> 1700
B65: 7 | C65: Tarta Frutillas 24cm | D65: Harina 0000 | E65: =IFERROR(VLOOKUP($D65,Insumos!$B:$U,D$1,0),"") -> Grs | F65: 300 | G65: =IFERROR(VLOOKUP($D65,Insumos!$B:$U,G$1,0)/VLOOKUP($D65,Insumos!$B:$U,F$1,0),"") -> 0.82 | H65: =IFERROR(F65*G65,"") -> 246
B66: =IF($D66="","",B65) -> 7 | C66: =IF($D66="","",C65) -> Tarta Frutillas 24cm | D66: manteca | E66: =IFERROR(VLOOKUP($D66,Insumos!$B:$U,D$1,0),"") -> Grs | F66: 180 | G66: =IFERROR(VLOOKUP($D66,Insumos!$B:$U,G$1,0)/VLOOKUP($D66,Insumos!$B:$U,F$1,0),"") -> 11 | H66: =IFERROR(F66*G66,"") -> 1980
B67: =IF($D67="","",B66) -> 7 | C67: =IF($D67="","",C66) -> Tarta Frutillas 24cm | D67: huevo | E67: =IFERROR(VLOOKUP($D67,Insumos!$B:$U,D$1,0),"") -> Unidad | F67: 2 | G67: =IFERROR(VLOOKUP($D67,Insumos!$B:$U,G$1,0)/VLOOKUP($D67,Insumos!$B:$U,F$1,0),"") -> 166.66667 | H67: =IFERROR(F67*G67,"") -> 333.33333
B68: =IF($D68="","",B67) -> 7 | C68: =IF($D68="","",C67) -> Tarta Frutillas 24cm | D68: Azúcar impalpable | E68: =IFERROR(VLOOKUP($D68,Insumos!$B:$U,D$1,0),"") -> Grs | F68: 120 | G68: =IFERROR(VLOOKUP($D68,Insumos!$B:$U,G$1,0)/VLOOKUP($D68,Insumos!$B:$U,F$1,0),"") -> 1.5 | H68: =IFERROR(F68*G68,"") -> 180
B69: =IF($D69="","",B68) -> 7 | C69: =IF($D69="","",C68) -> Tarta Frutillas 24cm | D69: Leche | E69: =IFERROR(VLOOKUP($D69,Insumos!$B:$U,D$1,0),"") -> Cm3 | F69: 500 | G69: =IFERROR(VLOOKUP($D69,Insumos!$B:$U,G$1,0)/VLOOKUP($D69,Insumos!$B:$U,F$1,0),"") -> 2.1 | H69: =IFERROR(F69*G69,"") -> 1050
B70: =IF($D70="","",B69) -> 7 | C70: =IF($D70="","",C69) -> Tarta Frutillas 24cm | D70: Azúcar | E70: =IFERROR(VLOOKUP($D70,Insumos!$B:$U,D$1,0),"") -> Grs | F70: 150 | G70: =IFERROR(VLOOKUP($D70,Insumos!$B:$U,G$1,0)/VLOOKUP($D70,Insumos!$B:$U,F$1,0),"") -> 1.4 | H70: =IFERROR(F70*G70,"") -> 210
B71: =IF($D71="","",B70) -> 7 | C71: =IF($D71="","",C70) -> Tarta Frutillas 24cm | D71: Maicena | E71: =IFERROR(VLOOKUP($D71,Insumos!$B:$U,D$1,0),"") -> Grs | F71: 45 | G71: =IFERROR(VLOOKUP($D71,Insumos!$B:$U,G$1,0)/VLOOKUP($D71,Insumos!$B:$U,F$1,0),"") -> 2.8 | H71: =IFERROR(F71*G71,"") -> 126
B72: =IF($D72="","",B71) -> 7 | C72: =IF($D71="","",C70) -> Tarta Frutillas 24cm | D72: Frutilla | E72: =IFERROR(VLOOKUP($D72,Insumos!$B:$U,D$1,0),"") -> Unidad | F72: 500 | G72: =IFERROR(VLOOKUP($D72,Insumos!$B:$U,G$1,0)/VLOOKUP($D72,Insumos!$B:$U,F$1,0),"") -> 4 | H72: =IFERROR(F72*G72,"") -> 2000
B73: 7 | C73: =IF($D71="","",C70) -> Tarta Frutillas 24cm
B74: 8 | C74: Bombas De DDL | D74: Manteca | E74: =IFERROR(VLOOKUP($D74,Insumos!$B:$U,D$1,0),"") -> Grs | F74: 125 | G74: =IFERROR(VLOOKUP($D74,Insumos!$B:$U,G$1,0)/VLOOKUP($D74,Insumos!$B:$U,F$1,0),"") -> 11 | H74: =IFERROR(F74*G74,"") -> 1375
B75: =IF($D75="","",B74) -> 8 | C75: =IF($D75="","",C74) -> Bombas De DDL | D75: Azúcar | E75: =IFERROR(VLOOKUP($D75,Insumos!$B:$U,D$1,0),"") -> Grs | F75: 1 | G75: =IFERROR(VLOOKUP($D75,Insumos!$B:$U,G$1,0)/VLOOKUP($D75,Insumos!$B:$U,F$1,0),"") -> 1.4 | H75: =IFERROR(F75*G75,"") -> 1.4
B76: =IF($D76="","",B75) -> 8 | C76: =IF($D76="","",C75) -> Bombas De DDL | D76: Harina 0000 | E76: =IFERROR(VLOOKUP($D76,Insumos!$B:$U,D$1,0),"") -> Grs | F76: 190 | G76: =IFERROR(VLOOKUP($D76,Insumos!$B:$U,G$1,0)/VLOOKUP($D76,Insumos!$B:$U,F$1,0),"") -> 0.82 | H76: =IFERROR(F76*G76,"") -> 155.8
B77: =IF($D77="","",B76) -> 8 | C77: =IF($D77="","",C76) -> Bombas De DDL | D77: Huevo | E77: =IFERROR(VLOOKUP($D77,Insumos!$B:$U,D$1,0),"") -> Unidad | F77: 5 | G77: =IFERROR(VLOOKUP($D77,Insumos!$B:$U,G$1,0)/VLOOKUP($D77,Insumos!$B:$U,F$1,0),"") -> 166.66667 | H77: =IFERROR(F77*G77,"") -> 833.33333
B78: =IF($D78="","",B77) -> 8 | C78: =IF($D78="","",C77) -> Bombas De DDL | D78: Dulce de leche | E78: =IFERROR(VLOOKUP($D78,Insumos!$B:$U,D$1,0),"") -> Grs | F78: 500 | G78: =IFERROR(VLOOKUP($D78,Insumos!$B:$U,G$1,0)/VLOOKUP($D78,Insumos!$B:$U,F$1,0),"") -> 3.4 | H78: =IFERROR(F78*G78,"") -> 1700
B79: =IF($D79="","",B78) -> 8 | C79: =IF($D79="","",C78) -> Bombas De DDL | D79: Mangas descartables N°4 | E79: =IFERROR(VLOOKUP($D79,Insumos!$B:$U,D$1,0),"") -> Unidad | F79: 2 | G79: =IFERROR(VLOOKUP($D79,Insumos!$B:$U,G$1,0)/VLOOKUP($D79,Insumos!$B:$U,F$1,0),"") -> 400 | H79: =IFERROR(F79*G79,"") -> 800
B80: =IF($D80="","",B79) -> 8 | C80: =IF($D80="","",C79) -> Bombas De DDL | D80: Chocolate | E80: =IFERROR(VLOOKUP($D80,Insumos!$B:$U,D$1,0),"") -> Grs | F80: 200 | G80: =IFERROR(VLOOKUP($D80,Insumos!$B:$U,G$1,0)/VLOOKUP($D80,Insumos!$B:$U,F$1,0),"") -> 10 | H80: =IFERROR(F80*G80,"") -> 2000
B81: 9 | C81: bombas De Crema | D81: Manteca | E81: =IFERROR(VLOOKUP($D81,Insumos!$B:$U,D$1,0),"") -> Grs | F81: 125 | G81: =IFERROR(VLOOKUP($D81,Insumos!$B:$U,G$1,0)/VLOOKUP($D81,Insumos!$B:$U,F$1,0),"") -> 11 | H81: =IFERROR(F81*G81,"") -> 1375
B82: =IF($D82="","",B81) -> 9 | C82: =IF($D82="","",C81) -> bombas De Crema | D82: Azúcar | E82: =IFERROR(VLOOKUP($D82,Insumos!$B:$U,D$1,0),"") -> Grs | F82: 1 | G82: =IFERROR(VLOOKUP($D82,Insumos!$B:$U,G$1,0)/VLOOKUP($D82,Insumos!$B:$U,F$1,0),"") -> 1.4 | H82: =IFERROR(F82*G82,"") -> 1.4
B83: =IF($D83="","",B82) -> 9 | C83: =IF($D83="","",C82) -> bombas De Crema | D83: Harina 0000 | E83: =IFERROR(VLOOKUP($D83,Insumos!$B:$U,D$1,0),"") -> Grs | F83: 190 | G83: =IFERROR(VLOOKUP($D83,Insumos!$B:$U,G$1,0)/VLOOKUP($D83,Insumos!$B:$U,F$1,0),"") -> 0.82 | H83: =IFERROR(F83*G83,"") -> 155.8
B84: =IF($D84="","",B83) -> 9 | C84: =IF($D84="","",C83) -> bombas De Crema | D84: Huevo | E84: =IFERROR(VLOOKUP($D84,Insumos!$B:$U,D$1,0),"") -> Unidad | F84: 5 | G84: =IFERROR(VLOOKUP($D84,Insumos!$B:$U,G$1,0)/VLOOKUP($D84,Insumos!$B:$U,F$1,0),"") -> 166.66667 | H84: =IFERROR(F84*G84,"") -> 833.33333
B85: =IF($D85="","",B84) -> 9 | C85: =IF($D85="","",C84) -> bombas De Crema | D85: Crema de leche | E85: =IFERROR(VLOOKUP($D85,Insumos!$B:$U,D$1,0),"") -> Grs | F85: 200 | G85: =IFERROR(VLOOKUP($D85,Insumos!$B:$U,G$1,0)/VLOOKUP($D85,Insumos!$B:$U,F$1,0),"") -> 9.2 | H85: =IFERROR(F85*G85,"") -> 1840
B86: =IF($D86="","",B85) -> 9 | C86: =IF($D86="","",C85) -> bombas De Crema | D86: Mangas descartables N°4 | E86: =IFERROR(VLOOKUP($D86,Insumos!$B:$U,D$1,0),"") -> Unidad | F86: 2 | G86: =IFERROR(VLOOKUP($D86,Insumos!$B:$U,G$1,0)/VLOOKUP($D86,Insumos!$B:$U,F$1,0),"") -> 400 | H86: =IFERROR(F86*G86,"") -> 800
B87: =IF($D87="","",B86) -> 9 | C87: =IF($D87="","",C86) -> bombas De Crema | D87: Chocolate | E87: =IFERROR(VLOOKUP($D87,Insumos!$B:$U,D$1,0),"") -> Grs | F87: 200 | G87: =IFERROR(VLOOKUP($D87,Insumos!$B:$U,G$1,0)/VLOOKUP($D87,Insumos!$B:$U,F$1,0),"") -> 10 | H87: =IFERROR(F87*G87,"") -> 2000
B88: 10 | C88: Cookies Chips Chocolatesx15 | D88: Manteca | E88: =IFERROR(VLOOKUP($D88,Insumos!$B:$U,D$1,0),"") -> Grs | F88: 125 | G88: =IFERROR(VLOOKUP($D88,Insumos!$B:$U,G$1,0)/VLOOKUP($D88,Insumos!$B:$U,F$1,0),"") -> 11 | H88: =IFERROR(F88*G88,"") -> 1375
B89: 10 | C89: =IF($D89="","",C88) -> Cookies Chips Chocolatesx15 | D89: Azúcar | E89: =IFERROR(VLOOKUP($D89,Insumos!$B:$U,D$1,0),"") -> Grs | F89: 125 | G89: =IFERROR(VLOOKUP($D89,Insumos!$B:$U,G$1,0)/VLOOKUP($D89,Insumos!$B:$U,F$1,0),"") -> 1.4 | H89: =IFERROR(F89*G89,"") -> 175
B90: =IF($D90="","",B89) -> 10 | C90: =IF($D90="","",C89) -> Cookies Chips Chocolatesx15 | D90: huevo | E90: =IFERROR(VLOOKUP($D90,Insumos!$B:$U,D$1,0),"") -> Unidad | F90: 1 | G90: =IFERROR(VLOOKUP($D90,Insumos!$B:$U,G$1,0)/VLOOKUP($D90,Insumos!$B:$U,F$1,0),"") -> 166.66667 | H90: =IFERROR(F90*G90,"") -> 166.66667
B91: =IF($D91="","",B90) -> 10 | C91: =IF($D91="","",C90) -> Cookies Chips Chocolatesx15 | D91: Harina 0000 | E91: =IFERROR(VLOOKUP($D91,Insumos!$B:$U,D$1,0),"") -> Grs | F91: 250 | G91: =IFERROR(VLOOKUP($D91,Insumos!$B:$U,G$1,0)/VLOOKUP($D91,Insumos!$B:$U,F$1,0),"") -> 0.82 | H91: =IFERROR(F91*G91,"") -> 205
B92: =IF($D92="","",B91) -> 10 | C92: =IF($D92="","",C91) -> Cookies Chips Chocolatesx15 | D92: Polvo de hornear | E92: =IFERROR(VLOOKUP($D92,Insumos!$B:$U,D$1,0),"") -> Grs | F92: 15 | G92: =IFERROR(VLOOKUP($D92,Insumos!$B:$U,G$1,0)/VLOOKUP($D92,Insumos!$B:$U,F$1,0),"") -> 8 | H92: =IFERROR(F92*G92,"") -> 120
B93: =IF($D93="","",B91) -> 10 | C93: =IF($D93="","",C92) -> Cookies Chips Chocolatesx15 | D93: Esencia de vainilla | E93: =IFERROR(VLOOKUP($D93,Insumos!$B:$U,D$1,0),"") -> Cm3 | F93: 1 | G93: =IFERROR(VLOOKUP($D93,Insumos!$B:$U,G$1,0)/VLOOKUP($D93,Insumos!$B:$U,F$1,0),"") -> 1.52 | H93: =IFERROR(F93*G93,"") -> 1.52
B94: =IF($D94="","",B93) -> 10 | C94: =IF($D94="","",C93) -> Cookies Chips Chocolatesx15 | D94: Chips de chocolate | E94: =IFERROR(VLOOKUP($D94,Insumos!$B:$U,D$1,0),"") -> Grs | F94: 40 | G94: =IFERROR(VLOOKUP($D94,Insumos!$B:$U,G$1,0)/VLOOKUP($D94,Insumos!$B:$U,F$1,0),"") -> 9 | H94: =IFERROR(F94*G94,"") -> 360
B95: =IF($D95="","",B94) -> 10 | C95: =IF($D95="","",C94) -> Cookies Chips Chocolatesx15 | D95: Bolsa 40x30 | E95: =IFERROR(VLOOKUP($D95,Insumos!$B:$U,D$1,0),"") -> Unidad | F95: 1 | G95: =IFERROR(VLOOKUP($D95,Insumos!$B:$U,G$1,0)/VLOOKUP($D95,Insumos!$B:$U,F$1,0),"") -> 7.94 | H95: =IFERROR(F95*G95,"") -> 7.94
B96: 11 | C96: Alfajores de Nuez x12 | D96: Huevo | E96: =IFERROR(VLOOKUP($D96,Insumos!$B:$U,D$1,0),"") -> Unidad | F96: 1 | G96: =IFERROR(VLOOKUP($D96,Insumos!$B:$U,G$1,0)/VLOOKUP($D96,Insumos!$B:$U,F$1,0),"") -> 166.66667 | H96: =IFERROR(F96*G96,"") -> 166.66667
B97: =IF($D97="","",B96) -> 11 | C97: =IF($D97="","",C96) -> Alfajores de Nuez x12 | D97: Azúcar | E97: =IFERROR(VLOOKUP($D97,Insumos!$B:$U,D$1,0),"") -> Grs | F97: 75 | G97: =IFERROR(VLOOKUP($D97,Insumos!$B:$U,G$1,0)/VLOOKUP($D97,Insumos!$B:$U,F$1,0),"") -> 1.4 | H97: =IFERROR(F97*G97,"") -> 105
B98: =IF($D98="","",B97) -> 11 | C98: =IF($D98="","",C97) -> Alfajores de Nuez x12 | D98: Manteca | E98: =IFERROR(VLOOKUP($D98,Insumos!$B:$U,D$1,0),"") -> Grs | F98: 75 | G98: =IFERROR(VLOOKUP($D98,Insumos!$B:$U,G$1,0)/VLOOKUP($D98,Insumos!$B:$U,F$1,0),"") -> 11 | H98: =IFERROR(F98*G98,"") -> 825
B99: =IF($D99="","",B98) -> 11 | C99: =IF($D99="","",C98) -> Alfajores de Nuez x12 | D99: Harina 0000 | E99: =IFERROR(VLOOKUP($D99,Insumos!$B:$U,D$1,0),"") -> Grs | F99: 75 | G99: =IFERROR(VLOOKUP($D99,Insumos!$B:$U,G$1,0)/VLOOKUP($D99,Insumos!$B:$U,F$1,0),"") -> 0.82 | H99: =IFERROR(F99*G99,"") -> 61.5
B100: =IF($D100="","",B99) -> 11 | C100: =IF($D100="","",C99) -> Alfajores de Nuez x12 | D100: Polvo de hornear | E100: =IFERROR(VLOOKUP($D100,Insumos!$B:$U,D$1,0),"") -> Grs | F100: 10 | G100: =IFERROR(VLOOKUP($D100,Insumos!$B:$U,G$1,0)/VLOOKUP($D100,Insumos!$B:$U,F$1,0),"") -> 8 | H100: =IFERROR(F100*G100,"") -> 80
...

Sheet Costo x Articulo
B2: Nro. | C2: Artículo | D2: Precio | E2: Bar | F2: Precio de venta recomendado 200% | G2: Costo total | H2: Ganancia Recomendada | I2: Precio de venta | J2: Ganancia | K2: Margen | L2: Doble puro | M2: Promo x2 | N2: Precio unitario promo | O2: Ganancia por unidad promo
B3: 1 | C3: =TEXT(IFERROR(VLOOKUP($B3,Recetas!$B:$C,2,0),""),) -> Budín de limón | D3: 10000 | E3: x | F3: =IFERROR(G3*(1+200%),0) -> 16674.2 | G3: =IF(C3="","",SUMIF(Recetas!$B:$B,'Costo x Articulo'!$B3,Recetas!$H:$H)) -> 5558.0667 | H3: =IFERROR(F3-G3,0) -> 11116.133 | I3: 4100 | J3: =IF(I3="","",I3-G3) -> -1458.0667 | K3: =IFERROR(J3/G3,"") -> -0.26233343
B4: 2 | C4: =TEXT(IFERROR(VLOOKUP($B4,Recetas!$B:$C,2,0),""),) -> Macarrons x 12 unidades | D4: 7000 | E4: x | F4: =IFERROR(G4*(1+200%),0) -> 10173.4 | G4: =IF(C4="","",SUMIF(Recetas!$B:$B,'Costo x Articulo'!$B4,Recetas!$H:$H)) -> 3391.1333 | H4: =IFERROR(F4-G4,0) -> 6782.2667 | I4: 2700 | J4: =IF(I4="","",I4-G4) -> -691.13333 | K4: =IFERROR(J4/G4,"") -> -0.203806
B5: 3 | C5: =TEXT(IFERROR(VLOOKUP($B5,Recetas!$B:$C,2,0),""),) -> Lemon pie 24cm | D5: 16000 | E5: x | F5: =IFERROR(G5*(1+200%),0) -> 27370.6 | G5: =IF(C5="","",SUMIF(Recetas!$B:$B,'Costo x Articulo'!$B5,Recetas!$H:$H)) -> 9123.5333 | H5: =IFERROR(F5-G5,0) -> 18247.067 | I5: 7300 | J5: =IF(I5="","",I5-G5) -> -1823.5333 | K5: =IFERROR(J5/G5,"") -> -0.19987139
B6: 4 | C6: =TEXT(IFERROR(VLOOKUP($B6,Recetas!$B:$C,2,0),""),) -> Lemon pie 12cm | F6: =IFERROR(G6*(1+200%),0) -> 13685.3 | G6: =IF(C6="","",SUMIF(Recetas!$B:$B,'Costo x Articulo'!$B6,Recetas!$H:$H)) -> 4561.7667 | H6: =IFERROR(F6-G6,0) -> 9123.5333 | I6: 2700 | J6: =IF(I6="","",I6-G6) -> -1861.7667 | K6: =IFERROR(J6/G6,"") -> -0.40812405
B7: 5 | C7: =TEXT(IFERROR(VLOOKUP($B7,Recetas!$B:$C,2,0),""),) -> Brownie 20x20cm | F7: =IFERROR(G7*(1+200%),0) -> 22591.983 | G7: =IF(C7="","",SUMIF(Recetas!$B:$B,'Costo x Articulo'!$B7,Recetas!$H:$H)) -> 7530.6611 | H7: =IFERROR(F7-G7,0) -> 15061.322 | I7: 4500 | J7: =IF(I7="","",I7-G7) -> -3030.6611 | K7: =IFERROR(J7/G7,"") -> -0.4024429
B8: 6 | C8: =TEXT(IFERROR(VLOOKUP($B8,Recetas!$B:$C,2,0),""),) -> Torta brownie 20x20cm | D8: 20000 | E8: x | F8: =IFERROR(G8*(1+200%),0) -> 30699.983 | G8: =IF(C8="","",SUMIF(Recetas!$B:$B,'Costo x Articulo'!$B8,Recetas!$H:$H)) -> 10233.328 | H8: =IFERROR(F8-G8,0) -> 20466.656 | I8: 7000 | J8: =IF(I8="","",I8-G8) -> -3233.3278 | K8: =IFERROR(J8/G8,"") -> -0.31596054
B9: 7 | C9: =TEXT(IFERROR(VLOOKUP($B9,Recetas!$B:$C,2,0),""),) -> Tarta Frutillas 24cm | F9: =IFERROR(G9*(1+200%),0) -> 18376 | G9: =IF(C9="","",SUMIF(Recetas!$B:$B,'Costo x Articulo'!$B9,Recetas!$H:$H)) -> 6125.3333 | H9: =IFERROR(F9-G9,0) -> 12250.667 | I9: 5100 | J9: =IF(I9="","",I9-G9) -> -1025.3333 | K9: =IFERROR(J9/G9,"") -> -0.16739225
B10: 8 | C10: =TEXT(IFERROR(VLOOKUP($B10,Recetas!$B:$C,2,0),""),) -> Bombas De DDL | F10: =IFERROR(G10*(1+200%),0) -> 20596.6 | G10: =IF(C10="","",SUMIF(Recetas!$B:$B,'Costo x Articulo'!$B10,Recetas!$H:$H)) -> 6865.5333 | H10: =IFERROR(F10-G10,0) -> 13731.067 | I10: 5400 | J10: =IF(I10="","",I10-G10) -> -1465.5333 | K10: =IFERROR(J10/G10,"") -> -0.21346242
B11: 9 | C11: =TEXT(IFERROR(VLOOKUP($B11,Recetas!$B:$C,2,0),""),) -> bombas De Crema | F11: =IFERROR(G11*(1+200%),0) -> 21016.6 | G11: =IF(C11="","",SUMIF(Recetas!$B:$B,'Costo x Articulo'!$B11,Recetas!$H:$H)) -> 7005.5333 | H11: =IFERROR(F11-G11,0) -> 14011.067 | I11: 5200 | J11: =IF(I11="","",I11-G11) -> -1805.5333 | K11: =IFERROR(J11/G11,"") -> -0.2577296
B12: 10 | C12: =TEXT(IFERROR(VLOOKUP($B12,Recetas!$B:$C,2,0),""),) -> Cookies Chips Chocolatesx15 | D12: 4500 | E12: x | F12: =IFERROR(G12*(1+200%),0) -> 7233.38 | G12: =IF(C12="","",SUMIF(Recetas!$B:$B,'Costo x Articulo'!$B12,Recetas!$H:$H)) -> 2411.1267 | H12: =IFERROR(F12-G12,0) -> 4822.2533 | I12: 1800 | J12: =IF(I12="","",I12-G12) -> -611.12667 | K12: =IFERROR(J12/G12,"") -> -0.25346104
B13: 11 | C13: =TEXT(IFERROR(VLOOKUP($B13,Recetas!$B:$C,2,0),""),) -> Alfajores de Nuez x12 | D13: 8000 | E13: x | F13: =IFERROR(G13*(1+200%),0) -> 10929.5 | G13: =IF(C13="","",SUMIF(Recetas!$B:$B,'Costo x Articulo'!$B13,Recetas!$H:$H)) -> 3643.1667 | H13: =IFERROR(F13-G13,0) -> 7286.3333 | I13: 3300 | J13: =IF(I13="","",I13-G13) -> -343.16667 | K13: =IFERROR(J13/G13,"") -> -0.094194611
B14: 12 | C14: =TEXT(IFERROR(VLOOKUP($B14,Recetas!$B:$C,2,0),""),) -> Tarta de Coco | F14: =IFERROR(G14*(1+200%),0) -> 28632.35 | G14: =IF(C14="","",SUMIF(Recetas!$B:$B,'Costo x Articulo'!$B14,Recetas!$H:$H)) -> 9544.1167 | H14: =IFERROR(F14-G14,0) -> 19088.233 | I14: 6700 | J14: =IF(I14="","",I14-G14) -> -2844.1167 | K14: =IFERROR(J14/G14,"") -> -0.29799685
B15: 13 | C15: =TEXT(IFERROR(VLOOKUP($B15,Recetas!$B:$C,2,0),""),) -> Selva Negra 20 cm | F15: =IFERROR(G15*(1+200%),0) -> 34123.35 | G15: =IF(C15="","",SUMIF(Recetas!$B:$B,'Costo x Articulo'!$B15,Recetas!$H:$H)) -> 11374.45 | H15: =IFERROR(F15-G15,0) -> 22748.9 | I15: 8700 | J15: =IF(I15="","",I15-G15) -> -2674.45 | K15: =IFERROR(J15/G15,"") -> -0.23512785
B16: 14 | C16: =TEXT(IFERROR(VLOOKUP($B16,Recetas!$B:$C,2,0),""),) -> Tiramisu | F16: =IFERROR(G16*(1+200%),0) -> 48748.568 | G16: =IF(C16="","",SUMIF(Recetas!$B:$B,'Costo x Articulo'!$B16,Recetas!$H:$H)) -> 16249.523 | H16: =IFERROR(F16-G16,0) -> 32499.045 | I16: 5100 | J16: =IF(I16="","",I16-G16) -> -11149.523 | K16: =IFERROR(J16/G16,"") -> -0.68614463
B17: 15 | C17: =TEXT(IFERROR(VLOOKUP($B17,Recetas!$B:$C,2,0),""),) -> Cheese Cake 18cm | F17: =IFERROR(G17*(1+200%),0) -> 28119.299 | G17: =IF(C17="","",SUMIF(Recetas!$B:$B,'Costo x Articulo'!$B17,Recetas!$H:$H)) -> 9373.0996 | H17: =IFERROR(F17-G17,0) -> 18746.199 | I17: 4100 | J17: =IF(I17="","",I17-G17) -> -5273.0996 | K17: =IFERROR(J17/G17,"") -> -0.562578
B18: 16 | C18: =TEXT(IFERROR(VLOOKUP($B18,Recetas!$B:$C,2,0),""),) -> Rogel | F18: =IFERROR(G18*(1+200%),0) -> 30949.15 | G18: =IF(C18="","",SUMIF(Recetas!$B:$B,'Costo x Articulo'!$B18,Recetas!$H:$H)) -> 10316.383 | H18: =IFERROR(F18-G18,0) -> 20632.767 | I18: 8300 | J18: =IF(I18="","",I18-G18) -> -2016.3833 | K18: =IFERROR(J18/G18,"") -> -0.19545448
B19: 17 | C19: =TEXT(IFERROR(VLOOKUP($B19,Recetas!$B:$C,2,0),""),) -> Cheese Cake DDL 18cm | F19: =IFERROR(G19*(1+200%),0) -> 28072.512 | G19: =IF(C19="","",SUMIF(Recetas!$B:$B,'Costo x Articulo'!$B19,Recetas!$H:$H)) -> 9357.504 | H19: =IFERROR(F19-G19,0) -> 18715.008 | I19: 4100 | J19: =IF(I19="","",I19-G19) -> -5257.504 | K19: =IFERROR(J19/G19,"") -> -0.56184897
B20: 18 | C20: =TEXT(IFERROR(VLOOKUP($B20,Recetas!$B:$C,2,0),""),) -> Pastafrola | F20: =IFERROR(G20*(1+200%),0) -> 18075.35 | G20: =IF(C20="","",SUMIF(Recetas!$B:$B,'Costo x Articulo'!$B20,Recetas!$H:$H)) -> 6025.1167 | H20: =IFERROR(F20-G20,0) -> 12050.233 | I20: 2900 | J20: =IF(I20="","",I20-G20) -> -3125.1167 | K20: =IFERROR(J20/G20,"") -> -0.51868152
B21: 19 | C21: =TEXT(IFERROR(VLOOKUP($B21,Recetas!$B:$C,2,0),""),) -> Tarta Ricota | F21: =IFERROR(G21*(1+200%),0) -> 24660.35 | G21: =IF(C21="","",SUMIF(Recetas!$B:$B,'Costo x Articulo'!$B21,Recetas!$H:$H)) -> 8220.1167 | H21: =IFERROR(F21-G21,0) -> 16440.233 | I21: 4500 | J21: =IF(I21="","",I21-G21) -> -3720.1167 | K21: =IFERROR(J21/G21,"") -> -0.45256251
B22: 20 | C22: =TEXT(IFERROR(VLOOKUP($B22,Recetas!$B:$C,2,0),""),) -> Tarta Frutos Secos | F22: =IFERROR(G22*(1+200%),0) -> 27530.75 | G22: =IF(C22="","",SUMIF(Recetas!$B:$B,'Costo x Articulo'!$B22,Recetas!$H:$H)) -> 9176.9167 | H22: =IFERROR(F22-G22,0) -> 18353.833 | I22: 7500 | J22: =IF(I22="","",I22-G22) -> -1676.9167 | K22: =IFERROR(J22/G22,"") -> -0.18273204
B23: 21 | C23: =TEXT(IFERROR(VLOOKUP($B23,Recetas!$B:$C,2,0),""),) -> Alfajor Marplatense | F23: =IFERROR(G23*(1+200%),0) -> 27365.18 | G23: =IF(C23="","",SUMIF(Recetas!$B:$B,'Costo x Articulo'!$B23,Recetas!$H:$H)) -> 9121.7267 | H23: =IFERROR(F23-G23,0) -> 18243.453 | I23: 6800 | J23: =IF(I23="","",I23-G23) -> -2321.7267 | K23: =IFERROR(J23/G23,"") -> -0.2545271
B24: 22 | C24: =TEXT(IFERROR(VLOOKUP($B24,Recetas!$B:$C,2,0),""),) -> Alfajor Maicena | F24: =IFERROR(G24*(1+200%),0) -> 16863.59 | G24: =IF(C24="","",SUMIF(Recetas!$B:$B,'Costo x Articulo'!$B24,Recetas!$H:$H)) -> 5621.1967 | H24: =IFERROR(F24-G24,0) -> 11242.393 | I24: 2500 | J24: =IF(I24="","",I24-G24) -> -3121.1967 | K24: =IFERROR(J24/G24,"") -> -0.55525484
B25: 23 | C25: =TEXT(IFERROR(VLOOKUP($B25,Recetas!$B:$C,2,0),""),) -> Tarta de Manzana 22cm | D25: 13000 | E25: x | F25: =IFERROR(G25*(1+200%),0) -> 20118.35 | G25: =IF(C25="","",SUMIF(Recetas!$B:$B,'Costo x Articulo'!$B25,Recetas!$H:$H)) -> 6706.1167 | H25: =IFERROR(F25-G25,0) -> 13412.233 | I25: 5600 | J25: =IF(I25="","",I25-G25) -> -1106.1167 | K25: =IFERROR(J25/G25,"") -> -0.16494146
B26: 24 | C26: =TEXT(IFERROR(VLOOKUP($B26,Recetas!$B:$C,2,0),""),) -> Chocotorta Redonda | F26: =IFERROR(G26*(1+200%),0) -> 48885.179 | G26: =IF(C26="","",SUMIF(Recetas!$B:$B,'Costo x Articulo'!$B26,Recetas!$H:$H)) -> 16295.06 | H26: =IFERROR(F26-G26,0) -> 32590.119 | I26: 8100 | J26: =IF(I26="","",I26-G26) -> -8195.0595 | K26: =IFERROR(J26/G26,"") -> -0.50291682
B27: 25 | C27: =TEXT(IFERROR(VLOOKUP($B27,Recetas!$B:$C,2,0),""),) -> Doble Cake | F27: =IFERROR(G27*(1+200%),0) -> 62970.109 | G27: =IF(C27="","",SUMIF(Recetas!$B:$B,'Costo x Articulo'!$B27,Recetas!$H:$H)) -> 20990.036 | H27: =IFERROR(F27-G27,0) -> 41980.073 | I27: 12100 | J27: =IF(I27="","",I27-G27) -> -8890.0363 | K27: =IFERROR(J27/G27,"") -> -0.42353601
B28: 26 | C28: =TEXT(IFERROR(VLOOKUP($B28,Recetas!$B:$C,2,0),""),) -> Des- DIA DE LA MADRE | F28: =IFERROR(G28*(1+200%),0) -> 957 | G28: =IF(C28="","",SUMIF(Recetas!$B:$B,'Costo x Articulo'!$B28,Recetas!$H:$H)) -> 319 | H28: =IFERROR(F28-G28,0) -> 638 | I28: 1500 | J28: =IF(I28="","",I28-G28) -> 1181 | K28: =IFERROR(J28/G28,"") -> 3.7021944
B29: 27 | C29: =TEXT(IFERROR(VLOOKUP($B29,Recetas!$B:$C,2,0),""),) -> Desayuno 108 | F29: =IFERROR(G29*(1+200%),0) -> 30377.64 | G29: =IF(C29="","",SUMIF(Recetas!$B:$B,'Costo x Articulo'!$B29,Recetas!$H:$H)) -> 10125.88 | H29: =IFERROR(F29-G29,0) -> 20251.76 | I29: 480 | J29: =IF(I29="","",I29-G29) -> -9645.88 | K29: =IFERROR(J29/G29,"") -> -0.95259671 | L29: =#REF!*120 -> #REF!
B30: 28 | C30: =TEXT(IFERROR(VLOOKUP($B30,Recetas!$B:$C,2,0),""),) -> Cookies decoradas x 12u | F30: =IFERROR(G30*(1+200%),0) -> 19228 | G30: =IF(C30="","",SUMIF(Recetas!$B:$B,'Costo x Articulo'!$B30,Recetas!$H:$H)) -> 6409.3333 | H30: =IFERROR(F30-G30,0) -> 12818.667 | I30: 10000 | J30: =IF(I30="","",I30-G30) -> 3590.6667 | K30: =IFERROR(J30/G30,"") -> 0.56022467
B31: 29 | C31: =TEXT(IFERROR(VLOOKUP($B31,Recetas!$B:$C,2,0),""),) -> Chipa 1/2 kg | F31: =IFERROR(G31*(1+200%),0) -> 24577 | G31: =IF(C31="","",SUMIF(Recetas!$B:$B,'Costo x Articulo'!$B31,Recetas!$H:$H)) -> 8192.3333 | H31: =IFERROR(F31-G31,0) -> 16384.667 | I31: 2500 | J31: =IF(I31="","",I31-G31) -> -5692.3333 | K31: =IFERROR(J31/G31,"") -> -0.69483664
B32: 30 | C32: =TEXT(IFERROR(VLOOKUP($B32,Recetas!$B:$C,2,0),""),) -> Pan Saborizado | F32: =IFERROR(G32*(1+200%),0) -> 1967.1 | G32: =IF(C32="","",SUMIF(Recetas!$B:$B,'Costo x Articulo'!$B32,Recetas!$H:$H)) -> 655.7 | H32: =IFERROR(F32-G32,0) -> 1311.4 | I32: 800 | J32: =IF(I32="","",I32-G32) -> 144.3 | K32: =IFERROR(J32/G32,"") -> 0.22007015
B33: 31 | C33: =TEXT(IFERROR(VLOOKUP($B33,Recetas!$B:$C,2,0),""),) -> Pan Trenzado | F33: =IFERROR(G33*(1+200%),0) -> 3662 | G33: =IF(C33="","",SUMIF(Recetas!$B:$B,'Costo x Articulo'!$B33,Recetas!$H:$H)) -> 1220.6667 | H33: =IFERROR(F33-G33,0) -> 2441.3333 | I33: 1000 | J33: =IF(I33="","",I33-G33) -> -220.66667 | K33: =IFERROR(J33/G33,"") -> -0.18077553
B34: 32 | C34: =TEXT(IFERROR(VLOOKUP($B34,Recetas!$B:$C,2,0),""),) -> Halloween | F34: =IFERROR(G34*(1+200%),0) -> 22101.142 | G34: =IF(C34="","",SUMIF(Recetas!$B:$B,'Costo x Articulo'!$B34,Recetas!$H:$H)) -> 7367.0472 | H34: =IFERROR(F34-G34,0) -> 14734.094 | J34: =IF(I34="","",I34-G34) | K34: =IFERROR(J34/G34,"") -> 0
B35: 33 | C35: =TEXT(IFERROR(VLOOKUP($B35,Recetas!$B:$C,2,0),""),) -> Frambuesas Grandes | F35: =IFERROR(G35*(1+200%),0) -> 1112 | G35: =IF(C35="","",SUMIF(Recetas!$B:$B,'Costo x Articulo'!$B35,Recetas!$H:$H)) -> 370.66667 | H35: =IFERROR(F35-G35,0) -> 741.33333 | I35: 350 | J35: =IF(I35="","",I35-G35) -> -20.666667 | K35: =IFERROR(J35/G35,"") -> -0.055755396
B36: 34 | C36: =TEXT(IFERROR(VLOOKUP($B36,Recetas!$B:$C,2,0),""),) -> Frambuesas chicas | F36: =IFERROR(G36*(1+200%),0) -> 572 | G36: =IF(C36="","",SUMIF(Recetas!$B:$B,'Costo x Articulo'!$B36,Recetas!$H:$H)) -> 190.66667 | H36: =IFERROR(F36-G36,0) -> 381.33333 | I36: 250 | J36: =IF(I36="","",I36-G36) -> 59.333333 | K36: =IFERROR(J36/G36,"") -> 0.31118881
B37: 35 | C37: =TEXT(IFERROR(VLOOKUP($B37,Recetas!$B:$C,2,0),""),) -> desayuno completo | F37: =IFERROR(G37*(1+200%),0) -> 31093.983 | G37: =IF(C37="","",SUMIF(Recetas!$B:$B,'Costo x Articulo'!$B37,Recetas!$H:$H)) -> 10364.661 | H37: =IFERROR(F37-G37,0) -> 20729.322 | I37: 8000 | J37: =IF(I37="","",I37-G37) -> -2364.6611 | K37: =IFERROR(J37/G37,"") -> -0.2281465
B38: 36 | C38: =TEXT(IFERROR(VLOOKUP($B38,Recetas!$B:$C,2,0),""),) -> Pan Dulce 700 gramos | F38: =IFERROR(G38*(1+200%),0) -> 23033.57 | G38: =IF(C38="","",SUMIF(Recetas!$B:$B,'Costo x Articulo'!$B38,Recetas!$H:$H)) -> 7677.8567 | H38: =IFERROR(F38-G38,0) -> 15355.713 | I38: 5800 | J38: =IF(I38="","",I38-G38) -> -1877.8567 | K38: =IFERROR(J38/G38,"") -> -0.24458084
B39: 37 | C39: =TEXT(IFERROR(VLOOKUP($B39,Recetas!$B:$C,2,0),""),) | F39: =IFERROR(G39*(1+200%),0) -> 0 | G39: =IF(C39="","",SUMIF(Recetas!$B:$B,'Costo x Articulo'!$B39,Recetas!$H:$H)) | H39: =IFERROR(F39-G39,0) -> 0 | I39: 1400 | J39: =IF(I39="","",I39-G39) -> 1400 | K39: =IFERROR(J39/G39,"")
B40: 38 | C40: =TEXT(IFERROR(VLOOKUP($B40,Recetas!$B:$C,2,0),""),) -> Pan Dulce 1 KG | F40: =IFERROR(G40*(1+200%),0) -> 20572.82 | G40: =IF(C40="","",SUMIF(Recetas!$B:$B,'Costo x Articulo'!$B40,Recetas!$H:$H)) -> 6857.6067 | H40: =IFERROR(F40-G40,0) -> 13715.213 | I40: 1600 | J40: =IF(I40="","",I40-G40) -> -5257.6067 | K40: =IFERROR(J40/G40,"") -> -0.76668245
B41: 39 | C41: =TEXT(IFERROR(VLOOKUP($B41,Recetas!$B:$C,2,0),""),) -> box dia del medico | F41: =IFERROR(G41*(1+200%),0) -> 19274.2 | G41: =IF(C41="","",SUMIF(Recetas!$B:$B,'Costo x Articulo'!$B41,Recetas!$H:$H)) -> 6424.7333 | H41: =IFERROR(F41-G41,0) -> 12849.467 | I41: 1900 | J41: =IF(I41="","",I41-G41) -> -4524.7333 | K41: =IFERROR(J41/G41,"") -> -0.70426788
B42: 40 | C42: =TEXT(IFERROR(VLOOKUP($B42,Recetas!$B:$C,2,0),""),) -> San Valentin "te amo" | F42: =IFERROR(G42*(1+200%),0) -> 21454.286 | G42: =IF(C42="","",SUMIF(Recetas!$B:$B,'Costo x Articulo'!$B42,Recetas!$H:$H)) -> 7151.4286 | H42: =IFERROR(F42-G42,0) -> 14302.857 | I42: 900 | J42: =IF(I42="","",I42-G42) -> -6251.4286 | K42: =IFERROR(J42/G42,"") -> -0.87415102
B43: 41 | C43: =TEXT(IFERROR(VLOOKUP($B43,Recetas!$B:$C,2,0),""),) -> San Valentin | F43: =IFERROR(G43*(1+200%),0) -> 35788.295 | G43: =IF(C43="","",SUMIF(Recetas!$B:$B,'Costo x Articulo'!$B43,Recetas!$H:$H)) -> 11929.432 | H43: =IFERROR(F43-G43,0) -> 23858.864 | I43: 2100 | J43: =IF(I43="","",I43-G43) -> -9829.4318 | K43: =IFERROR(J43/G43,"") -> -0.82396479
B44: 42 | C44: =TEXT(IFERROR(VLOOKUP($B44,Recetas!$B:$C,2,0),""),) -> Cheescake 22cm | D44: 20000 | E44: x | F44: =IFERROR(G44*(1+200%),0) -> 45749.796 | G44: =IF(C44="","",SUMIF(Recetas!$B:$B,'Costo x Articulo'!$B44,Recetas!$H:$H)) -> 15249.932 | H44: =IFERROR(F44-G44,0) -> 30499.864 | I44: 8500 | J44: =IF(I44="","",I44-G44) -> -6749.9318 | K44: =IFERROR(J44/G44,"") -> -0.44262046
B45: 43 | C45: =TEXT(IFERROR(VLOOKUP($B45,Recetas!$B:$C,2,0),""),) -> desayuno opcion 3 | F45: =IFERROR(G45*(1+200%),0) -> 42628.823 | G45: =IF(C45="","",SUMIF(Recetas!$B:$B,'Costo x Articulo'!$B45,Recetas!$H:$H)) -> 14209.608 | H45: =IFERROR(F45-G45,0) -> 28419.215 | I45: 8200 | J45: =IF(I45="","",I45-G45) -> -6009.6076 | K45: =IFERROR(J45/G45,"") -> -0.42292566
B46: 44 | C46: =TEXT(IFERROR(VLOOKUP($B46,Recetas!$B:$C,2,0),""),) -> Bizcho 20 cm pasta ballina | F46: =IFERROR(G46*(1+200%),0) -> 49592.8 | G46: =IF(C46="","",SUMIF(Recetas!$B:$B,'Costo x Articulo'!$B46,Recetas!$H:$H)) -> 16530.933 | H46: =IFERROR(F46-G46,0) -> 33061.867 | I46: 9600 | J46: =IF(I46="","",I46-G46) -> -6930.9333 | K46: =IFERROR(J46/G46,"") -> -0.41927054
B47: 45 | C47: =TEXT(IFERROR(VLOOKUP($B47,Recetas!$B:$C,2,0),""),) -> brownie 2 number cake | F47: =IFERROR(G47*(1+200%),0) -> 76313.6 | G47: =IF(C47="","",SUMIF(Recetas!$B:$B,'Costo x Articulo'!$B47,Recetas!$H:$H)) -> 25437.867 | H47: =IFERROR(F47-G47,0) -> 50875.733 | I47: 18600 | J47: =IF(I47="","",I47-G47) -> -6837.8667 | K47: =IFERROR(J47/G47,"") -> -0.26880661
B48: 46 | C48: =TEXT(IFERROR(VLOOKUP($B48,Recetas!$B:$C,2,0),""),) -> Huevos Rellenos N15 chocotorta | F48: =IFERROR(G48*(1+200%),0) -> 22534.571 | G48: =IF(C48="","",SUMIF(Recetas!$B:$B,'Costo x Articulo'!$B48,Recetas!$H:$H)) -> 7511.5238 | H48: =IFERROR(F48-G48,0) -> 15023.048 | I48: 3200 | J48: =IF(I48="","",I48-G48) -> -4311.5238 | K48: =IFERROR(J48/G48,"") -> -0.5739879 | L48: =I48*2 -> 6400 | M48: 5600 | N48: =M48/2 -> 2800 | O48: =N48-G48 -> -4711.5238
B49: 47 | C49: =TEXT(IFERROR(VLOOKUP($B49,Recetas!$B:$C,2,0),""),) -> Pan de Molde de Salvado | F49: =IFERROR(G49*(1+200%),0) -> 3675 | G49: =IF(C49="","",SUMIF(Recetas!$B:$B,'Costo x Articulo'!$B49,Recetas!$H:$H)) -> 1225 | H49: =IFERROR(F49-G49,0) -> 2450 | I49: 350 | J49: =IF(I49="","",I49-G49) -> -875 | K49: =IFERROR(J49/G49,"") -> -0.71428571
B50: 48 | C50: =TEXT(IFERROR(VLOOKUP($B50,Recetas!$B:$C,2,0),""),) -> Ferrero Rocher 20cm | F50: =IFERROR(G50*(1+200%),0) -> 48245.01 | G50: =IF(C50="","",SUMIF(Recetas!$B:$B,'Costo x Articulo'!$B50,Recetas!$H:$H)) -> 16081.67 | H50: =IFERROR(F50-G50,0) -> 32163.34 | I50: 8000 | J50: =IF(I50="","",I50-G50) -> -8081.6698 | K50: =IFERROR(J50/G50,"") -> -0.50253922
B51: 49 | C51: =TEXT(IFERROR(VLOOKUP($B51,Recetas!$B:$C,2,0),""),) -> Torta Buttercream 12 cm | F51: =IFERROR(G51*(1+200%),0) -> 43469.72 | G51: =IF(C51="","",SUMIF(Recetas!$B:$B,'Costo x Articulo'!$B51,Recetas!$H:$H)) -> 14489.907 | H51: =IFERROR(F51-G51,0) -> 28979.813 | I51: 11600 | J51: =IF(I51="","",I51-G51) -> -2889.9067 | K51: =IFERROR(J51/G51,"") -> -0.19944274
B52: 50 | C52: =TEXT(IFERROR(VLOOKUP($B52,Recetas!$B:$C,2,0),""),) -> Balcarce 16 cm | F52: =IFERROR(G52*(1+200%),0) -> 45444.72 | G52: =IF(C52="","",SUMIF(Recetas!$B:$B,'Costo x Articulo'!$B52,Recetas!$H:$H)) -> 15148.24 | H52: =IFERROR(F52-G52,0) -> 30296.48 | I52: 7100 | J52: =IF(I52="","",I52-G52) -> -8048.24 | K52: =IFERROR(J52/G52,"") -> -0.53129869
B53: 51 | C53: =TEXT(IFERROR(VLOOKUP($B53,Recetas!$B:$C,2,0),""),) -> Panes Saborizados 740 gr | F53: =IFERROR(G53*(1+200%),0) -> 4204.8 | G53: =IF(C53="","",SUMIF(Recetas!$B:$B,'Costo x Articulo'!$B53,Recetas!$H:$H)) -> 1401.6 | H53: =IFERROR(F53-G53,0) -> 2803.2 | I53: 1000 | J53: =IF(I53="","",I53-G53) -> -401.6 | K53: =IFERROR(J53/G53,"") -> -0.28652968
B54: 52 | C54: =TEXT(IFERROR(VLOOKUP($B54,Recetas!$B:$C,2,0),""),) -> Mini Budin (redondo) citricio | F54: =IFERROR(G54*(1+200%),0) -> 7536.1 | G54: =IF(C54="","",SUMIF(Recetas!$B:$B,'Costo x Articulo'!$B54,Recetas!$H:$H)) -> 2512.0333 | H54: =IFERROR(F54-G54,0) -> 5024.0667 | I54: 2100 | J54: =IF(I54="","",I54-G54) -> -412.03333 | K54: =IFERROR(J54/G54,"") -> -0.16402383
B55: 53 | C55: =TEXT(IFERROR(VLOOKUP($B55,Recetas!$B:$C,2,0),""),) -> Torta brownie 20cm frutos rojos | F55: =IFERROR(G55*(1+200%),0) -> 43719.983 | G55: =IF(C55="","",SUMIF(Recetas!$B:$B,'Costo x Articulo'!$B55,Recetas!$H:$H)) -> 14573.328 | H55: =IFERROR(F55-G55,0) -> 29146.656 | I55: 9400 | J55: =IF(I55="","",I55-G55) -> -5173.3278 | K55: =IFERROR(J55/G55,"") -> -0.35498603
B56: 54 | C56: =TEXT(IFERROR(VLOOKUP($B56,Recetas!$B:$C,2,0),""),) -> Number Cake 1 número | F56: =IFERROR(G56*(1+200%),0) -> 45558.1 | G56: =IF(C56="","",SUMIF(Recetas!$B:$B,'Costo x Articulo'!$B56,Recetas!$H:$H)) -> 15186.033 | H56: =IFERROR(F56-G56,0) -> 30372.067 | I56: 15000 | J56: =IF(I56="","",I56-G56) -> -186.03333 | K56: =IFERROR(J56/G56,"") -> -0.012250291
B57: 55 | C57: =TEXT(IFERROR(VLOOKUP($B57,Recetas!$B:$C,2,0),""),) -> box pasteleros | F57: =IFERROR(G57*(1+200%),0) -> 11398.22 | G57: =IF(C57="","",SUMIF(Recetas!$B:$B,'Costo x Articulo'!$B57,Recetas!$H:$H)) -> 3799.4067 | H57: =IFERROR(F57-G57,0) -> 7598.8133 | I57: 1100 | J57: =IF(I57="","",I57-G57) -> -2699.4067 | K57: =IFERROR(J57/G57,"") -> -0.71048111
B58: 56 | C58: =TEXT(IFERROR(VLOOKUP($B58,Recetas!$B:$C,2,0),""),) -> Box dia del Padre | F58: =IFERROR(G58*(1+200%),0) -> 3274.4 | G58: =IF(C58="","",SUMIF(Recetas!$B:$B,'Costo x Articulo'!$B58,Recetas!$H:$H)) -> 1091.4667 | H58: =IFERROR(F58-G58,0) -> 2182.9333 | I58: 600 | J58: =IF(I58="","",I58-G58) -> -491.46667 | K58: =IFERROR(J58/G58,"") -> -0.45028097
B59: 57 | C59: =TEXT(IFERROR(VLOOKUP($B59,Recetas!$B:$C,2,0),""),) -> Grisines | F59: =IFERROR(G59*(1+200%),0) -> 1777.5 | G59: =IF(C59="","",SUMIF(Recetas!$B:$B,'Costo x Articulo'!$B59,Recetas!$H:$H)) -> 592.5 | H59: =IFERROR(F59-G59,0) -> 1185 | I59: 250 | J59: =IF(I59="","",I59-G59) -> -342.5 | K59: =IFERROR(J59/G59,"") -> -0.57805907
B60: 58 | C60: =TEXT(IFERROR(VLOOKUP($B60,Recetas!$B:$C,2,0),""),) -> Pastelitos | F60: =IFERROR(G60*(1+200%),0) -> 23565 | G60: =IF(C60="","",SUMIF(Recetas!$B:$B,'Costo x Articulo'!$B60,Recetas!$H:$H)) -> 7855 | H60: =IFERROR(F60-G60,0) -> 15710 | I60: 3600 | J60: =IF(I60="","",I60-G60) -> -4255 | K60: =IFERROR(J60/G60,"") -> -0.54169319
... B63: 61 | C63: =TEXT(IFERROR(VLOOKUP($B63,Recetas!$B:$C,2,0),""),) -> Pan Dulce OREO kilo | F63: =IFERROR(G63*(1+200%),0) -> 31194 | G63: =IF(C63="","",SUMIF(Recetas!$B:$B,'Costo x Articulo'!$B63,Recetas!$H:$H)) -> 10398 | H63: =IFERROR(F63-G63,0) -> 20796 | I63: 2000 | J63: =IF(I63="","",I63-G63) -> -8398 | K63: =IFERROR(J63/G63,"") -> -0.80765532
B64: 62 | C64: =TEXT(IFERROR(VLOOKUP($B64,Recetas!$B:$C,2,0),""),) -> buttercream 20 cm | D64: 35000 | F64: =IFERROR(G64*(1+200%),0) -> 51441 | G64: =IF(C64="","",SUMIF(Recetas!$B:$B,'Costo x Articulo'!$B64,Recetas!$H:$H)) -> 17147 | H64: =IFERROR(F64-G64,0) -> 34294 | I64: 14150 | J64: =IF(I64="","",I64-G64) -> -2997 | K64: =IFERROR(J64/G64,"") -> -0.17478276
B65: 63 | C65: =TEXT(IFERROR(VLOOKUP($B65,Recetas!$B:$C,2,0),""),) | F65: =IFERROR(G65*(1+200%),0) -> 0 | G65: =IF(C65="","",SUMIF(Recetas!$B:$B,'Costo x Articulo'!$B65,Recetas!$H:$H)) | H65: =IFERROR(F65-G65,0) -> 0 | I65: 24950 | J65: =IF(I65="","",I65-G65) -> 24950 | K65: =IFERROR(J65/G65,"")
B66: 64 | C66: =TEXT(IFERROR(VLOOKUP($B66,Recetas!$B:$C,2,0),""),) -> MINI CHEESCAKE | F66: =IFERROR(G66*(1+200%),0) -> 4477.4744 | G66: =IF(C66="","",SUMIF(Recetas!$B:$B,'Costo x Articulo'!$B66,Recetas!$H:$H)) -> 1492.4915 | H66: =IFERROR(F66-G66,0) -> 2984.983 | J66: =IF(I66="","",I66-G66) | K66: =IFERROR(J66/G66,"") -> 0
B67: 65 | C67: =TEXT(IFERROR(VLOOKUP($B67,Recetas!$B:$C,2,0),""),) -> Doble Oreo 22cm | D67: 16000 | E67: x | F67: =IFERROR(G67*(1+200%),0) -> 53745 | G67: =IF(C67="","",SUMIF(Recetas!$B:$B,'Costo x Articulo'!$B67,Recetas!$H:$H)) -> 17915 | H67: =IFERROR(F67-G67,0) -> 35830 | J67: =IF(I67="","",I67-G67) | K67: =IFERROR(J67/G67,"") -> 0
B68: 66 | C68: =TEXT(IFERROR(VLOOKUP($B68,Recetas!$B:$C,2,0),""),) -> Macarrons x 48 unidades | F68: =IFERROR(G68*(1+200%),0) -> 23020.5 | G68: =IF(C68="","",SUMIF(Recetas!$B:$B,'Costo x Articulo'!$B68,Recetas!$H:$H)) -> 7673.5 | H68: =IFERROR(F68-G68,0) -> 15347 | J68: =IF(I68="","",I68-G68) | K68: =IFERROR(J68/G68,"") -> 0
B69: 67 | C69: =TEXT(IFERROR(VLOOKUP($B69,Recetas!$B:$C,2,0),""),) -> Huevos Rellenos N12 chocotorta | F69: =IFERROR(G69*(1+200%),0) -> 18428.857 | G69: =IF(C69="","",SUMIF(Recetas!$B:$B,'Costo x Articulo'!$B69,Recetas!$H:$H)) -> 6142.9524 | H69: =IFERROR(F69-G69,0) -> 12285.905 | I69: 2800 | J69: =IF(I69="","",I69-G69) -> -3342.9524 | K69: =IFERROR(J69/G69,"") -> -0.54419311 | L69: =I69*2 -> 5600 | M69: 4600 | N69: =M69/2 -> 2300 | O69: =N69-G69 -> -3842.9524
B70: 68 | C70: =TEXT(IFERROR(VLOOKUP($B70,Recetas!$B:$C,2,0),""),) -> Huevos Rellenos N15 oreo | F70: =IFERROR(G70*(1+200%),0) -> 25481.282 | G70: =IF(C70="","",SUMIF(Recetas!$B:$B,'Costo x Articulo'!$B70,Recetas!$H:$H)) -> 8493.7607 | H70: =IFERROR(F70-G70,0) -> 16987.521 | I70: 3400 | J70: =IF(I70="","",I70-G70) -> -5093.7607 | K70: =IFERROR(J70/G70,"") -> -0.59970617 | L70: =I70*2 -> 6800 | M70: 6000 | N70: =M70/2 -> 3000 | O70: =N70-G70 -> -5493.7607
B71: 69 | C71: =TEXT(IFERROR(VLOOKUP($B71,Recetas!$B:$C,2,0),""),) -> pizzetas x 12 | F71: =IFERROR(G71*(1+200%),0) -> 3626.3571 | G71: =IF(C71="","",SUMIF(Recetas!$B:$B,'Costo x Articulo'!$B71,Recetas!$H:$H)) -> 1208.7857 | H71: =IFERROR(F71-G71,0) -> 2417.5714 | I71: 400 | J71: =IF(I71="","",I71-G71) -> -808.78571 | K71: =IFERROR(J71/G71,"") -> -0.66908941
B72: 70 | C72: =TEXT(IFERROR(VLOOKUP($B72,Recetas!$B:$C,2,0),""),) -> buttercream 22 cm | D72: 40000 | F72: =IFERROR(G72*(1+200%),0) -> 74409 | G72: =IF(C72="","",SUMIF(Recetas!$B:$B,'Costo x Articulo'!$B72,Recetas!$H:$H)) -> 24803 | H72: =IFERROR(F72-G72,0) -> 49606 | I72: 17700 | J72: =IF(I72="","",I72-G72) -> -7103 | K72: =IFERROR(J72/G72,"") -> -0.28637665
B73: 71 | C73: =TEXT(IFERROR(VLOOKUP($B73,Recetas!$B:$C,2,0),""),) -> PAN de campo | F73: =IFERROR(G73*(1+200%),0) -> 2056.5 | G73: =IF(C73="","",SUMIF(Recetas!$B:$B,'Costo x Articulo'!$B73,Recetas!$H:$H)) -> 685.5 | H73: =IFERROR(F73-G73,0) -> 1371 | I73: 250 | J73: =IF(I73="","",I73-G73) -> -435.5 | K73: =IFERROR(J73/G73,"") -> -0.6353027
B74: 72 | C74: =TEXT(IFERROR(VLOOKUP($B74,Recetas!$B:$C,2,0),""),) -> Carrot Cake 22cm | D74: 13000 | E74: x | F74: =IFERROR(G74*(1+200%),0) -> 16667.857 | G74: =IF(C74="","",SUMIF(Recetas!$B:$B,'Costo x Articulo'!$B74,Recetas!$H:$H)) -> 5555.9524 | H74: =IFERROR(F74-G74,0) -> 11111.905 | I74: 2500 | J74: =IF(I74="","",I74-G74) -> -3055.9524 | K74: =IFERROR(J74/G74,"") -> -0.55003214
B75: 73 | C75: =TEXT(IFERROR(VLOOKUP($B75,Recetas!$B:$C,2,0),""),) -> Masas de manga / masas secas | F75: =IFERROR(G75*(1+200%),0) -> 19860.8 | G75: =IF(C75="","",SUMIF(Recetas!$B:$B,'Costo x Articulo'!$B75,Recetas!$H:$H)) -> 6620.2667 | H75: =IFERROR(F75-G75,0) -> 13240.533 | I75: 2300 | J75: =IF(I75="","",I75-G75) -> -4320.2667 | K75: =IFERROR(J75/G75,"") -> -0.65258197
B76: 74 | C76: =TEXT(IFERROR(VLOOKUP($B76,Recetas!$B:$C,2,0),""),) -> Heladitos x 6 | F76: =IFERROR(G76*(1+200%),0) -> 68102 | G76: =IF(C76="","",SUMIF(Recetas!$B:$B,'Costo x Articulo'!$B76,Recetas!$H:$H)) -> 22700.667 | H76: =IFERROR(F76-G76,0) -> 45401.333 | I76: 4300 | J76: =IF(I76="","",I76-G76) -> -18400.667 | K76: =IFERROR(J76/G76,"") -> -0.81057825
B77: 75 | C77: =TEXT(IFERROR(VLOOKUP($B77,Recetas!$B:$C,2,0),""),) -> mini torta oreo VEGANA | F77: =IFERROR(G77*(1+200%),0) -> 17935.082 | G77: =IF(C77="","",SUMIF(Recetas!$B:$B,'Costo x Articulo'!$B77,Recetas!$H:$H)) -> 5978.3607 | H77: =IFERROR(F77-G77,0) -> 11956.721 | I77: 2300 | J77: =IF(I77="","",I77-G77) -> -3678.3607 | K77: =IFERROR(J77/G77,"") -> -0.61527915
B78: 76 | C78: =TEXT(IFERROR(VLOOKUP($B78,Recetas!$B:$C,2,0),""),) -> muffins decorados con pasta | F78: =IFERROR(G78*(1+200%),0) -> 44980.6 | G78: =IF(C78="","",SUMIF(Recetas!$B:$B,'Costo x Articulo'!$B78,Recetas!$H:$H)) -> 14993.533 | H78: =IFERROR(F78-G78,0) -> 29987.067 | I78: 10200 | J78: =IF(I78="","",I78-G78) -> -4793.5333 | K78: =IFERROR(J78/G78,"") -> -0.31970672
B79: 77 | C79: =TEXT(IFERROR(VLOOKUP($B79,Recetas!$B:$C,2,0),""),) -> cookies chips de chocolate 12 | F79: =IFERROR(G79*(1+200%),0) -> 6987.8 | G79: =IF(C79="","",SUMIF(Recetas!$B:$B,'Costo x Articulo'!$B79,Recetas!$H:$H)) -> 2329.2667 | H79: =IFERROR(F79-G79,0) -> 4658.5333 | I79: 2100 | J79: =IF(I79="","",I79-G79) -> -229.26667 | K79: =IFERROR(J79/G79,"") -> -0.09842869
B80: 78 | C80: =TEXT(IFERROR(VLOOKUP($B80,Recetas!$B:$C,2,0),""),) -> DESAYUNO MINI TORTA | F80: =IFERROR(G80*(1+200%),0) -> 84977.25 | G80: =IF(C80="","",SUMIF(Recetas!$B:$B,'Costo x Articulo'!$B80,Recetas!$H:$H)) -> 28325.75 | H80: =IFERROR(F80-G80,0) -> 56651.5 | I80: 12200 | J80: =IF(I80="","",I80-G80) -> -16125.75 | K80: =IFERROR(J80/G80,"") -> -0.56929649
B81: 79 | C81: =TEXT(IFERROR(VLOOKUP($B81,Recetas!$B:$C,2,0),""),) -> CHOCOTORTA CON DECO EN CHOCO | F81: =IFERROR(G81*(1+200%),0) -> 73009.714 | G81: =IF(C81="","",SUMIF(Recetas!$B:$B,'Costo x Articulo'!$B81,Recetas!$H:$H)) -> 24336.571 | H81: =IFERROR(F81-G81,0) -> 48673.143 | I81: 16000 | J81: =IF(I81="","",I81-G81) -> -8336.5714 | K81: =IFERROR(J81/G81,"") -> -0.34255324
B82: 80 | C82: =TEXT(IFERROR(VLOOKUP($B82,Recetas!$B:$C,2,0),""),) -> muffins sin tacc 12 u. | F82: =IFERROR(G82*(1+200%),0) -> 11282.8 | G82: =IF(C82="","",SUMIF(Recetas!$B:$B,'Costo x Articulo'!$B82,Recetas!$H:$H)) -> 3760.9333 | H82: =IFERROR(F82-G82,0) -> 7521.8667 | I82: 1500 | J82: =IF(I82="","",I82-G82) -> -2260.9333 | K82: =IFERROR(J82/G82,"") -> -0.60116283
B83: 81 | C83: =TEXT(IFERROR(VLOOKUP($B83,Recetas!$B:$C,2,0),""),) -> masa para tartas dulces Sin tacc | F83: =IFERROR(G83*(1+200%),0) -> 15662.8 | G83: =IF(C83="","",SUMIF(Recetas!$B:$B,'Costo x Articulo'!$B83,Recetas!$H:$H)) -> 5220.9333 | H83: =IFERROR(F83-G83,0) -> 10441.867 | I83: 4300 | J83: =IF(I83="","",I83-G83) -> -920.93333 | K83: =IFERROR(J83/G83,"") -> -0.17639247
B84: 82 | C84: =TEXT(IFERROR(VLOOKUP($B84,Recetas!$B:$C,2,0),""),) -> relleno pastafrola sin tacc | F84: =IFERROR(G84*(1+200%),0) -> 17370 | G84: =IF(C84="","",SUMIF(Recetas!$B:$B,'Costo x Articulo'!$B84,Recetas!$H:$H)) -> 5790 | H84: =IFERROR(F84-G84,0) -> 11580 | I84: 2700 | J84: =IF(I84="","",I84-G84) -> -3090 | K84: =IFERROR(J84/G84,"") -> -0.53367876
B85: 83 | C85: =TEXT(IFERROR(VLOOKUP($B85,Recetas!$B:$C,2,0),""),) -> relleno ricota sin tacc | F85: =IFERROR(G85*(1+200%),0) -> 13608 | G85: =IF(C85="","",SUMIF(Recetas!$B:$B,'Costo x Articulo'!$B85,Recetas!$H:$H)) -> 4536 | H85: =IFERROR(F85-G85,0) -> 9072 | I85: 2000 | J85: =IF(I85="","",I85-G85) -> -2536 | K85: =IFERROR(J85/G85,"") -> -0.55908289
B86: 84 | C86: =TEXT(IFERROR(VLOOKUP($B86,Recetas!$B:$C,2,0),""),) -> alfajores de Maicena SIN TACC | F86: =IFERROR(G86*(1+200%),0) -> 16890.6 | G86: =IF(C86="","",SUMIF(Recetas!$B:$B,'Costo x Articulo'!$B86,Recetas!$H:$H)) -> 5630.2 | H86: =IFERROR(F86-G86,0) -> 11260.4 | I86: 1800 | J86: =IF(I86="","",I86-G86) -> -3830.2 | K86: =IFERROR(J86/G86,"") -> -0.68029555
... B93: 91 | C93: =TEXT(IFERROR(VLOOKUP($B93,Recetas!$B:$C,2,0),""),) -> TARTA DE MANZANA SIN TACC | F93: =IFERROR(G93*(1+200%),0) -> 15491 | G93: =IF(C93="","",SUMIF(Recetas!$B:$B,'Costo x Articulo'!$B93,Recetas!$H:$H)) -> 5163.6667 | H93: =IFERROR(F93-G93,0) -> 10327.333 | I93: 1400 | J93: =IF(I93="","",I93-G93) -> -3763.6667 | K93: =IFERROR(J93/G93,"") -> -0.72887483
B94: 92 | C94: =TEXT(IFERROR(VLOOKUP($B94,Recetas!$B:$C,2,0),""),) -> Mini budin x8 unidades | F94: =IFERROR(G94*(1+200%),0) -> 12980 | G94: =IF(C94="","",SUMIF(Recetas!$B:$B,'Costo x Articulo'!$B94,Recetas!$H:$H)) -> 4326.6667 | H94: =IFERROR(F94-G94,0) -> 8653.3333 | I94: =245*8 -> 1960 | J94: =IF(I94="","",I94-G94) -> -2366.6667 | K94: =IFERROR(J94/G94,"") -> -0.54699538
B95: 93 | C95: =TEXT(IFERROR(VLOOKUP($B95,Recetas!$B:$C,2,0),""),) -> Torta piñata | F95: =IFERROR(G95*(1+200%),0) -> 59700 | G95: =IF(C95="","",SUMIF(Recetas!$B:$B,'Costo x Articulo'!$B95,Recetas!$H:$H)) -> 19900 | H95: =IFERROR(F95-G95,0) -> 39800 | I95: 20700 | J95: =IF(I95="","",I95-G95) -> 800 | K95: =IFERROR(J95/G95,"") -> 0.040201005
B96: 94 | C96: =TEXT(IFERROR(VLOOKUP($B96,Recetas!$B:$C,2,0),""),) -> Balcarse 20 cm | F96: =IFERROR(G96*(1+200%),0) -> 53599.65 | G96: =IF(C96="","",SUMIF(Recetas!$B:$B,'Costo x Articulo'!$B96,Recetas!$H:$H)) -> 17866.55 | H96: =IFERROR(F96-G96,0) -> 35733.1 | I96: 7900 | J96: =IF(I96="","",I96-G96) -> -9966.55 | K96: =IFERROR(J96/G96,"") -> -0.55783293
B97: 95 | C97: =TEXT(IFERROR(VLOOKUP($B97,Recetas!$B:$C,2,0),""),) -> Oreos Bañadas con deco | F97: =IFERROR(G97*(1+200%),0) -> 22980 | G97: =IF(C97="","",SUMIF(Recetas!$B:$B,'Costo x Articulo'!$B97,Recetas!$H:$H)) -> 7660 | H97: =IFERROR(F97-G97,0) -> 15320 | I97: 5600 | J97: =IF(I97="","",I97-G97) -> -2060 | K97: =IFERROR(J97/G97,"") -> -0.2689295
B98: 96 | C98: =TEXT(IFERROR(VLOOKUP($B98,Recetas!$B:$C,2,0),""),) -> Chocotorta rectangular 20x30 cm | F98: =IFERROR(G98*(1+200%),0) -> 69296.571 | G98: =IF(C98="","",SUMIF(Recetas!$B:$B,'Costo x Articulo'!$B98,Recetas!$H:$H)) -> 23098.857 | H98: =IFERROR(F98-G98,0) -> 46197.714 | I98: 17000 | J98: =IF(I98="","",I98-G98) -> -6098.8571 | K98: =IFERROR(J98/G98,"") -> -0.26403285
B99: 97 | C99: =TEXT(IFERROR(VLOOKUP($B99,Recetas!$B:$C,2,0),""),) -> Arrollado con crema | F99: =IFERROR(G99*(1+200%),0) -> 22017.8 | G99: =IF(C99="","",SUMIF(Recetas!$B:$B,'Costo x Articulo'!$B99,Recetas!$H:$H)) -> 7339.2667 | H99: =IFERROR(F99-G99,0) -> 14678.533 | I99: 4400 | J99: =IF(I99="","",I99-G99) -> -2939.2667 | K99: =IFERROR(J99/G99,"") -> -0.40048506
B100: 98 | C100: =TEXT(IFERROR(VLOOKUP($B100,Recetas!$B:$C,2,0),""),) -> Huevos Rellenos N12 oreo | F100: =IFERROR(G100*(1+200%),0) -> 20661.487 | G100: =IF(C100="","",SUMIF(Recetas!$B:$B,'Costo x Articulo'!$B100,Recetas!$H:$H)) -> 6887.1624 | H100: =IFERROR(F100-G100,0) -> 13774.325 | I100: 3000 | J100: =IF(I100="","",I100-G100) -> -3887.1624 | K100: =IFERROR(J100/G100,"") -> -0.56440696 | L100: =I100*2 -> 6000 | M100: 5000 | N100: =M100/2 -> 2500 | O100: =N100-G100 -> -4387.1624
B101: 99 | C101: =TEXT(IFERROR(VLOOKUP($B101,Recetas!$B:$C,2,0),""),) -> Huevo copa del mundo | F101: =IFERROR(G101*(1+200%),0) -> 16720 | G101: =IF(C101="","",SUMIF(Recetas!$B:$B,'Costo x Articulo'!$B101,Recetas!$H:$H)) -> 5573.3333 | H101: =IFERROR(F101-G101,0) -> 11146.667 | I101: 3000 | J101: =IF(I101="","",I101-G101) -> -2573.3333 | K101: =IFERROR(J101/G101,"") -> -0.46172249 | L101: =I101*2 -> 6000 | M101: 5800 | N101: =M101/2 -> 2900 | O101: =N101-G101 -> -2673.3333
B102: 100 | C102: =TEXT(IFERROR(VLOOKUP($B102,Recetas!$B:$C,2,0),""),) -> Huevo Colorido N15 | F102: =IFERROR(G102*(1+200%),0) -> 21946 | G102: =IF(C102="","",SUMIF(Recetas!$B:$B,'Costo x Articulo'!$B102,Recetas!$H:$H)) -> 7315.3333 | H102: =IFERROR(F102-G102,0) -> 14630.667 | I102: 2700 | J102: =IF(I102="","",I102-G102) -> -4615.3333 | K102: =IFERROR(J102/G102,"") -> -0.63091224 | L102: =I102*2 -> 5400 | M102: 5200 | N102: =M102/2 -> 2600 | O102: =N102-G102 -> -4715.3333
B103: 101 | C103: =TEXT(IFERROR(VLOOKUP($B103,Recetas!$B:$C,2,0),""),) -> Huevo Colorido N12 | F103: =IFERROR(G103*(1+200%),0) -> 18219 | G103: =IF(C103="","",SUMIF(Recetas!$B:$B,'Costo x Articulo'!$B103,Recetas!$H:$H)) -> 6073 | H103: =IFERROR(F103-G103,0) -> 12146 | I103: 2200 | J103: =IF(I103="","",I103-G103) -> -3873 | K103: =IFERROR(J103/G103,"") -> -0.63774082 | L103: =I103*2 -> 4400 | M103: 4200 | N103: =M103/2 -> 2100 | O103: =N103-G103 -> -3973
B104: 102 | C104: =TEXT(IFERROR(VLOOKUP($B104,Recetas!$B:$C,2,0),""),) -> Rosca de pascua | D104: 8000 | F104: =IFERROR(G104*(1+200%),0) -> 25755.62 | G104: =IF(C104="","",SUMIF(Recetas!$B:$B,'Costo x Articulo'!$B104,Recetas!$H:$H)) -> 8585.2067 | H104: =IFERROR(F104-G104,0) -> 17170.413 | I104: 3000 | J104: =IF(I104="","",I104-G104) -> -5585.2067 | K104: =IFERROR(J104/G104,"") -> -0.6505617 | L104: =I104*2 -> 6000 | M104: 5800 | N104: =M104/2 -> 2900 | O104: =N104-G104 -> -5685.2067
B105: 103 | C105: =TEXT(IFERROR(VLOOKUP($B105,Recetas!$B:$C,2,0),""),) -> Chips DOCENA | F105: =IFERROR(G105*(1+200%),0) -> 21814.2 | G105: =IF(C105="","",SUMIF(Recetas!$B:$B,'Costo x Articulo'!$B105,Recetas!$H:$H)) -> 7271.4 | H105: =IFERROR(F105-G105,0) -> 14542.8 | I105: 3700 | J105: =IF(I105="","",I105-G105) -> -3571.4 | K105: =IFERROR(J105/G105,"") -> -0.49115714
B106: 104 | C106: =TEXT(IFERROR(VLOOKUP($B106,Recetas!$B:$C,2,0),""),) -> Chips de pollo DOCENA | F106: =IFERROR(G106*(1+200%),0) -> 45289.2 | G106: =IF(C106="","",SUMIF(Recetas!$B:$B,'Costo x Articulo'!$B106,Recetas!$H:$H)) -> 15096.4 | H106: =IFERROR(F106-G106,0) -> 30192.8 | I106: 3300 | J106: =IF(I106="","",I106-G106) -> -11796.4 | K106: =IFERROR(J106/G106,"") -> -0.78140484
B107: 105 | C107: =TEXT(IFERROR(VLOOKUP($B107,Recetas!$B:$C,2,0),""),) -> Medalla de chocolate x3 | F107: =IFERROR(G107*(1+200%),0) -> 9838 | G107: =IF(C107="","",SUMIF(Recetas!$B:$B,'Costo x Articulo'!$B107,Recetas!$H:$H)) -> 3279.3333 | H107: =IFERROR(F107-G107,0) -> 6558.6667 | I107: 1500 | J107: =IF(I107="","",I107-G107) -> -1779.3333 | K107: =IFERROR(J107/G107,"") -> -0.54258996 | L107: =I107*2 -> 3000 | M107: 2800
B108: 106 | C108: =TEXT(IFERROR(VLOOKUP($B108,Recetas!$B:$C,2,0),""),) -> Figacitas de manteca 36 unidades | F108: =IFERROR(G108*(1+200%),0) -> 10668 | G108: =IF(C108="","",SUMIF(Recetas!$B:$B,'Costo x Articulo'!$B108,Recetas!$H:$H)) -> 3556 | H108: =IFERROR(F108-G108,0) -> 7112 | I108: 2700 | J108: =IF(I108="","",I108-G108) -> -856 | K108: =IFERROR(J108/G108,"") -> -0.24071991
B109: 107 | C109: =TEXT(IFERROR(VLOOKUP($B109,Recetas!$B:$C,2,0),""),) -> Focaccia | F109: =IFERROR(G109*(1+200%),0) -> 1994.3571 | G109: =IF(C109="","",SUMIF(Recetas!$B:$B,'Costo x Articulo'!$B109,Recetas!$H:$H)) -> 664.78571 | H109: =IFERROR(F109-G109,0) -> 1329.5714 | I109: 1100 | J109: =IF(I109="","",I109-G109) -> 435.21429 | K109: =IFERROR(J109/G109,"") -> 0.65466853
...

Sheet Bar
L2: =SUM(L8:L26) -> 58580 | M2: =SUM(M8:M26) -> -286739.16 | P2: =SUM(P8:P26) -> 702960 | Q2: =SUM(Q8:Q26) -> -2293913.3
K6: Por pedido | O6: Por Mes (12 pedidos)
B7: Nro. | C7: Artículo | D7: Costo | E7: Precio minorista | F7: Margen minorista | H7: Precio mayorista | I7: Margen mayorista | K7: Cantidad | L7: Venta Bruta | M7: Ganancia | O7: Cantidad | P7: Venta Bruta | Q7: Ganancia | R7: %
B8: 1 | C8: Budín Limón | D8: ='Costo x Articulo'!G3 -> 5558.0667 | E8: 12000 | F8: =IFERROR((E8-D8)/D8,0) -> 1.1590241 | H8: 1000 | I8: =IFERROR((H8-D8)/D8,0) -> -0.82008132 | K8: 3 | L8: =H8*K8 -> 3000 | M8: =K8*(H8-D8) -> -13674.2 | O8: =K8*12 -> 36 | P8: =L8*12 -> 36000 | Q8: =M8*8 -> -109393.6 | R8: =Q8/$Q$2 -> 0.047688638 | T8: =H8*1.1 -> 1100
B9: 2 | C9: Budín zanahoria | D9: =D8 -> 5558.0667 | E9: =E8 -> 12000 | F9: =IFERROR((E9-D9)/D9,0) -> 1.1590241 | H9: =H8 -> 1000 | I9: =IFERROR((H9-D9)/D9,0) -> -0.82008132 | K9: 3 | L9: =L8 -> 3000 | M9: =K9*(H9-D9) -> -13674.2 | O9: =K9*12 -> 36 | P9: =L9*12 -> 36000 | Q9: =M9*8 -> -109393.6 | R9: =Q9/$Q$2 -> 0.047688638 | T9: =H9*1.1 -> 1100
B10: 3 | C10: Budín marmolado | D10: =D9 -> 5558.0667 | E10: =E9 -> 12000 | F10: =IFERROR((E10-D10)/D10,0) -> 1.1590241 | H10: =H9 -> 1000 | I10: =IFERROR((H10-D10)/D10,0) -> -0.82008132 | K10: 3 | L10: =L9 -> 3000 | M10: =K10*(H10-D10) -> -13674.2 | O10: =K10*12 -> 36 | P10: =L10*12 -> 36000 | Q10: =M10*8 -> -109393.6 | R10: =Q10/$Q$2 -> 0.047688638 | T10: =H10*1.1 -> 1100
B11: 4 | C11: Budín frutos secos | D11: ='Costo x Articulo'!G126 -> 6604.7333 | E11: 15000 | F11: =IFERROR((E11-D11)/D11,0) -> 1.2710985 | H11: =H10 -> 1000 | I11: =IFERROR((H11-D11)/D11,0) -> -0.84859343 | K11: =K10 -> 3 | L11: =L10 -> 3000 | M11: =K11*(H11-D11) -> -16814.2 | O11: =K11*12 -> 36 | P11: =L11*12 -> 36000 | Q11: =M11*8 -> -134513.6 | R11: =Q11/$Q$2 -> 0.058639358 | T11: =H11*1.1 -> 1100
B12: 5 | C12: Lemon Pie | D12: ='Costo x Articulo'!G5/6 -> 1520.5889 | E12: 3000 | F12: =IFERROR((E12-D12)/D12,0) -> 0.97291985 | H12: 350 | I12: =IFERROR((H12-D12)/D12,0) -> -0.76982602 | K12: 12 | L12: =H12*K12 -> 4200 | M12: =K12*(H12-D12) -> -14047.067 | O12: =K12*12 -> 144 | P12: =L12*12 -> 50400 | Q12: =M12*8 -> -112376.53 | R12: =Q12/$Q$2 -> 0.048989007 | T12: =H12*1.1 -> 385
B13: 6 | C13: Browrnie Oreo | D13: ='Costo x Articulo'!G55/6 -> 2428.888 | E13: 4500 | F13: =IFERROR((E13-D13)/D13,0) -> 0.8526997 | H13: =H12 -> 350 | I13: =IFERROR((H13-D13)/D13,0) -> -0.85590113 | K13: 24 | L13: =H13*K13 -> 8400 | M13: =K13*(H13-D13) -> -49893.311 | O13: =K13*12 -> 288 | P13: =L13*12 -> 100800 | Q13: =M13*8 -> -399146.49 | R13: =Q13/$Q$2 -> 0.17400243 | T13: =H13*1.1 -> 385
B14: 7 | C14: Chocotorta | D14: ='Costo x Articulo'!G127/6 -> 2817.2619 | E14: 5000 | F14: =IFERROR((E14-D14)/D14,0) -> 0.77477287 | H14: =H13 -> 350 | I14: =IFERROR((H14-D14)/D14,0) -> -0.8757659 | K14: 24 | L14: =H14*K14 -> 8400 | M14: =K14*(H14-D14) -> -59214.286 | O14: =K14*12 -> 288 | P14: =L14*12 -> 100800 | Q14: =M14*8 -> -473714.29 | R14: =Q14/$Q$2 -> 0.20650924 | T14: =H14*1.1 -> 385
B15: 8 | C15: Cheese Cake Frutos rojos | D15: ='Costo x Articulo'!G44/6 -> 2541.6553 | E15: 5000 | F15: =IFERROR((E15-D15)/D15,0) -> 0.96722191 | H15: =H14 -> 350 | I15: =IFERROR((H15-D15)/D15,0) -> -0.86229447 | K15: 24 | L15: =H15*K15 -> 8400 | M15: =K15*(H15-D15) -> -52599.727 | O15: =K15*12 -> 288 | P15: =L15*12 -> 100800 | Q15: =M15*8 -> -420797.82 | R15: =Q15/$Q$2 -> 0.18344103 | T15: =H15*1.1 -> 385
B16: 9 | C16: Torta Oreo | D16: ='Costo x Articulo'!G67/6 -> 2985.8333 | E16: 5000 | F16: =IFERROR((E16-D16)/D16,0) -> 0.67457438 | H16: =H15 -> 350 | I16: =IFERROR((H16-D16)/D16,0) -> -0.88277979 | K16: 12 | L16: =H16*K16 -> 4200 | M16: =K16*(H16-D16) -> -31630 | O16: =K16*12 -> 144 | P16: =L16*12 -> 50400 | Q16: =M16*8 -> -253040 | R16: =Q16/$Q$2 -> 0.11030931 | T16: =H16*1.1 -> 385
B17: 10 | C17: Apple Crumble | D17: ='Costo x Articulo'!G25/6 -> 1117.6861 | E17: 2500 | F17: =IFERROR((E17-D17)/D17,0) -> 1.2367639 | H17: =H16 -> 350 | I17: =IFERROR((H17-D17)/D17,0) -> -0.68685305 | K17: 24 | L17: =H17*K17 -> 8400 | M17: =K17*(H17-D17) -> -18424.467 | O17: =K17*12 -> 288 | P17: =L17*12 -> 100800 | Q17: =M17*8 -> -147395.73 | R17: =Q17/$Q$2 -> 0.064255147 | T17: =H17*1.1 -> 385
B18: 11 | C18: Macarrons x12 | D18: ='Costo x Articulo'!G68/4 -> 1918.375 | E18: 3000 | F18: =IFERROR((E18-D18)/D18,0) -> 0.56382355 | H18: =75*12 -> 900 | I18: =IFERROR((H18-D18)/D18,0) -> -0.53085294 | K18: 4 | L18: =H18*K18 -> 3600 | M18: =K18*(H18-D18) -> -4073.5 | O18: =K18*12 -> 48 | P18: =L18*12 -> 43200 | Q18: =M18*8 -> -32588 | R18: =Q18/$Q$2 -> 0.014206291 | T18: =H18*1.1 -> 990
B19: 12 | C19: Carrot Cake | D19: ='Costo x Articulo'!G74/8 -> 694.49405 | E19: 2400 | F19: =IFERROR((E19-D19)/D19,0) -> 2.4557532 | H19: =H17 -> 350 | I19: =IFERROR((H19-D19)/D19,0) -> -0.496036 | L19: =H19*K19 -> 0 | M19: =K19*(H19-D19) -> 0 | P19: =L19*12 -> 0 | Q19: =M19*8 -> 0 | R19: =Q19/$Q$2 -> 0
B20: 13 | C20: Pastafrola 7cm x 7cm | D20: =SUM(Recetas!H176:H184)*2/6/10*7 -> 873.56889 | E20: 2000 | F20: =IFERROR((E20-D20)/D20,0) -> 1.2894588 | H20: 120 | I20: =IFERROR((H20-D20)/D20,0) -> -0.86263247 | L20: =H20*K20 -> 0 | M20: =K20*(H20-D20) -> 0 | O20: =K20*12 -> 0 | P20: =L20*12 -> 0 | Q20: =M20*8 -> 0 | R20: =Q20/$Q$2 -> 0
B21: 14 | C21: Ricota 7cm x 7cm | D21: =SUM(Recetas!H188:H196)*2/6/10*7 -> 1385.7356 | E21: 2600 | F21: =IFERROR((E21-D21)/D21,0) -> 0.87625986 | H21: 180 | I21: =IFERROR((H21-D21)/D21,0) -> -0.87010509 | L21: =H21*K21 -> 0 | M21: =K21*(H21-D21) -> 0 | O21: =K21*12 -> 0 | P21: =L21*12 -> 0 | Q21: =M21*8 -> 0 | R21: =Q21/$Q$2 -> 0
B22: 15 | C22: Coco y dulce de leche 7cm x 7cm | D22: =SUM(Recetas!H104:H112)*2/6/10*7 -> 1694.6689 | E22: 2900 | F22: =IFERROR((E22-D22)/D22,0) -> 0.71124874 | H22: 200 | I22: =IFERROR((H22-D22)/D22,0) -> -0.88198285 | L22: =H22*K22 -> 0 | M22: =K22*(H22-D22) -> 0 | O22: =K22*12 -> 0 | P22: =L22*12 -> 0 | Q22: =M22*8 -> 0 | R22: =Q22/$Q$2 -> 0
B23: 16 | C23: Torta cumpleaños Selva Negra 20cm | D23: =SUM(Recetas!H116:H124) -> 9093.2 | E23: 22500 | F23: =IFERROR((E23-D23)/D23,0) -> 1.4743765 | H23: 2000 | I23: =IFERROR((H23-D23)/D23,0) -> -0.78005543 | L23: =H23*K23 -> 0 | M23: =K23*(H23-D23) -> 0 | O23: =K23*12 -> 0 | P23: =L23*12 -> 0 | Q23: =M23*8 -> 0 | R23: =Q23/$Q$2 -> 0
B24: 17 | C24: Pan de Campo | D24: =SUM(Recetas!H722:H725) -> 685.5 | E24: 1500 | F24: =IFERROR((E24-D24)/D24,0) -> 1.1881838 | H24: 150 | I24: =IFERROR((H24-D24)/D24,0) -> -0.78118162 | L24: =H24*K24 -> 0 | M24: =K24*(H24-D24) -> 0 | P24: =L24*12 -> 0 | Q24: =M24*8 -> 0 | R24: =Q24/$Q$2 -> 0
B25: 18 | C25: cookies chips de chocolate x 12 | E25: 1100 | F25: =IFERROR((E25-D25)/D25,0) -> 0 | H25: 980 | I25: =IFERROR((H25-D25)/D25,0) -> 0 | K25: 1 | L25: =H25*K25 -> 980 | M25: =K25*(H25-D25) -> 980 | O25: 6 | P25: =L25*12 -> 11760 | Q25: =M25*8 -> 7840
F26: =IFERROR((E26-D26)/D26,0) -> 0 | I26: =IFERROR((H26-D26)/D26,0) -> 0 | Q26: =M26*8 -> 0

Sheet Catering
C2: Catering para 50 personas | D2: Importe | E2: Costo
B3: canape de atun x 50 unidades | C3: Canapé de Atún x 50u. | E3: =SUMIF(Recetas!C:C,Catering!B3,Recetas!H:H) -> 25370
B4: canape de queso crema y cibulet x 50 | C4: Canapé de Queso crema y ciboullet x 50u. | E4: =SUMIF(Recetas!C:C,Catering!B4,Recetas!H:H) -> 19400
B5: empanadas copetin x 24 | C5: Empanadas Copetín x 50u. | E5: =SUMIF(Recetas!C:C,Catering!B5,Recetas!H:H)/24*50 -> 38229.167
B6: figacitas con bondiola | C6: Figacitas de manteca con bondiola x 50u. | E6: =SUMIF(Recetas!C:C,Catering!B6,Recetas!H:H) -> 44966.667
B7: pinchos capresse | C7: Pincho Capresse x 50u. | E7: =SUMIF(Recetas!C:C,Catering!B7,Recetas!H:H) -> 24875
B8: Chip de pollo x50 | C8: Chips de pollo x 50u. | E8: =SUM(Recetas!H953:H960)/12*50 -> 62901.667
B9: Chip de fiambre x50 | C9: Chips de jamón y queso x 50u. | E9: =SUM(Recetas!H946:H952)/12*50 -> 30297.5
B10: pizzetas x 12 | C10: Pizzetas x50u. | E10: =SUM(Recetas!H710:H713)/12*50 -> 5036.6071 | L10: =281*2 -> 562
D11: =SUM(D3:D10) -> 0 | E11: =SUM(E3:E10) -> 251076.61
E12: =D11/E11-1 -> -1

Sheet Ventas Bar
B3: N° | C3: Fecha | D3: Mes | E3: Nro. | F3: Artículo | G3: Unidades | H3: Costo Total | I3: Venta Total | J3: Ganancia
B4: 1 | C4: 44637 | D4: =IFERROR(MONTH(C4),"") -> 3 | E4: 1 | F4: =IFERROR(VLOOKUP(E4,Bar!$B:$C,2,0),"") -> Budín Limón | G4: 3 | H4: =IFERROR(IFERROR(VLOOKUP(E4,Bar!$B:$D,3,0),"")*G4,"") -> 16674.2 | I4: 2400 | J4: =IFERROR(I4-H4,"") -> -14274.2
B5: 1 | C5: 44637 | D5: =IFERROR(MONTH(C5),"") -> 3 | E5: 2 | F5: =IFERROR(VLOOKUP(E5,Bar!$B:$C,2,0),"") -> Budín zanahoria | G5: 3 | H5: =IFERROR(IFERROR(VLOOKUP(E5,Bar!$B:$D,3,0),"")*G5,"") -> 16674.2 | I5: 2400 | J5: =IFERROR(I5-H5,"") -> -14274.2
B6: 1 | C6: 44637 | D6: =IFERROR(MONTH(C6),"") -> 3 | E6: 3 | F6: =IFERROR(VLOOKUP(E6,Bar!$B:$C,2,0),"") -> Budín marmolado | G6: 3 | H6: =IFERROR(IFERROR(VLOOKUP(E6,Bar!$B:$D,3,0),"")*G6,"") -> 16674.2 | I6: 2400 | J6: =IFERROR(I6-H6,"") -> -14274.2
B7: 1 | C7: 44637 | D7: =IFERROR(MONTH(C7),"") -> 3 | E7: 4 | F7: =IFERROR(VLOOKUP(E7,Bar!$B:$C,2,0),"") -> Budín frutos secos | G7: 3 | H7: =IFERROR(IFERROR(VLOOKUP(E7,Bar!$B:$D,3,0),"")*G7,"") -> 19814.2 | I7: 2400 | J7: =IFERROR(I7-H7,"") -> -17414.2
B8: 1 | C8: 44637 | D8: =IFERROR(MONTH(C8),"") -> 3 | E8: 11 | F8: =IFERROR(VLOOKUP(E8,Bar!$B:$C,2,0),"") -> Macarrons x12 | G8: 2 | H8: =IFERROR(IFERROR(VLOOKUP(E8,Bar!$B:$D,3,0),"")*G8,"") -> 3836.75 | I8: 1000 | J8: =IFERROR(I8-H8,"") -> -2836.75
B9: =B8+1 -> 2 | C9: 44638 | D9: =IFERROR(MONTH(C9),"") -> 3 | E9: 8 | F9: =IFERROR(VLOOKUP(E9,Bar!$B:$C,2,0),"") -> Cheese Cake Frutos rojos | G9: 24 | H9: =IFERROR(IFERROR(VLOOKUP(E9,Bar!$B:$D,3,0),"")*G9,"") -> 60999.727 | I9: 6480 | J9: =IFERROR(I9-H9,"") -> -54519.727
B10: 2 | C10: =IFERROR(IF(B10=B9,C9,""),"") -> 44638 | D10: =IFERROR(MONTH(C10),"") -> 3 | E10: 5 | F10: =IFERROR(VLOOKUP(E10,Bar!$B:$C,2,0),"") -> Lemon Pie | G10: 12 | H10: =IFERROR(IFERROR(VLOOKUP(E10,Bar!$B:$D,3,0),"")*G10,"") -> 18247.067 | I10: 3240 | J10: =IFERROR(I10-H10,"") -> -15007.067
B11: 2 | C11: =IFERROR(IF(B11=B10,C10,""),"") -> 44638 | D11: =IFERROR(MONTH(C11),"") -> 3 | E11: 6 | F11: =IFERROR(VLOOKUP(E11,Bar!$B:$C,2,0),"") -> Browrnie Oreo | G11: 24 | H11: =IFERROR(IFERROR(VLOOKUP(E11,Bar!$B:$D,3,0),"")*G11,"") -> 58293.311 | I11: 6480 | J11: =IFERROR(I11-H11,"") -> -51813.311
B12: 2 | C12: =IFERROR(IF(B12=B11,C11,""),"") -> 44638 | D12: =IFERROR(MONTH(C12),"") -> 3 | E12: 7 | F12: =IFERROR(VLOOKUP(E12,Bar!$B:$C,2,0),"") -> Chocotorta | G12: 24 | H12: =IFERROR(IFERROR(VLOOKUP(E12,Bar!$B:$D,3,0),"")*G12,"") -> 67614.286 | I12: 6480 | J12: =IFERROR(I12-H12,"") -> -61134.286
B13: 2 | C13: =IFERROR(IF(B13=B12,C12,""),"") -> 44638 | D13: =IFERROR(MONTH(C13),"") -> 3 | E13: 9 | F13: =IFERROR(VLOOKUP(E13,Bar!$B:$C,2,0),"") -> Torta Oreo | G13: 12 | H13: =IFERROR(IFERROR(VLOOKUP(E13,Bar!$B:$D,3,0),"")*G13,"") -> 35830 | I13: 3240 | J13: =IFERROR(I13-H13,"") -> -32590
B14: 2 | C14: =IFERROR(IF(B14=B13,C13,""),"") -> 44638 | D14: =IFERROR(MONTH(C14),"") -> 3 | E14: 10 | F14: =IFERROR(VLOOKUP(E14,Bar!$B:$C,2,0),"") -> Apple Crumble | G14: 17 | H14: =IFERROR(IFERROR(VLOOKUP(E14,Bar!$B:$D,3,0),"")*G14,"") -> 19000.664 | I14: 4590 | J14: =IFERROR(I14-H14,"") -> -14410.664
B15: 2 | C15: =IFERROR(IF(B15=B14,C14,""),"") -> 44638 | D15: =IFERROR(MONTH(C15),"") -> 3 | E15: 1 | F15: =IFERROR(VLOOKUP(E15,Bar!$B:$C,2,0),"") -> Budín Limón | G15: 3 | H15: =IFERROR(IFERROR(VLOOKUP(E15,Bar!$B:$D,3,0),"")*G15,"") -> 16674.2 | I15: 2400 | J15: =IFERROR(I15-H15,"") -> -14274.2
B16: 2 | C16: =IFERROR(IF(B16=B15,C15,""),"") -> 44638 | D16: =IFERROR(MONTH(C16),"") -> 3 | E16: 2 | F16: =IFERROR(VLOOKUP(E16,Bar!$B:$C,2,0),"") -> Budín zanahoria | G16: 3 | H16: =IFERROR(IFERROR(VLOOKUP(E16,Bar!$B:$D,3,0),"")*G16,"") -> 16674.2 | I16: 2400 | J16: =IFERROR(I16-H16,"") -> -14274.2
B17: 2 | C17: =IFERROR(IF(B17=B16,C16,""),"") -> 44638 | D17: =IFERROR(MONTH(C17),"") -> 3 | E17: 3 | F17: =IFERROR(VLOOKUP(E17,Bar!$B:$C,2,0),"") -> Budín marmolado | G17: 3 | H17: =IFERROR(IFERROR(VLOOKUP(E17,Bar!$B:$D,3,0),"")*G17,"") -> 16674.2 | I17: 2400 | J17: =IFERROR(I17-H17,"") -> -14274.2
B18: 2 | C18: =IFERROR(IF(B18=B17,C17,""),"") -> 44638 | D18: =IFERROR(MONTH(C18),"") -> 3 | E18: 4 | F18: =IFERROR(VLOOKUP(E18,Bar!$B:$C,2,0),"") -> Budín frutos secos | G18: 3 | H18: =IFERROR(IFERROR(VLOOKUP(E18,Bar!$B:$D,3,0),"")*G18,"") -> 19814.2 | I18: 2400 | J18: =IFERROR(I18-H18,"") -> -17414.2
B19: 2 | C19: =IFERROR(IF(B19=B18,C18,""),"") -> 44638 | D19: =IFERROR(MONTH(C19),"") -> 3 | E19: 11 | F19: =IFERROR(VLOOKUP(E19,Bar!$B:$C,2,0),"") -> Macarrons x12 | G19: 4 | H19: =IFERROR(IFERROR(VLOOKUP(E19,Bar!$B:$D,3,0),"")*G19,"") -> 7673.5 | I19: 2000 | J19: =IFERROR(I19-H19,"") -> -5673.5
B20: =B19+1 -> 3 | C20: 44641 | D20: =IFERROR(MONTH(C20),"") -> 3 | E20: 8 | F20: =IFERROR(VLOOKUP(E20,Bar!$B:$C,2,0),"") -> Cheese Cake Frutos rojos | G20: 24 | H20: =IFERROR(IFERROR(VLOOKUP(E20,Bar!$B:$D,3,0),"")*G20,"") -> 60999.727 | I20: 6480 | J20: =IFERROR(I20-H20,"") -> -54519.727
B21: 3 | C21: =IFERROR(IF(B21=B20,C20,""),"") -> 44641 | D21: =IFERROR(MONTH(C21),"") -> 3 | E21: 5 | F21: =IFERROR(VLOOKUP(E21,Bar!$B:$C,2,0),"") -> Lemon Pie | G21: 12 | H21: =IFERROR(IFERROR(VLOOKUP(E21,Bar!$B:$D,3,0),"")*G21,"") -> 18247.067 | I21: 3240 | J21: =IFERROR(I21-H21,"") -> -15007.067
B22: 3 | C22: =IFERROR(IF(B22=B21,C21,""),"") -> 44641 | D22: =IFERROR(MONTH(C22),"") -> 3 | E22: 7 | F22: =IFERROR(VLOOKUP(E22,Bar!$B:$C,2,0),"") -> Chocotorta | G22: 18 | H22: =IFERROR(IFERROR(VLOOKUP(E22,Bar!$B:$D,3,0),"")*G22,"") -> 50710.714 | I22: 4860 | J22: =IFERROR(I22-H22,"") -> -45850.714
B23: 3 | C23: =IFERROR(IF(B23=B22,C22,""),"") -> 44641 | D23: =IFERROR(MONTH(C23),"") -> 3 | E23: 10 | F23: =IFERROR(VLOOKUP(E23,Bar!$B:$C,2,0),"") -> Apple Crumble | G23: 18 | H23: =IFERROR(IFERROR(VLOOKUP(E23,Bar!$B:$D,3,0),"")*G23,"") -> 20118.35 | I23: 4860 | J23: =IFERROR(I23-H23,"") -> -15258.35
B24: 3 | C24: =IFERROR(IF(B24=B23,C23,""),"") -> 44641 | D24: =IFERROR(MONTH(C24),"") -> 3 | E24: 9 | F24: =IFERROR(VLOOKUP(E24,Bar!$B:$C,2,0),"") -> Torta Oreo | G24: 17 | H24: =IFERROR(IFERROR(VLOOKUP(E24,Bar!$B:$D,3,0),"")*G24,"") -> 50759.167 | I24: 4590 | J24: =IFERROR(I24-H24,"") -> -46169.167
B25: 3 | C25: =IFERROR(IF(B25=B24,C24,""),"") -> 44641 | D25: =IFERROR(MONTH(C25),"") -> 3 | E25: 6 | F25: =IFERROR(VLOOKUP(E25,Bar!$B:$C,2,0),"") -> Browrnie Oreo | G25: 18 | H25: =IFERROR(IFERROR(VLOOKUP(E25,Bar!$B:$D,3,0),"")*G25,"") -> 43719.983 | I25: 4860 | J25: =IFERROR(I25-H25,"") -> -38859.983
B26: 3 | C26: =IFERROR(IF(B26=B25,C25,""),"") -> 44641 | D26: =IFERROR(MONTH(C26),"") -> 3 | E26: 11 | F26: =IFERROR(VLOOKUP(E26,Bar!$B:$C,2,0),"") -> Macarrons x12 | G26: 4 | H26: =IFERROR(IFERROR(VLOOKUP(E26,Bar!$B:$D,3,0),"")*G26,"") -> 7673.5 | I26: 2000 | J26: =IFERROR(I26-H26,"") -> -5673.5
B27: 3 | C27: =IFERROR(IF(B27=B23,C23,""),"") -> 44641 | D27: =IFERROR(MONTH(C27),"") -> 3 | E27: 1 | F27: =IFERROR(VLOOKUP(E27,Bar!$B:$C,2,0),"") -> Budín Limón | G27: 4 | H27: =IFERROR(IFERROR(VLOOKUP(E27,Bar!$B:$D,3,0),"")*G27,"") -> 22232.267 | I27: 3200 | J27: =IFERROR(I27-H27,"") -> -19032.267
B28: 3 | C28: =IFERROR(IF(B28=B24,C24,""),"") -> 44641 | D28: =IFERROR(MONTH(C28),"") -> 3 | E28: 2 | F28: =IFERROR(VLOOKUP(E28,Bar!$B:$C,2,0),"") -> Budín zanahoria | G28: 2 | H28: =IFERROR(IFERROR(VLOOKUP(E28,Bar!$B:$D,3,0),"")*G28,"") -> 11116.133 | I28: 1600 | J28: =IFERROR(I28-H28,"") -> -9516.1333
B29: 3 | C29: =IFERROR(IF(B29=B25,C25,""),"") -> 44641 | D29: =IFERROR(MONTH(C29),"") -> 3 | E29: 3 | F29: =IFERROR(VLOOKUP(E29,Bar!$B:$C,2,0),"") -> Budín marmolado | G29: 2 | H29: =IFERROR(IFERROR(VLOOKUP(E29,Bar!$B:$D,3,0),"")*G29,"") -> 11116.133 | I29: 1600 | J29: =IFERROR(I29-H29,"") -> -9516.1333
B30: 3 | C30: =IFERROR(IF(B30=B26,C26,""),"") -> 44641 | D30: =IFERROR(MONTH(C30),"") -> 3 | E30: 4 | F30: =IFERROR(VLOOKUP(E30,Bar!$B:$C,2,0),"") -> Budín frutos secos | G30: 2 | H30: =IFERROR(IFERROR(VLOOKUP(E30,Bar!$B:$D,3,0),"")*G30,"") -> 13209.467 | I30: 1600 | J30: =IFERROR(I30-H30,"") -> -11609.467
B31: 4 | C31: 44645 | D31: =IFERROR(MONTH(C31),"") -> 3 | E31: 7 | F31: =IFERROR(VLOOKUP(E31,Bar!$B:$C,2,0),"") -> Chocotorta | G31: 12 | H31: =IFERROR(IFERROR(VLOOKUP(E31,Bar!$B:$D,3,0),"")*G31,"") -> 33807.143 | I31: 3240 | J31: =IFERROR(I31-H31,"") -> -30567.143
B32: 4 | C32: =IFERROR(IF(B32=B31,C31,""),"") -> 44645 | D32: =IFERROR(MONTH(C32),"") -> 3 | E32: 8 | F32: =IFERROR(VLOOKUP(E32,Bar!$B:$C,2,0),"") -> Cheese Cake Frutos rojos | G32: 12 | H32: =IFERROR(IFERROR(VLOOKUP(E32,Bar!$B:$D,3,0),"")*G32,"") -> 30499.864 | I32: 3240 | J32: =IFERROR(I32-H32,"") -> -27259.864
B33: 4 | C33: =IFERROR(IF(B33=B32,C32,""),"") -> 44645 | D33: =IFERROR(MONTH(C33),"") -> 3 | E33: 6 | F33: =IFERROR(VLOOKUP(E33,Bar!$B:$C,2,0),"") -> Browrnie Oreo | G33: 10 | H33: =IFERROR(IFERROR(VLOOKUP(E33,Bar!$B:$D,3,0),"")*G33,"") -> 24288.88 | I33: 2700 | J33: =IFERROR(I33-H33,"") -> -21588.88
B34: 4 | C34: =IFERROR(IF(B34=B33,C33,""),"") -> 44645 | D34: =IFERROR(MONTH(C34),"") -> 3 | E34: 10 | F34: =IFERROR(VLOOKUP(E34,Bar!$B:$C,2,0),"") -> Apple Crumble | G34: 10 | H34: =IFERROR(IFERROR(VLOOKUP(E34,Bar!$B:$D,3,0),"")*G34,"") -> 11176.861 | I34: 2700 | J34: =IFERROR(I34-H34,"") -> -8476.8611
B35: 4 | C35: =IFERROR(IF(B35=B34,C34,""),"") -> 44645 | D35: =IFERROR(MONTH(C35),"") -> 3 | E35: 5 | F35: =IFERROR(VLOOKUP(E35,Bar!$B:$C,2,0),"") -> Lemon Pie | G35: 6 | H35: =IFERROR(IFERROR(VLOOKUP(E35,Bar!$B:$D,3,0),"")*G35,"") -> 9123.5333 | I35: 1620 | J35: =IFERROR(I35-H35,"") -> -7503.5333
B36: 4 | C36: =IFERROR(IF(B36=B35,C35,""),"") -> 44645 | D36: =IFERROR(MONTH(C36),"") -> 3 | E36: 1 | F36: =IFERROR(VLOOKUP(E36,Bar!$B:$C,2,0),"") -> Budín Limón | G36: 2 | H36: =IFERROR(IFERROR(VLOOKUP(E36,Bar!$B:$D,3,0),"")*G36,"") -> 11116.133 | I36: 1600 | J36: =IFERROR(I36-H36,"") -> -9516.1333
B37: 4 | C37: =IFERROR(IF(B37=B36,C36,""),"") -> 44645 | D37: =IFERROR(MONTH(C37),"") -> 3 | E37: 2 | F37: =IFERROR(VLOOKUP(E37,Bar!$B:$C,2,0),"") -> Budín zanahoria | G37: 2 | H37: =IFERROR(IFERROR(VLOOKUP(E37,Bar!$B:$D,3,0),"")*G37,"") -> 11116.133 | I37: 1600 | J37: =IFERROR(I37-H37,"") -> -9516.1333
B38: 4 | C38: =IFERROR(IF(B38=B37,C37,""),"") -> 44645 | D38: =IFERROR(MONTH(C38),"") -> 3 | E38: 3 | F38: =IFERROR(VLOOKUP(E38,Bar!$B:$C,2,0),"") -> Budín marmolado | G38: 2 | H38: =IFERROR(IFERROR(VLOOKUP(E38,Bar!$B:$D,3,0),"")*G38,"") -> 11116.133 | I38: 1600 | J38: =IFERROR(I38-H38,"") -> -9516.1333
B39: 4 | C39: =IFERROR(IF(B39=B38,C38,""),"") -> 44645 | D39: =IFERROR(MONTH(C39),"") -> 3 | E39: 4 | F39: =IFERROR(VLOOKUP(E39,Bar!$B:$C,2,0),"") -> Budín frutos secos | G39: 2 | H39: =IFERROR(IFERROR(VLOOKUP(E39,Bar!$B:$D,3,0),"")*G39,"") -> 13209.467 | I39: 1600 | J39: =IFERROR(I39-H39,"") -> -11609.467
B40: 4 | C40: =IFERROR(IF(B40=B39,C39,""),"") -> 44645 | D40: =IFERROR(MONTH(C40),"") -> 3 | E40: 11 | F40: =IFERROR(VLOOKUP(E40,Bar!$B:$C,2,0),"") -> Macarrons x12 | G40: 2 | H40: =IFERROR(IFERROR(VLOOKUP(E40,Bar!$B:$D,3,0),"")*G40,"") -> 3836.75 | I40: 1000 | J40: =IFERROR(I40-H40,"") -> -2836.75
B41: =B40+1 -> 5 | C41: 44649 | D41: =IFERROR(MONTH(C41),"") -> 3 | E41: 8 | F41: =IFERROR(VLOOKUP(E41,Bar!$B:$C,2,0),"") -> Cheese Cake Frutos rojos | G41: 18 | H41: =IFERROR(IFERROR(VLOOKUP(E41,Bar!$B:$D,3,0),"")*G41,"") -> 45749.796 | I41: 4860 | J41: =IFERROR(I41-H41,"") -> -40889.796
B42: 5 | C42: =IFERROR(IF(B42=B41,C41,""),"") -> 44649 | D42: =IFERROR(MONTH(C42),"") -> 3 | E42: 5 | F42: =IFERROR(VLOOKUP(E42,Bar!$B:$C,2,0),"") -> Lemon Pie | G42: 12 | H42: =IFERROR(IFERROR(VLOOKUP(E42,Bar!$B:$D,3,0),"")*G42,"") -> 18247.067 | I42: 3240 | J42: =IFERROR(I42-H42,"") -> -15007.067
B43: 5 | C43: =IFERROR(IF(B43=B42,C42,""),"") -> 44649 | D43: =IFERROR(MONTH(C43),"") -> 3 | E43: 7 | F43: =IFERROR(VLOOKUP(E43,Bar!$B:$C,2,0),"") -> Chocotorta | G43: 12 | H43: =IFERROR(IFERROR(VLOOKUP(E43,Bar!$B:$D,3,0),"")*G43,"") -> 33807.143 | I43: 3240 | J43: =IFERROR(I43-H43,"") -> -30567.143
B44: 5 | C44: =IFERROR(IF(B44=B43,C43,""),"") -> 44649 | D44: =IFERROR(MONTH(C44),"") -> 3 | E44: 10 | F44: =IFERROR(VLOOKUP(E44,Bar!$B:$C,2,0),"") -> Apple Crumble | G44: 12 | H44: =IFERROR(IFERROR(VLOOKUP(E44,Bar!$B:$D,3,0),"")*G44,"") -> 13412.233 | I44: 3240 | J44: =IFERROR(I44-H44,"") -> -10172.233
B45: 5 | C45: =IFERROR(IF(B45=B44,C44,""),"") -> 44649 | D45: =IFERROR(MONTH(C45),"") -> 3 | E45: 9 | F45: =IFERROR(VLOOKUP(E45,Bar!$B:$C,2,0),"") -> Torta Oreo | G45: 24 | H45: =IFERROR(IFERROR(VLOOKUP(E45,Bar!$B:$D,3,0),"")*G45,"") -> 71660 | I45: 6480 | J45: =IFERROR(I45-H45,"") -> -65180
B46: 5 | C46: =IFERROR(IF(B46=B45,C45,""),"") -> 44649 | D46: =IFERROR(MONTH(C46),"") -> 3 | E46: 11 | F46: =IFERROR(VLOOKUP(E46,Bar!$B:$C,2,0),"") -> Macarrons x12 | G46: 4 | H46: =IFERROR(IFERROR(VLOOKUP(E46,Bar!$B:$D,3,0),"")*G46,"") -> 7673.5 | I46: 2000 | J46: =IFERROR(I46-H46,"") -> -5673.5
B47: 5 | C47: =IFERROR(IF(B47=B46,C46,""),"") -> 44649 | D47: =IFERROR(MONTH(C47),"") -> 3 | E47: 1 | F47: Budín Limón | G47: 2 | H47: =IFERROR(IFERROR(VLOOKUP(E47,Bar!$B:$D,3,0),"")*G47,"") -> 11116.133 | I47: 1600 | J47: =IFERROR(I47-H47,"") -> -9516.1333
B48: 5 | C48: =IFERROR(IF(B48=B47,C47,""),"") -> 44649 | D48: =IFERROR(MONTH(C48),"") -> 3 | E48: 2 | F48: Budín zanahoria | G48: 2 | H48: =IFERROR(IFERROR(VLOOKUP(E48,Bar!$B:$D,3,0),"")*G48,"") -> 11116.133 | I48: 1600 | J48: =IFERROR(I48-H48,"") -> -9516.1333
B49: 5 | C49: =IFERROR(IF(B49=B48,C48,""),"") -> 44649 | D49: =IFERROR(MONTH(C49),"") -> 3 | E49: 3 | F49: Budín marmolado | G49: 2 | H49: =IFERROR(IFERROR(VLOOKUP(E49,Bar!$B:$D,3,0),"")*G49,"") -> 11116.133 | I49: 1600 | J49: =IFERROR(I49-H49,"") -> -9516.1333
B50: 5 | C50: =IFERROR(IF(B50=B49,C49,""),"") -> 44649 | D50: =IFERROR(MONTH(C50),"") -> 3 | E50: 4 | F50: Budín frutos secos | G50: 2 | H50: =IFERROR(IFERROR(VLOOKUP(E50,Bar!$B:$D,3,0),"")*G50,"") -> 13209.467 | I50: 1600 | J50: =IFERROR(I50-H50,"") -> -11609.467
B51: =IF(E51="","",B50+1) -> 6 | C51: 44653 | D51: =IFERROR(MONTH(C51),"") -> 4 | E51: 8 | F51: =IFERROR(VLOOKUP(E51,Bar!$B:$C,2,0),"") -> Cheese Cake Frutos rojos | G51: 17 | H51: =IFERROR(IFERROR(VLOOKUP(E51,Bar!$B:$D,3,0),"")*G51,"") -> 43208.14 | I51: 4590 | J51: =IFERROR(I51-H51,"") -> -38618.14
B52: 6 | C52: =IFERROR(IF(B52=B51,C51,""),"") -> 44653 | D52: =IFERROR(MONTH(C52),"") -> 4 | E52: 5 | F52: =IFERROR(VLOOKUP(E52,Bar!$B:$C,2,0),"") -> Lemon Pie | G52: 12 | H52: =IFERROR(IFERROR(VLOOKUP(E52,Bar!$B:$D,3,0),"")*G52,"") -> 18247.067 | I52: 3240 | J52: =IFERROR(I52-H52,"") -> -15007.067
B53: 6 | C53: =IFERROR(IF(B53=B52,C52,""),"") -> 44653 | D53: =IFERROR(MONTH(C53),"") -> 4 | E53: 10 | F53: =IFERROR(VLOOKUP(E53,Bar!$B:$C,2,0),"") -> Apple Crumble | G53: 12 | H53: =IFERROR(IFERROR(VLOOKUP(E53,Bar!$B:$D,3,0),"")*G53,"") -> 13412.233 | I53: 3240 | J53: =IFERROR(I53-H53,"") -> -10172.233
B54: 6 | C54: =IFERROR(IF(B54=B53,C53,""),"") -> 44653 | D54: =IFERROR(MONTH(C54),"") -> 4 | E54: 9 | F54: =IFERROR(VLOOKUP(E54,Bar!$B:$C,2,0),"") -> Torta Oreo | G54: 12 | H54: =IFERROR(IFERROR(VLOOKUP(E54,Bar!$B:$D,3,0),"")*G54,"") -> 35830 | I54: 3240 | J54: =IFERROR(I54-H54,"") -> -32590
B55: 6 | C55: =IFERROR(IF(B55=B54,C54,""),"") -> 44653 | D55: =IFERROR(MONTH(C55),"") -> 4 | E55: 11 | F55: =IFERROR(VLOOKUP(E55,Bar!$B:$C,2,0),"") -> Macarrons x12 | G55: 4 | H55: =IFERROR(IFERROR(VLOOKUP(E55,Bar!$B:$D,3,0),"")*G55,"") -> 7673.5 | I55: 2000 | J55: =IFERROR(I55-H55,"") -> -5673.5
B56: 6 | C56: =IFERROR(IF(B56=B55,C55,""),"") -> 44653 | D56: =IFERROR(MONTH(C56),"") -> 4 | E56: 1 | F56: =IFERROR(VLOOKUP(E56,Bar!$B:$C,2,0),"") -> Budín Limón | G56: 2 | H56: =IFERROR(IFERROR(VLOOKUP(E56,Bar!$B:$D,3,0),"")*G56,"") -> 11116.133 | I56: 1600 | J56: =IFERROR(I56-H56,"") -> -9516.1333
B57: 6 | C57: =IFERROR(IF(B57=B56,C56,""),"") -> 44653 | D57: =IFERROR(MONTH(C57),"") -> 4 | E57: 2 | F57: =IFERROR(VLOOKUP(E57,Bar!$B:$C,2,0),"") -> Budín zanahoria | G57: 2 | H57: =IFERROR(IFERROR(VLOOKUP(E57,Bar!$B:$D,3,0),"")*G57,"") -> 11116.133 | I57: 1600 | J57: =IFERROR(I57-H57,"") -> -9516.1333
B58: 6 | C58: =IFERROR(IF(B58=B57,C57,""),"") -> 44653 | D58: =IFERROR(MONTH(C58),"") -> 4 | E58: 4 | F58: =IFERROR(VLOOKUP(E58,Bar!$B:$C,2,0),"") -> Budín frutos secos | G58: 2 | H58: =IFERROR(IFERROR(VLOOKUP(E58,Bar!$B:$D,3,0),"")*G58,"") -> 13209.467 | I58: 1600 | J58: =IFERROR(I58-H58,"") -> -11609.467
B59: 6 | C59: =IFERROR(IF(B59=B58,C58,""),"") -> 44653 | D59: =IFERROR(MONTH(C59),"") -> 4 | E59: 7 | F59: =IFERROR(VLOOKUP(E59,Bar!$B:$C,2,0),"") -> Chocotorta | G59: 17 | H59: =IFERROR(IFERROR(VLOOKUP(E59,Bar!$B:$D,3,0),"")*G59,"") -> 47893.452 | I59: 4590 | J59: =IFERROR(I59-H59,"") -> -43303.452
B60: 7 | C60: 44671 | D60: =IFERROR(MONTH(C60),"") -> 4 | E60: 8 | F60: =IFERROR(VLOOKUP(E60,Bar!$B:$C,2,0),"") -> Cheese Cake Frutos rojos | G60: 18 | H60: =IFERROR(IFERROR(VLOOKUP(E60,Bar!$B:$D,3,0),"")*G60,"") -> 45749.796 | I60: 4860 | J60: =IFERROR(I60-H60,"") -> -40889.796
B61: 7 | C61: 44671 | D61: =IFERROR(MONTH(C61),"") -> 4 | E61: 5 | F61: =IFERROR(VLOOKUP(E61,Bar!$B:$C,2,0),"") -> Lemon Pie | G61: 18 | H61: =IFERROR(IFERROR(VLOOKUP(E61,Bar!$B:$D,3,0),"")*G61,"") -> 27370.6 | I61: 4860 | J61: =IFERROR(I61-H61,"") -> -22510.6
B62: 7 | C62: 44671 | D62: 4 | E62: 7 | F62: =IFERROR(VLOOKUP(E62,Bar!$B:$C,2,0),"") -> Chocotorta | G62: 18 | H62: =IFERROR(IFERROR(VLOOKUP(E62,Bar!$B:$D,3,0),"")*G62,"") -> 50710.714 | I62: 4860 | J62: =IFERROR(I62-H62,"") -> -45850.714
B63: 7 | C63: 44671 | D63: =IFERROR(MONTH(C63),"") -> 4 | E63: 9 | F63: =IFERROR(VLOOKUP(E63,Bar!$B:$C,2,0),"") -> Torta Oreo | G63: 18 | H63: =IFERROR(IFERROR(VLOOKUP(E63,Bar!$B:$D,3,0),"")*G63,"") -> 53745 | I63: 4860 | J63: =IFERROR(I63-H63,"") -> -48885
B64: 7 | C64: 44671 | D64: =IFERROR(MONTH(C64),"") -> 4 | E64: 6 | F64: =IFERROR(VLOOKUP(E64,Bar!$B:$C,2,0),"") -> Browrnie Oreo | G64: 18 | H64: =IFERROR(IFERROR(VLOOKUP(E64,Bar!$B:$D,3,0),"")*G64,"") -> 43719.983 | I64: 4860 | J64: =IFERROR(I64-H64,"") -> -38859.983
B65: 7 | C65: 44671 | D65: =IFERROR(MONTH(C65),"") -> 4 | E65: 1 | F65: =IFERROR(VLOOKUP(E65,Bar!$B:$C,2,0),"") -> Budín Limón | G65: 2 | H65: =IFERROR(IFERROR(VLOOKUP(E65,Bar!$B:$D,3,0),"")*G65,"") -> 11116.133 | I65: 1600 | J65: =IFERROR(I65-H65,"") -> -9516.1333
B66: 7 | C66: 44671 | D66: =IFERROR(MONTH(C66),"") -> 4 | E66: 2 | F66: =IFERROR(VLOOKUP(E66,Bar!$B:$C,2,0),"") -> Budín zanahoria | G66: 2 | H66: =IFERROR(IFERROR(VLOOKUP(E66,Bar!$B:$D,3,0),"")*G66,"") -> 11116.133 | I66: 1600 | J66: =IFERROR(I66-H66,"") -> -9516.1333
B67: 7 | C67: 44671 | D67: =IFERROR(MONTH(C67),"") -> 4 | E67: 4 | F67: =IFERROR(VLOOKUP(E67,Bar!$B:$C,2,0),"") -> Budín frutos secos | G67: 2 | H67: =IFERROR(IFERROR(VLOOKUP(E67,Bar!$B:$D,3,0),"")*G67,"") -> 13209.467 | I67: 1600 | J67: =IFERROR(I67-H67,"") -> -11609.467
B68: 7 | C68: 44671 | D68: =IFERROR(MONTH(C68),"") -> 4 | E68: 3 | F68: =IFERROR(VLOOKUP(E68,Bar!$B:$C,2,0),"") -> Budín marmolado | G68: 2 | H68: =IFERROR(IFERROR(VLOOKUP(E68,Bar!$B:$D,3,0),"")*G68,"") -> 11116.133 | I68: 1600 | J68: =IFERROR(I68-H68,"") -> -9516.1333
B69: 8 | C69: 44678 | D69: =IFERROR(MONTH(C69),"") -> 4 | E69: 8 | F69: =IFERROR(VLOOKUP(E69,Bar!$B:$C,2,0),"") -> Cheese Cake Frutos rojos | G69: 18 | H69: =IFERROR(IFERROR(VLOOKUP(E69,Bar!$B:$D,3,0),"")*G69,"") -> 45749.796 | I69: 4860 | J69: =IFERROR(I69-H69,"") -> -40889.796
B70: 8 | C70: =IFERROR(IF(B70=B69,C69,""),"") -> 44678 | D70: =IFERROR(MONTH(C70),"") -> 4 | E70: 6 | F70: =IFERROR(VLOOKUP(E70,Bar!$B:$C,2,0),"") -> Browrnie Oreo | G70: 18 | H70: =IFERROR(IFERROR(VLOOKUP(E70,Bar!$B:$D,3,0),"")*G70,"") -> 43719.983 | I70: 4860 | J70: =IFERROR(I70-H70,"") -> -38859.983
B71: 8 | C71: =IFERROR(IF(B71=B70,C70,""),"") -> 44678 | D71: =IFERROR(MONTH(C71),"") -> 4 | E71: 7 | F71: =IFERROR(VLOOKUP(E71,Bar!$B:$C,2,0),"") -> Chocotorta | G71: 18 | H71: =IFERROR(IFERROR(VLOOKUP(E71,Bar!$B:$D,3,0),"")*G71,"") -> 50710.714 | I71: 4860 | J71: =IFERROR(I71-H71,"") -> -45850.714
B72: 8 | C72: =IFERROR(IF(B72=B71,C71,""),"") -> 44678 | D72: =IFERROR(MONTH(C72),"") -> 4 | E72: 9 | F72: =IFERROR(VLOOKUP(E72,Bar!$B:$C,2,0),"") -> Torta Oreo | G72: 18 | H72: =IFERROR(IFERROR(VLOOKUP(E72,Bar!$B:$D,3,0),"")*G72,"") -> 53745 | I72: 4860 | J72: =IFERROR(I72-H72,"") -> -48885
B73: 8 | C73: =IFERROR(IF(B73=B72,C72,""),"") -> 44678 | D73: =IFERROR(MONTH(C73),"") -> 4 | E73: 10 | F73: =IFERROR(VLOOKUP(E73,Bar!$B:$C,2,0),"") -> Apple Crumble | G73: 12 | H73: =IFERROR(IFERROR(VLOOKUP(E73,Bar!$B:$D,3,0),"")*G73,"") -> 13412.233 | I73: 3240 | J73: =IFERROR(I73-H73,"") -> -10172.233
B74: 8 | C74: =IFERROR(IF(B74=B73,C73,""),"") -> 44678 | D74: =IFERROR(MONTH(C74),"") -> 4 | E74: 5 | F74: =IFERROR(VLOOKUP(E74,Bar!$B:$C,2,0),"") -> Lemon Pie | G74: 12 | H74: =IFERROR(IFERROR(VLOOKUP(E74,Bar!$B:$D,3,0),"")*G74,"") -> 18247.067 | I74: 3240 | J74: =IFERROR(I74-H74,"") -> -15007.067
B75: 8 | C75: =IFERROR(IF(B75=B74,C74,""),"") -> 44678 | D75: =IFERROR(MONTH(C75),"") -> 4 | F75: =IFERROR(VLOOKUP(E75,Bar!$B:$C,2,0),"") | H75: =IFERROR(IFERROR(VLOOKUP(E75,Bar!$B:$D,3,0),"")*G75,"") -> 0 | J75: =IFERROR(I75-H75,"") -> 0
B76: =IF(E76="","",B75+1) -> 9 | C76: 44685 | D76: =IFERROR(MONTH(C76),"") -> 5 | E76: 8 | F76: =IFERROR(VLOOKUP(E76,Bar!$B:$C,2,0),"") -> Cheese Cake Frutos rojos | G76: 17 | H76: =IFERROR(IFERROR(VLOOKUP(E76,Bar!$B:$D,3,0),"")*G76,"") -> 43208.14 | I76: 4590 | J76: =IFERROR(I76-H76,"") -> -38618.14
B77: 9 | C77: 44685 | D77: =IFERROR(MONTH(C77),"") -> 5 | E77: 5 | F77: =IFERROR(VLOOKUP(E77,Bar!$B:$C,2,0),"") -> Lemon Pie | G77: 17 | H77: =IFERROR(IFERROR(VLOOKUP(E77,Bar!$B:$D,3,0),"")*G77,"") -> 25850.011 | I77: 4590 | J77: =IFERROR(I77-H77,"") -> -21260.011
B78: 9 | C78: 44685 | D78: 5 | E78: 7 | F78: =IFERROR(VLOOKUP(E78,Bar!$B:$C,2,0),"") -> Chocotorta | G78: 17 | H78: =IFERROR(IFERROR(VLOOKUP(E78,Bar!$B:$D,3,0),"")*G78,"") -> 47893.452 | I78: 4590 | J78: =IFERROR(I78-H78,"") -> -43303.452
B79: 9 | C79: 44685 | D79: 5 | E79: 9 | F79: =IFERROR(VLOOKUP(E79,Bar!$B:$C,2,0),"") -> Torta Oreo | G79: 12 | H79: =IFERROR(IFERROR(VLOOKUP(E79,Bar!$B:$D,3,0),"")*G79,"") -> 35830 | I79: 3240 | J79: =IFERROR(I79-H79,"") -> -32590
B80: 9 | C80: 44685 | D80: =IFERROR(MONTH(C80),"") -> 5 | E80: 6 | F80: =IFERROR(VLOOKUP(E80,Bar!$B:$C,2,0),"") -> Browrnie Oreo | G80: 12 | H80: =IFERROR(IFERROR(VLOOKUP(E80,Bar!$B:$D,3,0),"")*G80,"") -> 29146.656 | I80: 3240 | J80: =IFERROR(I80-H80,"") -> -25906.656
B81: 9 | C81: 44686 | D81: =IFERROR(MONTH(C81),"") -> 5 | E81: 10 | F81: =IFERROR(VLOOKUP(E81,Bar!$B:$C,2,0),"") -> Apple Crumble | G81: 12 | H81: =IFERROR(IFERROR(VLOOKUP(E81,Bar!$B:$D,3,0),"")*G81,"") -> 13412.233 | I81: 3240 | J81: =IFERROR(I81-H81,"") -> -10172.233
B82: 9 | C82: 44685 | D82: =IFERROR(MONTH(C82),"") -> 5 | E82: 11 | F82: =IFERROR(VLOOKUP(E82,Bar!$B:$C,2,0),"") -> Macarrons x12 | G82: 2 | H82: =IFERROR(IFERROR(VLOOKUP(E82,Bar!$B:$D,3,0),"")*G82,"") -> 3836.75 | I82: 1000 | J82: =IFERROR(I82-H82,"") -> -2836.75
B83: 10 | C83: 44692 | D83: =IFERROR(MONTH(C83),"") -> 5 | E83: 8 | F83: =IFERROR(VLOOKUP(E83,Bar!$B:$C,2,0),"") -> Cheese Cake Frutos rojos | G83: 20 | H83: =IFERROR(IFERROR(VLOOKUP(E83,Bar!$B:$D,3,0),"")*G83,"") -> 50833.106 | I83: 5400 | J83: =IFERROR(I83-H83,"") -> -45433.106
B84: 10 | C84: =IFERROR(IF(B84=B83,C83,""),"") -> 44692 | D84: =IFERROR(MONTH(C84),"") -> 5 | E84: 5 | F84: =IFERROR(VLOOKUP(E84,Bar!$B:$C,2,0),"") -> Lemon Pie | G84: 12 | H84: =IFERROR(IFERROR(VLOOKUP(E84,Bar!$B:$D,3,0),"")*G84,"") -> 18247.067 | I84: 3240 | J84: =IFERROR(I84-H84,"") -> -15007.067
B85: 10 | C85: =IFERROR(IF(B85=B84,C84,""),"") -> 44692 | D85: =IFERROR(MONTH(C85),"") -> 5 | E85: 6 | F85: =IFERROR(VLOOKUP(E85,Bar!$B:$C,2,0),"") -> Browrnie Oreo | G85: 12 | H85: =IFERROR(IFERROR(VLOOKUP(E85,Bar!$B:$D,3,0),"")*G85,"") -> 29146.656 | I85: 3240 | J85: =IFERROR(I85-H85,"") -> -25906.656
B86: 10 | C86: =IFERROR(IF(B86=B85,C85,""),"") -> 44692 | D86: =IFERROR(MONTH(C86),"") -> 5 | E86: 9 | F86: =IFERROR(VLOOKUP(E86,Bar!$B:$C,2,0),"") -> Torta Oreo | G86: 17 | H86: =IFERROR(IFERROR(VLOOKUP(E86,Bar!$B:$D,3,0),"")*G86,"") -> 50759.167 | I86: 4590 | J86: =IFERROR(I86-H86,"") -> -46169.167
B87: 10 | C87: =IFERROR(IF(B87=B86,C86,""),"") -> 44692 | D87: =IFERROR(MONTH(C87),"") -> 5 | E87: 10 | F87: =IFERROR(VLOOKUP(E87,Bar!$B:$C,2,0),"") -> Apple Crumble | G87: 17 | H87: =IFERROR(IFERROR(VLOOKUP(E87,Bar!$B:$D,3,0),"")*G87,"") -> 19000.664 | I87: 4590 | J87: =IFERROR(I87-H87,"") -> -14410.664
B88: 10 | C88: =IFERROR(IF(B88=B87,C87,""),"") -> 44692 | D88: =IFERROR(MONTH(C88),"") -> 5 | E88: 11 | F88: =IFERROR(VLOOKUP(E88,Bar!$B:$C,2,0),"") -> Macarrons x12 | G88: 2 | H88: =IFERROR(IFERROR(VLOOKUP(E88,Bar!$B:$D,3,0),"")*G88,"") -> 3836.75 | I88: 1000 | J88: =IFERROR(I88-H88,"") -> -2836.75
B89: 11 | C89: 44700 | D89: =IFERROR(MONTH(C89),"") -> 5 | E89: 8 | F89: =IFERROR(VLOOKUP(E89,Bar!$B:$C,2,0),"") -> Cheese Cake Frutos rojos | G89: 24 | H89: =IFERROR(IFERROR(VLOOKUP(E89,Bar!$B:$D,3,0),"")*G89,"") -> 60999.727 | I89: 6480 | J89: =IFERROR(I89-H89,"") -> -54519.727
B90: 11 | C90: =IFERROR(IF(B90=B89,C89,""),"") -> 44700 | D90: =IFERROR(MONTH(C90),"") -> 5 | E90: 5 | F90: =IFERROR(VLOOKUP(E90,Bar!$B:$C,2,0),"") -> Lemon Pie | G90: 24 | H90: =IFERROR(IFERROR(VLOOKUP(E90,Bar!$B:$D,3,0),"")*G90,"") -> 36494.133 | I90: 6480 | J90: =IFERROR(I90-H90,"") -> -30014.133
B91: 11 | C91: =IFERROR(IF(B91=B90,C90,""),"") -> 44700 | D91: =IFERROR(MONTH(C91),"") -> 5 | E91: 6 | F91: =IFERROR(VLOOKUP(E91,Bar!$B:$C,2,0),"") -> Browrnie Oreo | G91: 24 | H91: =IFERROR(IFERROR(VLOOKUP(E91,Bar!$B:$D,3,0),"")*G91,"") -> 58293.311 | I91: 6480 | J91: =IFERROR(I91-H91,"") -> -51813.311
B92: 11 | C92: =IFERROR(IF(B92=B91,C91,""),"") -> 44700 | D92: =IFERROR(MONTH(C92),"") -> 5 | E92: 7 | F92: =IFERROR(VLOOKUP(E92,Bar!$B:$C,2,0),"") -> Chocotorta | G92: 24 | H92: =IFERROR(IFERROR(VLOOKUP(E92,Bar!$B:$D,3,0),"")*G92,"") -> 67614.286 | I92: 6480 | J92: =IFERROR(I92-H92,"") -> -61134.286
B93: 11 | C93: =IFERROR(IF(B93=B92,C92,""),"") -> 44700 | D93: =IFERROR(MONTH(C93),"") -> 5 | E93: 9 | F93: =IFERROR(VLOOKUP(E93,Bar!$B:$C,2,0),"") -> Torta Oreo | G93: 24 | H93: =IFERROR(IFERROR(VLOOKUP(E93,Bar!$B:$D,3,0),"")*G93,"") -> 71660 | I93: 6480 | J93: =IFERROR(I93-H93,"") -> -65180
B94: 11 | C94: =IFERROR(IF(B94=B93,C93,""),"") -> 44700 | D94: =IFERROR(MONTH(C94),"") -> 5 | E94: 10 | F94: =IFERROR(VLOOKUP(E94,Bar!$B:$C,2,0),"") -> Apple Crumble | G94: 24 | H94: =IFERROR(IFERROR(VLOOKUP(E94,Bar!$B:$D,3,0),"")*G94,"") -> 26824.467 | I94: 6480 | J94: =IFERROR(I94-H94,"") -> -20344.467
B95: 11 | C95: =IFERROR(IF(B95=B94,C94,""),"") -> 44700 | D95: =IFERROR(MONTH(C95),"") -> 5 | E95: 11 | F95: =IFERROR(VLOOKUP(E95,Bar!$B:$C,2,0),"") -> Macarrons x12 | G95: 2 | H95: =IFERROR(IFERROR(VLOOKUP(E95,Bar!$B:$D,3,0),"")*G95,"") -> 3836.75 | I95: 1000 | J95: =IFERROR(I95-H95,"") -> -2836.75
B96: 12 | C96: 44707 | D96: =IFERROR(MONTH(C96),"") -> 5 | E96: 8 | F96: =IFERROR(VLOOKUP(E96,Bar!$B:$C,2,0),"") -> Cheese Cake Frutos rojos | G96: 20 | H96: =IFERROR(IFERROR(VLOOKUP(E96,Bar!$B:$D,3,0),"")*G96,"") -> 50833.106 | I96: 5400 | J96: =IFERROR(I96-H96,"") -> -45433.106
B97: 12 | C97: =IFERROR(IF(B97=B96,C96,""),"") -> 44707 | D97: =IFERROR(MONTH(C97),"") -> 5 | E97: 6 | F97: =IFERROR(VLOOKUP(E97,Bar!$B:$C,2,0),"") -> Browrnie Oreo | G97: 12 | H97: =IFERROR(IFERROR(VLOOKUP(E97,Bar!$B:$D,3,0),"")*G97,"") -> 29146.656 | I97: 3240 | J97: =IFERROR(I97-H97,"") -> -25906.656
B98: 12 | C98: =IFERROR(IF(B98=B97,C97,""),"") -> 44707 | D98: =IFERROR(MONTH(C98),"") -> 5 | E98: 9 | F98: =IFERROR(VLOOKUP(E98,Bar!$B:$C,2,0),"") -> Torta Oreo | G98: 17 | H98: =IFERROR(IFERROR(VLOOKUP(E98,Bar!$B:$D,3,0),"")*G98,"") -> 50759.167 | I98: 4590 | J98: =IFERROR(I98-H98,"") -> -46169.167
B99: 12 | C99: =IFERROR(IF(B99=B98,C98,""),"") -> 44707 | D99: =IFERROR(MONTH(C99),"") -> 5 | E99: 7 | F99: =IFERROR(VLOOKUP(E99,Bar!$B:$C,2,0),"") -> Chocotorta | G99: 17 | H99: =IFERROR(IFERROR(VLOOKUP(E99,Bar!$B:$D,3,0),"")*G99,"") -> 47893.452 | I99: 4590 | J99: =IFERROR(I99-H99,"") -> -43303.452
B100: 12 | C100: =IFERROR(IF(B100=B99,C99,""),"") -> 44707 | D100: =IFERROR(MONTH(C100),"") -> 5 | E100: 10 | F100: =IFERROR(VLOOKUP(E100,Bar!$B:$C,2,0),"") -> Apple Crumble | G100: 12 | H100: =IFERROR(IFERROR(VLOOKUP(E100,Bar!$B:$D,3,0),"")*G100,"") -> 13412.233 | I100: 3240 | J100: =IFERROR(I100-H100,"") -> -10172.233
B101: 12 | C101: =IFERROR(IF(B101=B100,C100,""),"") -> 44707 | D101: =IFERROR(MONTH(C101),"") -> 5 | E101: 5 | F101: =IFERROR(VLOOKUP(E101,Bar!$B:$C,2,0),"") -> Lemon Pie | G101: 17 | H101: =IFERROR(IFERROR(VLOOKUP(E101,Bar!$B:$D,3,0),"")*G101,"") -> 25850.011 | I101: 4590 | J101: =IFERROR(I101-H101,"") -> -21260.011
B102: 12 | C102: =IFERROR(IF(B102=B101,C101,""),"") -> 44707 | D102: =IFERROR(MONTH(C102),"") -> 5 | E102: 11 | F102: =IFERROR(VLOOKUP(E102,Bar!$B:$C,2,0),"") -> Macarrons x12 | G102: 1 | H102: =IFERROR(IFERROR(VLOOKUP(E102,Bar!$B:$D,3,0),"")*G102,"") -> 1918.375 | I102: 500 | J102: =IFERROR(I102-H102,"") -> -1418.375
...

Sheet Rendimiento mensual
C3: =SUM(C6:C17) -> 27 | D3: =SUM(D6:D17) -> 1036250 | E3: =SUM(E6:E17) -> 332809.9 | F3: =SUM(F6:F17) -> 703440.1 | G3: =IFERROR(F3/D3,0) -> 0.67883242
B5: Mes | C5: Q Pedidos | D5: Ventas | E5: Costo | F5: Margen | G5: Margen %
B6: 1 | C6: =IFERROR(SUMIF('Ventas Bar'!D:D,'Rendimiento mensual'!B6,'Ventas Bar'!D:D)/COUNTIF('Ventas Bar'!D:D,'Rendimiento mensual'!B6),0) -> 0 | D6: =SUMIF('Ventas Bar'!$D:$D,'Rendimiento mensual'!B6,'Ventas Bar'!I:I) -> 0 | E6: =SUMIF('Pedidos insumos'!$D:$D,'Rendimiento mensual'!B6,'Pedidos insumos'!E:E) -> 0 | F6: =D6-E6 -> 0 | G6: =IFERROR(F6/D6,0) -> 0
B7: =B6+1 -> 2 | C7: =IFERROR(SUMIF('Ventas Bar'!D:D,'Rendimiento mensual'!B7,'Ventas Bar'!D:D)/COUNTIF('Ventas Bar'!D:D,'Rendimiento mensual'!B7),0) -> 0 | D7: =SUMIF('Ventas Bar'!$D:$D,'Rendimiento mensual'!B7,'Ventas Bar'!I:I) -> 0 | E7: =SUMIF('Pedidos insumos'!$D:$D,'Rendimiento mensual'!B7,'Pedidos insumos'!E:E) -> 0 | F7: =D7-E7 -> 0 | G7: =IFERROR(F7/D7,0) -> 0
B8: =B7+1 -> 3 | C8: 5 | D8: =SUMIF('Ventas Bar'!$D:$D,'Rendimiento mensual'!B8,'Ventas Bar'!I:I) -> 141960 | E8: =SUMIF('Pedidos insumos'!$D:$D,'Rendimiento mensual'!B8,'Pedidos insumos'!E:E) -> 31969 | F8: =D8-E8 -> 109991 | G8: =IFERROR(F8/D8,0) -> 0.77480276
B9: =B8+1 -> 4 | C9: 3 | D9: =SUMIF('Ventas Bar'!$D:$D,'Rendimiento mensual'!B9,'Ventas Bar'!I:I) -> 82320 | E9: =SUMIF('Pedidos insumos'!$D:$D,'Rendimiento mensual'!B9,'Pedidos insumos'!E:E) -> 23123.15 | F9: =D9-E9 -> 59196.85 | G9: =IFERROR(F9/D9,0) -> 0.71910654
B10: =B9+1 -> 5 | C10: 4 | D10: =SUMIF('Ventas Bar'!$D:$D,'Rendimiento mensual'!B10,'Ventas Bar'!I:I) -> 112580 | E10: =SUMIF('Pedidos insumos'!$D:$D,'Rendimiento mensual'!B10,'Pedidos insumos'!E:E) -> 35088 | F10: =D10-E10 -> 77492 | G10: =IFERROR(F10/D10,0) -> 0.6883283
B11: =B10+1 -> 6 | C11: 5 | D11: =SUMIF('Ventas Bar'!$D:$D,'Rendimiento mensual'!B11,'Ventas Bar'!I:I) -> 43250 | E11: =SUMIF('Pedidos insumos'!$D:$D,'Rendimiento mensual'!B11,'Pedidos insumos'!E:E) -> 27200 | F11: =D11-E11 -> 16050 | G11: =IFERROR(F11/D11,0) -> 0.37109827
B12: =B11+1 -> 7 | C12: 10 | D12: =SUMIF('Ventas Bar'!$D:$D,'Rendimiento mensual'!B12,'Ventas Bar'!I:I)+SUMIFS('Vituca Cakes'!L:L,'Vituca Cakes'!$E:$E,'Rendimiento mensual'!B12,'Vituca Cakes'!$D:$D,2022) -> 268490 | E12: =SUMIF('Pedidos insumos'!$D:$D,'Rendimiento mensual'!B12,'Pedidos insumos'!E:E) -> 104789.75 | F12: =D12-E12 -> 163700.25 | G12: =IFERROR(F12/D12,0) -> 0.60970707
B13: =B12+1 -> 8 | C13: 0 | D13: =SUMIF('Ventas Bar'!$D:$D,'Rendimiento mensual'!B13,'Ventas Bar'!I:I)+SUMIFS('Vituca Cakes'!L:L,'Vituca Cakes'!$E:$E,'Rendimiento mensual'!B13,'Vituca Cakes'!$D:$D,2022) -> 214690 | E13: =SUMIF('Pedidos insumos'!$D:$D,'Rendimiento mensual'!B13,'Pedidos insumos'!E:E) -> 37700 | F13: =D13-E13 -> 176990 | G13: =IFERROR(F13/D13,0) -> 0.82439797
B14: =B13+1 -> 9 | C14: 0 | D14: =SUMIF('Ventas Bar'!$D:$D,'Rendimiento mensual'!B14,'Ventas Bar'!I:I)+SUMIFS('Vituca Cakes'!L:L,'Vituca Cakes'!$E:$E,'Rendimiento mensual'!B14,'Vituca Cakes'!$D:$D,2022) -> 164660 | E14: =SUMIF('Pedidos insumos'!$D:$D,'Rendimiento mensual'!B14,'Pedidos insumos'!E:E) -> 72940 | F14: =D14-E14 -> 91720 | G14: =IFERROR(F14/D14,0) -> 0.5570266
B15: =B14+1 -> 10 | C15: 0 | D15: =SUMIF('Ventas Bar'!$D:$D,'Rendimiento mensual'!B15,'Ventas Bar'!I:I)+SUMIFS('Vituca Cakes'!L:L,'Vituca Cakes'!$E:$E,'Rendimiento mensual'!B15,'Vituca Cakes'!$D:$D,2022) -> 8300 | E15: =SUMIF('Pedidos insumos'!$D:$D,'Rendimiento mensual'!B15,'Pedidos insumos'!E:E) -> 0 | F15: =D15-E15 -> 8300 | G15: =IFERROR(F15/D15,0) -> 1
B16: =B15+1 -> 11 | C16: 0 | D16: =SUMIF('Ventas Bar'!$D:$D,'Rendimiento mensual'!B16,'Ventas Bar'!I:I)+SUMIFS('Vituca Cakes'!L:L,'Vituca Cakes'!$E:$E,'Rendimiento mensual'!B16,'Vituca Cakes'!$D:$D,2022) -> 0 | E16: =SUMIF('Pedidos insumos'!$D:$D,'Rendimiento mensual'!B16,'Pedidos insumos'!E:E) -> 0 | F16: =D16-E16 -> 0 | G16: =IFERROR(F16/D16,0) -> 0
B17: =B16+1 -> 12 | C17: 0 | D17: =SUMIF('Ventas Bar'!$D:$D,'Rendimiento mensual'!B17,'Ventas Bar'!I:I)+SUMIFS('Vituca Cakes'!L:L,'Vituca Cakes'!$E:$E,'Rendimiento mensual'!B17,'Vituca Cakes'!$D:$D,2022) -> 0 | E17: =SUMIF('Pedidos insumos'!$D:$D,'Rendimiento mensual'!B17,'Pedidos insumos'!E:E) -> 0 | F17: =D17-E17 -> 0 | G17: =IFERROR(F17/D17,0) -> 0
B20: Promedio por pedido | D20: =D3/MAX('Ventas Bar'!$B:$B) -> 18840.909 | E20: =E3/MAX('Ventas Bar'!$B:$B) -> 6051.0891 | F20: =F3/MAX('Ventas Bar'!$B:$B) -> 12789.82 | G20: =IFERROR(F20/D20,0) -> 0.67883242

Sheet Pedidos insumos
B3: Nro. | C3: Fecha | D3: Mes | E3: Monto
B4: 1 | C4: 44635 | D4: =IF(IFERROR(MONTH(C4),"")=1,"",IFERROR(MONTH(C4),"")) -> 3 | E4: 11000
B5: =B4+1 -> 2 | C5: 44635 | D5: =IF(IFERROR(MONTH(C5),"")=1,"",IFERROR(MONTH(C5),"")) -> 3 | E5: 11000
B6: =B5+1 -> 3 | C6: 44649 | D6: =IF(IFERROR(MONTH(C6),"")=1,"",IFERROR(MONTH(C6),"")) -> 3 | E6: 9969
B7: =B6+1 -> 4 | C7: 44652 | D7: =IF(IFERROR(MONTH(C7),"")=1,"",IFERROR(MONTH(C7),"")) -> 4 | E7: =4222.15+1350+1850+1685 -> 9107.15
B8: =B7+1 -> 5 | C8: 44669 | D8: =IF(IFERROR(MONTH(C8),"")=1,"",IFERROR(MONTH(C8),"")) -> 4 | E8: 14016
B9: =B8+1 -> 6 | C9: 44685 | D9: =IF(IFERROR(MONTH(C9),"")=1,"",IFERROR(MONTH(C9),"")) -> 5 | E9: 14738
B10: =B9+1 -> 7 | C10: 44697 | D10: =IF(IFERROR(MONTH(C10),"")=1,"",IFERROR(MONTH(C10),"")) -> 5 | E10: 20350
B11: =B10+1 -> 8 | C11: 44713 | D11: =IF(IFERROR(MONTH(C11),"")=1,"",IFERROR(MONTH(C11),"")) -> 6 | E11: 27200
B12: =B11+1 -> 9 | C12: 44748 | D12: =IF(IFERROR(MONTH(C12),"")=1,"",IFERROR(MONTH(C12),"")) -> 7 | E12: 21880
B13: =B12+1 -> 10 | C13: 44762 | D13: =IF(IFERROR(MONTH(C13),"")=1,"",IFERROR(MONTH(C13),"")) -> 7 | E13: 21460
B14: =B13+1 -> 11 | C14: 44762 | D14: 7 | E14: 300
B15: =B14+1 -> 12 | C15: 44762 | D15: 7 | E15: 3270
B16: =B15+1 -> 13 | C16: 44762 | D16: =IF(IFERROR(MONTH(C16),"")=1,"",IFERROR(MONTH(C16),"")) -> 7 | E16: 790
B17: =B16+1 -> 14 | C17: 44762 | D17: =IF(IFERROR(MONTH(C17),"")=1,"",IFERROR(MONTH(C17),"")) -> 7 | E17: 1510
B18: =B17+1 -> 15 | C18: 44762 | D18: 7 | E18: 93
B19: =B18+1 -> 16 | C19: 44762 | D19: =IF(IFERROR(MONTH(C19),"")=1,"",IFERROR(MONTH(C19),"")) -> 7 | E19: 350
B20: =B19+1 -> 17 | C20: 44762 | D20: =IF(IFERROR(MONTH(C20),"")=1,"",IFERROR(MONTH(C20),"")) -> 7 | E20: 830
B21: =B20+1 -> 18 | C21: 44764 | D21: =IF(IFERROR(MONTH(C21),"")=1,"",IFERROR(MONTH(C21),"")) -> 7 | E21: 6110
B22: =B21+1 -> 19 | C22: 44767 | D22: =IF(IFERROR(MONTH(C22),"")=1,"",IFERROR(MONTH(C22),"")) -> 7 | E22: =45200 -> 45200
B23: =B22+1 -> 20 | C23: 44767 | D23: =IF(IFERROR(MONTH(C23),"")=1,"",IFERROR(MONTH(C23),"")) -> 7 | E23: 1946.75
B24: =B23+1 -> 21 | C24: 44767 | D24: =IF(IFERROR(MONTH(C24),"")=1,"",IFERROR(MONTH(C24),"")) -> 7 | E24: 1050
B25: =B24+1 -> 22 | C25: 44790 | D25: =IF(IFERROR(MONTH(C25),"")=1,"",IFERROR(MONTH(C25),"")) -> 8 | E25: 27350
B26: =B25+1 -> 23 | C26: 44790 | D26: =IF(IFERROR(MONTH(C26),"")=1,"",IFERROR(MONTH(C26),"")) -> 8 | E26: =550*2 -> 1100
B27: =B26+1 -> 24 | C27: 44790 | D27: =IF(IFERROR(MONTH(C27),"")=1,"",IFERROR(MONTH(C27),"")) -> 8 | E27: 2750
B28: =B27+1 -> 25 | C28: 44791 | D28: =IF(IFERROR(MONTH(C28),"")=1,"",IFERROR(MONTH(C28),"")) -> 8 | E28: 2000
B29: =B28+1 -> 26 | C29: 44804 | D29: =IF(IFERROR(MONTH(C29),"")=1,"",IFERROR(MONTH(C29),"")) -> 8 | E29: 4500
B30: =B29+1 -> 27 | C30: 44810 | D30: =IF(IFERROR(MONTH(C30),"")=1,"",IFERROR(MONTH(C30),"")) -> 9 | E30: 22580
B31: =B30+1 -> 28 | C31: 44810 | D31: =IF(IFERROR(MONTH(C31),"")=1,"",IFERROR(MONTH(C31),"")) -> 9 | E31: 2550
B32: =B31+1 -> 29 | C32: 44820 | D32: =IF(IFERROR(MONTH(C32),"")=1,"",IFERROR(MONTH(C32),"")) -> 9 | E32: 42000
B33: =B32+1 -> 30 | C33: 44820 | D33: =IF(IFERROR(MONTH(C33),"")=1,"",IFERROR(MONTH(C33),"")) -> 9 | E33: 2460
B34: =B33+1 -> 31 | C34: 44830 | D34: =IF(IFERROR(MONTH(C34),"")=1,"",IFERROR(MONTH(C34),"")) -> 9 | E34: 3350
B35: =B34+1 -> 32 | D35: =IF(IFERROR(MONTH(C35),"")=1,"",IFERROR(MONTH(C35),"")) -> 12
B36: =B35+1 -> 33 | D36: =IF(IFERROR(MONTH(C36),"")=1,"",IFERROR(MONTH(C36),"")) -> 12
B37: =B36+1 -> 34 | D37: =IF(IFERROR(MONTH(C37),"")=1,"",IFERROR(MONTH(C37),"")) -> 12
B38: =B37+1 -> 35 | D38: =IF(IFERROR(MONTH(C38),"")=1,"",IFERROR(MONTH(C38),"")) -> 12
B39: =B38+1 -> 36 | D39: =IF(IFERROR(MONTH(C39),"")=1,"",IFERROR(MONTH(C39),"")) -> 12
B40: =B39+1 -> 37 | D40: =IF(IFERROR(MONTH(C40),"")=1,"",IFERROR(MONTH(C40),"")) -> 12
B41: =B40+1 -> 38 | D41: =IF(IFERROR(MONTH(C41),"")=1,"",IFERROR(MONTH(C41),"")) -> 12
B42: =B41+1 -> 39 | D42: =IF(IFERROR(MONTH(C42),"")=1,"",IFERROR(MONTH(C42),"")) -> 12
B43: =B42+1 -> 40 | D43: =IF(IFERROR(MONTH(C43),"")=1,"",IFERROR(MONTH(C43),"")) -> 12
B44: =B43+1 -> 41 | D44: =IF(IFERROR(MONTH(C44),"")=1,"",IFERROR(MONTH(C44),"")) -> 12
B45: =B44+1 -> 42 | D45: =IF(IFERROR(MONTH(C45),"")=1,"",IFERROR(MONTH(C45),"")) -> 12
B46: =B45+1 -> 43 | D46: =IF(IFERROR(MONTH(C46),"")=1,"",IFERROR(MONTH(C46),"")) -> 12
... B103: =B102+1 -> 100 | D103: =IF(IFERROR(MONTH(C103),"")=1,"",IFERROR(MONTH(C103),"")) -> 12
